Workbook

Sheet ФАКТ 2024
E1: 01.2024 | F1: 02.2024 | G1: 03.2024 | H1: 04.2024 | I1: 05.2024 | J1: 06.2024 | K1: 07.2024 | L1: 08.2024 | M1: 09.2024 | N1: 10.2024 | O1: 11.2024 | P1: 12.2024 | Q1: 45658
A2: КЛО_МРЦ | B2: Киев,Фора МРЦ Оросительная,5 | C2: ИТОГО 2024 | D2: % К ОБОРОТУ | E2: 45292 | F2: 45323 | G2: 45352 | H2: 45383 | I2: 45413 | J2: 45444 | K2: 45474 | L2: 45505 | M2: 45536 | N2: 45566 | O2: 45597 | P2: 45627 | Q2: 45658
A3: Доходы
A4: Код | B4: 1. Выручка | C4: 681330.86 | D4: 5.1821135e-05 | E4: 183621.9 | F4: 105830.36 | G4: 83405.79 | H4: 165711.28 | I4: 142761.53 | J4: 109287.22 | K4: 146074.91 | L4: 124682.94 | M4: =SUM(M5:M13) -> 171168.47 | N4: 128016.34 | O4: 68150.28 | P4: 40121.3 | Q4: 56312.5
A5: 70200000 | B5: ДоходРеалТовара | C5: 681330.86 | D5: 5.1821135e-05 | E5: 183621.9 | F5: 105830.36 | G5: 83405.79 | H5: 165711.28 | I5: 142761.53 | J5: 109287.22 | K5: 146074.91 | L5: 124682.94 | M5: 171168.47 | N5: 128016.34 | O5: 68150.28 | P5: 40121.3 | Q5: 56312.5
A6: 70200001 | B6: ДоходРеалПрогрЛояльн | C6: 0 | D6: 0 | E6: 0 | F6: 0 | G6: 0 | H6: 0 | I6: 0 | J6: 0 | K6: 0 | L6: 0 | M6: 0 | N6: 0 | O6: 0 | P6: 0 | Q6: 0
A7: 70200002 | B7: ДоходРеалТВаучера | C7: 0 | D7: 0 | E7: 0 | F7: 0 | G7: 0 | H7: 0 | I7: 0 | J7: 0 | K7: 0 | L7: 0 | M7: 0 | N7: 0 | O7: 0 | P7: 0 | Q7: 0
A8: 70200003 | B8: ДоходРеалТовКомиссия | C8: 0 | D8: 0 | E8: 0 | F8: 0 | G8: 0 | H8: 0 | I8: 0 | J8: 0 | K8: 0 | L8: 0 | M8: 0 | N8: 0 | O8: 0 | P8: 0 | Q8: 0
A9: 70200004 | B9: ДоходРеалАгентсДог | C9: 0 | D9: 0 | E9: 0 | F9: 0 | G9: 0 | H9: 0 | I9: 0 | J9: 0 | K9: 0 | L9: 0 | M9: 0 | N9: 0 | O9: 0 | P9: 0 | Q9: 0
A10: 70200009 | B10: Недополучен.выручка | C10: 0 | D10: 0 | E10: 0 | F10: 0 | G10: 0 | H10: 0 | I10: 0 | J10: 0 | K10: 0 | L10: 0 | M10: 0 | N10: 0 | O10: 0 | P10: 0 | Q10: 0
A11: 70200200 | B11: ДоходРеалТовЭкспорт | C11: 0 | D11: 0 | E11: 0 | F11: 0 | G11: 0 | H11: 0 | I11: 0 | J11: 0 | K11: 0 | L11: 0 | M11: 0 | N11: 0 | O11: 0 | P11: 0 | Q11: 0
A12: 70400000 | B12: ВычетыДоходТовар | C12: 0 | D12: 0 | E12: 0 | F12: 0 | G12: 0 | H12: 0 | I12: 0 | J12: 0 | K12: 0 | L12: 0 | M12: 0 | N12: 0 | O12: 0 | P12: 0 | Q12: 0
A13: 70430000 | B13: ВычетыДоходАгентсДог | C13: 0 | D13: 0 | E13: 0 | F13: 0 | G13: 0 | H13: 0 | I13: 0 | J13: 0 | K13: 0 | L13: 0 | M13: 0 | N13: 0 | O13: 0 | P13: 0 | Q13: 0
A14: 1
A15: 1 | B15: 2. Себестоимость | C15: -882994.65 | D15: -6.7159419e-05 | E15: -196589.95 | F15: -110137.22 | G15: -91151.58 | H15: -175001.97 | I15: -310113.93 | J15: -107949.08 | K15: 334795.8 | L15: -116384.02 | M15: -176431.82 | N15: -328962.69 | O15: -74351.6 | P15: -43172.07 | Q15: -63168.81
A16: 90200000 | B16: СебестРеализТоваров | C16: -237145.18 | D16: -1.8036952e-05 | E16: 0 | F16: 0 | G16: 0 | H16: 0 | I16: -237145.18 | J16: 0 | K16: -35.23 | L16: -31.96 | M16: 0 | N16: -239193.28 | O16: 0 | P16: 0 | Q16: 0
A17: 90200001 | B17: СебестРеалТоваровПро | C17: -645849.47 | D17: -4.9122467e-05 | E17: -196589.95 | F17: -110137.22 | G17: -91151.58 | H17: -175001.97 | I17: -72968.75 | J17: -107949.08 | K17: 334831.03 | L17: -116352.06 | M17: -176431.82 | N17: -89769.41 | O17: -74351.6 | P17: -43172.07 | Q17: -63168.81
A18: 1
A19: 1 | B19: 3. Валовая маржа | C19: -201663.79 | D19: -1.5338284e-05 | E19: -12968.05 | F19: -4306.86 | G19: -7745.79 | H19: -9290.69 | I19: -167352.4 | J19: 1338.14 | K19: 480870.71 | L19: 8298.92 | M19: -5263.35 | N19: -200946.35 | O19: -6201.32 | P19: -3050.77 | Q19: -6856.31
A20: 1
A21: 1 | B21: 4. Бонусы | C21: 0 | D21: 0 | E21: 0 | F21: 0 | G21: 0 | H21: 0 | I21: 0 | J21: 0 | K21: 0 | L21: 0 | M21: 0 | N21: 0 | O21: 0 | P21: 0 | Q21: 0
A22: 71900700 | B22: ДоходОтБонусов | C22: 0 | D22: 0 | E22: 0 | F22: 0 | G22: 0 | H22: 0 | I22: 0 | J22: 0 | K22: 0 | L22: 0 | M22: 0 | N22: 0 | O22: 0 | P22: 0 | Q22: 0
A23: 1
A24: 1 | B24: 5. Прочее - Доходы | C24: 13424511 | D24: 0.0010210508 | E24: 2077536.5 | F24: 2423558.5 | G24: 3095621.3 | H24: 3170559.6 | I24: 2657235.3 | J24: 2074000.5 | K24: 1294218.6 | L24: 1904695 | M24: 749230.8 | N24: 2152332.6 | O24: 2114249.5 | P24: 1302730 | Q24: 3105094.5
A25: 70300000 | B25: ДоходРеалРабУсл | C25: 0 | D25: 0 | E25: 0 | F25: 0 | G25: 0 | H25: 0 | I25: 0 | J25: 0 | K25: 0 | L25: 0 | M25: 0 | N25: 0 | O25: 0 | P25: 0 | Q25: 0
A26: 70300200 | B26: ДохРазмРеклСобствНН | C26: 0 | D26: 0 | E26: 0 | F26: 0 | G26: 0 | H26: 0 | I26: 0 | J26: 0 | K26: 0 | L26: 0 | M26: 0 | N26: 0 | O26: 0 | P26: 0 | Q26: 0
A27: 70300700 | B27: ДохРеалУслЛогист | C27: 0 | D27: 0 | E27: 0 | F27: 0 | G27: 0 | H27: 0 | I27: 0 | J27: 0 | K27: 0 | L27: 0 | M27: 0 | N27: 0 | O27: 0 | P27: 0 | Q27: 0
A28: 70300800 | B28: ДоходДогКомиссии | C28: 0 | D28: 0 | E28: 0 | F28: 0 | G28: 0 | H28: 0 | I28: 0 | J28: 0 | K28: 0 | L28: 0 | M28: 0 | N28: 0 | O28: 0 | P28: 0 | Q28: 0
A29: 70300900 | B29: ДоходУслугКонечнПотр | C29: 0 | D29: 0 | E29: 0 | F29: 0 | G29: 0 | H29: 0 | I29: 0 | J29: 0 | K29: 0 | L29: 0 | M29: 0 | N29: 0 | O29: 0 | P29: 0 | Q29: 0
A30: 71200000 | B30: ДохРеалПрочОбАкт | C30: 0 | D30: 0 | E30: 0 | F30: 0 | G30: 0 | H30: 0 | I30: 0 | J30: 0 | K30: 0 | L30: 0 | M30: 0 | N30: 0 | O30: 0 | P30: 0 | Q30: 0
A31: 71200100 | B31: ДохРеалМакулатуры | C31: 0 | D31: 0 | E31: 0 | F31: 0 | G31: 0 | H31: 0 | I31: 0 | J31: 0 | K31: 0 | L31: 0 | M31: 0 | N31: 0 | O31: 0 | P31: 0 | Q31: 0
A32: 71300000 | B32: ДохАренОборудован | C32: 0 | D32: 0 | E32: 0 | F32: 0 | G32: 0 | H32: 0 | I32: 0 | J32: 0 | K32: 0 | L32: 0 | M32: 0 | N32: 0 | O32: 0 | P32: 0 | Q32: 0
A33: 71300200 | B33: ДохАренТранспорта | C33: 0 | D33: 0 | E33: 0 | F33: 0 | G33: 0 | H33: 0 | I33: 0 | J33: 0 | K33: 0 | L33: 0 | M33: 0 | N33: 0 | O33: 0 | P33: 0 | Q33: 0
A34: 71500000 | B34: ПолучШтрафПени | C34: 0 | D34: 0 | E34: 0 | F34: 0 | G34: 0 | H34: 0 | I34: 0 | J34: 0 | K34: 0 | L34: 0 | M34: 0 | N34: 0 | O34: 0 | P34: 0 | Q34: 0
A35: 71500100 | B35: ОтримШтрафиПеніКомер
A36: 71700000 | B36: ДохСписКредЗадолж | C36: 0 | D36: 0 | E36: 0 | F36: 0 | G36: 0 | H36: 0 | I36: 0 | J36: 0 | K36: 0 | L36: 0 | M36: 0 | N36: 0 | O36: 0 | P36: 0 | Q36: 0
A37: 71800000 | B37: ДохБесплПолОборАкт | C37: 0 | D37: 0 | E37: 0 | F37: 0 | G37: 0 | H37: 0 | I37: 0 | J37: 0 | K37: 0 | L37: 0 | M37: 0 | N37: 0 | O37: 0 | P37: 0 | Q37: 0
A38: 71800400 | B38: ДохБесплПолАктив.РЦ | C38: 0 | D38: 0 | E38: 0 | F38: 0 | G38: 0 | H38: 0 | I38: 0 | J38: 0 | K38: 0 | L38: 0 | M38: 0 | N38: 0 | O38: 0 | P38: 0 | Q38: 0
A39: 71900000 | B39: ПрочДоходОперДеят | C39: 13424511 | D39: 0.0010210508 | E39: 2077536.5 | F39: 2423558.5 | G39: 3095621.3 | H39: 3170559.6 | I39: 2657235.3 | J39: 2074000.5 | K39: 1294218.6 | L39: 1904695 | M39: 749230.8 | N39: 2152332.6 | O39: 2114249.5 | P39: 1302730 | Q39: 3105094.5
A40: 71900100 | B40: ПрочДоход% банка | C40: 0 | D40: 0 | E40: 0 | F40: 0 | G40: 0 | H40: 0 | I40: 0 | J40: 0 | K40: 0 | L40: 0 | M40: 0 | N40: 0 | O40: 0 | P40: 0 | Q40: 0
A41: 71900500 | B41: ПрДоходИзлишки кассы | C41: 0 | D41: 0 | E41: 0 | F41: 0 | G41: 0 | H41: 0 | I41: 0 | J41: 0 | K41: 0 | L41: 0 | M41: 0 | N41: 0 | O41: 0 | P41: 0 | Q41: 0
A42: 71900600 | B42: Доход гостинич услуг | C42: 0 | D42: 0 | E42: 0 | F42: 0 | G42: 0 | H42: 0 | I42: 0 | J42: 0 | K42: 0 | L42: 0 | M42: 0 | N42: 0 | O42: 0 | P42: 0 | Q42: 0
A43: 71900900 | B43: ДохідСтраховВідшк
A44: 71901000 | B44: ІнДоход%депозит | C44: 0 | D44: 0 | E44: 0 | F44: 0 | G44: 0 | H44: 0 | I44: 0 | J44: 0 | K44: 0 | L44: 0 | M44: 0 | N44: 0 | O44: 0 | P44: 0 | Q44: 0
A45: 1
A46: 1 | B46: 6. Прочие доходы аренда | C46: 19166.68 | D46: 1.4577926e-06 | E46: 2500 | F46: 4166.67 | G46: 4166.67 | H46: 4166.67 | I46: 4166.67 | J46: 4166.67 | K46: 4166.67 | L46: 4166.67 | M46: 4166.67 | N46: 4166.67 | O46: 4166.67 | P46: 4166.67 | Q46: 5000
A47: 71300100 | B47: ДохАренПомещений | C47: 19166.68 | D47: 1.4577926e-06 | E47: 2500 | F47: 4166.67 | G47: 4166.67 | H47: 4166.67 | I47: 4166.67 | J47: 4166.67 | K47: 4166.67 | L47: 4166.67 | M47: 4166.67 | N47: 4166.67 | O47: 4166.67 | P47: 4166.67 | Q47: 5000
A48: 71900400 | B48: ВозмещКомЭксплЗатрат | C48: 0 | D48: 0 | E48: 0 | F48: 0 | G48: 0 | H48: 0 | I48: 0 | J48: 0 | K48: 0 | L48: 0 | M48: 0 | N48: 0 | O48: 0 | P48: 0 | Q48: 0
A49: 1
A50: 1 | B50: Валовая прибыль | C50: 13242014 | D50: 0.0010071703 | E50: 2067068.4 | F50: 2423418.3 | G50: 3092042.2 | H50: 3165435.6 | I50: 2494049.6 | J50: 2079505.3 | K50: 1779256 | L50: 1917160.6 | M50: 748134.12 | N50: 1955552.9 | O50: 2112214.9 | P50: 1303845.9 | Q50: 3103238.2
A51: Затраты
A52: 1 | B52: 7. Списания и переучеты | C52: -20648896 | D52: -0.001570528 | E52: -4243232.7 | F52: -4165012.7 | G52: -5006133.8 | H52: -4282250.4 | I52: -2952266.2 | J52: -2307492.2 | K52: -4646145.5 | L52: -4790109.5 | M52: -4277996.5 | N52: -5405712.2 | O52: -3577426.8 | P52: -6022932 | Q52: -1544187
A53: 80810000 | B53: РасхТоварПереуч | C53: 52533.81 | D53: 3.9956529e-06 | E53: 40736.39 | F53: 2655.59 | G53: 1164.51 | H53: 2856.21 | I53: 5121.11 | J53: 4780.58 | K53: 5291.5 | L53: 3027.87 | M53: 1452.38 | N53: 162736.09 | O53: 62695.44 | P53: 42501.53 | Q53: 2987.1
A54: 80810001 | B54: РасхМатПереучетПроиз | C54: -1660907.2 | D54: -0.00012632643 | E54: -695031.57 | F54: -400190.69 | G54: -452549.97 | H54: -394883.37 | I54: 281748.38 | J54: -264429.83 | K54: -487231.74 | L54: -3160439.4 | M54: -901638.04 | N54: -2555267.6 | O54: -1433049.3 | P54: -3686439.2 | Q54: 1930883.7
A55: 80820000 | B55: РасхТоварПотериСпис | C55: -41240.5 | D55: -3.1366985e-06 | E55: -1062.3 | F55: -2670.37 | G55: -297.86 | H55: 0 | I55: -37209.97 | J55: -185.25 | K55: -456385.9 | L55: -1709.79 | M55: -6987.64 | N55: 0 | O55: 0 | P55: 0 | Q55: 0
A56: 80820001 | B56: РасхМатПотПоСписПр | C56: -18999282 | D56: -0.0014450606 | E56: -3587875.2 | F56: -3764807.2 | G56: -4554450.5 | H56: -3890223.2 | I56: -3201925.8 | J56: -2047657.8 | K56: -3707819.4 | L56: -1630988.2 | M56: -3370823.2 | N56: -3013180.7 | O56: -2207073 | P56: -2378994.3 | Q56: -3478057.7
A57: 1
A58: 1 | B58: 8. ФОТ, в т.ч. налоги | C58: -33871975 | D58: -0.0025762582 | E58: -6708036.1 | F58: -6460441.3 | G58: -6527717.3 | H58: -7020261.7 | I58: -7155518.6 | J58: -7194966.3 | K58: -8070910.4 | L58: -7139213.4 | M58: -6489593.5 | N58: -7185474.7 | O58: -6737792.6 | P58: -7162066.6 | Q58: -7050050.5
A59: 81100000 | B59: РасхОплТрОклады | C59: -28151658 | D59: -0.0021411783 | E59: -5627730 | F59: -5158129.8 | G59: -5523574.5 | H59: -5875693.8 | I59: -5966530.1 | J59: -6013450 | K59: -6884945 | L59: -5825197.8 | M59: -5501885.4 | N59: -5878306.8 | O59: -5609939.8 | P59: -5924213.7 | Q59: -5920748
A60: 81100100 | B60: Оплата Моб,ТРО | C60: -365000 | D60: -2.7761423e-05 | E60: -70000 | F60: -70000 | G60: -75000 | H60: -75000 | I60: -75000 | J60: -75000 | K60: -65000 | L60: -60000 | M60: -65000 | N60: -65000 | O60: -65000 | P60: -67990 | Q60: -67990
A61: 81200000 | B61: ПремииПоощрения | C61: 0 | D61: 0 | E61: 0 | F61: 0 | G61: 0 | H61: 0 | I61: 0 | J61: 0 | K61: 0 | L61: 0 | M61: 0 | N61: 0 | O61: 0 | P61: 0 | Q61: 0
A62: 81400000 | B62: Оплата отпусков | C62: -1288395.5 | D62: -9.7993679e-05 | E62: -238426.51 | F62: -416747.76 | G62: -144998.75 | H62: -223151.46 | I62: -265071.04 | J62: -266987.36 | K62: -282687.15 | L62: -390876.12 | M62: -136528.12 | N62: -323203.5 | O62: -187323.6 | P62: -257271.96 | Q62: -217999.17
A63: 81500000 | B63: ПрочРасхНаОплТр | C63: 0 | D63: 0 | E63: 0 | F63: 0 | G63: 0 | H63: 0 | I63: 0 | J63: 0 | K63: 0 | L63: 0 | M63: 0 | N63: 0 | O63: 0 | P63: 0 | Q63: 0
A64: 81500100 | B64: СПД и директорство | C64: 0 | D64: 0 | E64: 0 | F64: 0 | G64: 0 | H64: 0 | I64: 0 | J64: 0 | K64: 0 | L64: 0 | M64: 0 | N64: 0 | O64: 0 | P64: 0 | Q64: 0
A65: 82100000 | B65: Налоги на ФОТ | C65: -4066921.2 | D65: -0.00030932471 | E65: -771879.57 | F65: -815563.75 | G65: -784144.02 | H65: -846416.41 | I65: -848917.43 | J65: -839528.96 | K65: -838278.28 | L65: -863139.42 | M65: -786179.97 | N65: -918964.44 | O65: -875529.3 | P65: -912590.88 | Q65: -843313.31
A66: 84210100 | B66: УслЦенБумагИС | C66: 0 | D66: 0 | E66: 0 | F66: 0 | G66: 0 | H66: 0 | I66: 0 | J66: 0 | K66: 0 | L66: 0 | M66: 0 | N66: 0 | O66: 0 | P66: 0 | Q66: 0
A67: 1
A68: 1 | B68: 9. Персонал | C68: -108670.33 | D68: -8.2653233e-06 | E68: -18209.29 | F68: -10885.9 | G68: -15285.93 | H68: -32541.69 | I68: -31747.52 | J68: -49047.21 | K68: -32332.64 | L68: -35060.88 | M68: -32168.89 | N68: -42139.01 | O68: -73226.42 | P68: -43815.73 | Q68: -35546.97
A69: 81300000 | B69: КомпенсацВыплаты | C69: 0 | D69: 0 | E69: 0 | F69: 0 | G69: 0 | H69: 0 | I69: 0 | J69: 0 | K69: 0 | L69: 0 | M69: 0 | N69: 0 | O69: 0 | P69: 0 | Q69: 0
A70: 81300100 | B70: КомпЗаИспЛичнТр | C70: -8899.66 | D70: -6.7689651e-07 | E70: -3350 | F70: 0 | G70: -2774.83 | H70: 0 | I70: -2774.83 | J70: 0 | K70: -2774.83 | L70: -3333.93 | M70: -3465 | N70: -6608.85 | O70: 0 | P70: 0 | Q70: 0
A71: 81300200 | B71: КомпКвартир | C71: 0 | D71: 0 | E71: 0 | F71: 0 | G71: 0 | H71: 0 | I71: 0 | J71: 0 | K71: 0 | L71: 0 | M71: 0 | N71: 0 | O71: 0 | P71: 0 | Q71: 0
A72: 81300300 | B72: МатПомощьСотр | C72: -23300 | D72: -1.7721675e-06 | E72: -5300 | F72: 0 | G72: 0 | H72: -18000 | I72: 0 | J72: -3000 | K72: 0 | L72: 0 | M72: 0 | N72: -6650 | O72: 0 | P72: 0 | Q72: 0
A73: 81300400 | B73: МатПомНаПогребен | C73: 0 | D73: 0 | E73: 0 | F73: 0 | G73: 0 | H73: 0 | I73: 0 | J73: 0 | K73: 0 | L73: 0 | M73: 0 | N73: 0 | O73: 0 | P73: 0 | Q73: 0
A74: 82400000 | B74: ОтчислНаИндивСтрах | C74: 0 | D74: 0 | E74: 0 | F74: 0 | G74: 0 | H74: 0 | I74: 0 | J74: 0 | K74: 0 | L74: 0 | M74: 0 | N74: 0 | O74: 0 | P74: 0 | Q74: 0
A75: 84220100 | B75: ПерсоналПоиск | C75: -13200 | D75: -1.0039747e-06 | E75: -2400 | F75: -3600 | G75: 0 | H75: -7200 | I75: 0 | J75: 0 | K75: 0 | L75: 0 | M75: 0 | N75: 0 | O75: 0 | P75: 0 | Q75: 0
A76: 84220200 | B76: ПерсоналОбучВнутр | C76: 0 | D76: 0 | E76: 0 | F76: 0 | G76: 0 | H76: 0 | I76: 0 | J76: 0 | K76: 0 | L76: 0 | M76: 0 | N76: 0 | O76: 0 | P76: 0 | Q76: 0
A77: 84220300 | B77: ПерсоналОбучВнешн | C77: -1140 | D77: -8.670691e-08 | E77: 0 | F77: 0 | G77: 0 | H77: -1140 | I77: 0 | J77: 0 | K77: 0 | L77: 0 | M77: 0 | N77: 0 | O77: 0 | P77: 0 | Q77: 0
A78: 84220400 | B78: Персонал медосмотры | C78: -6616 | D78: -5.0320431e-07 | E78: -682 | F78: -1450 | G78: -848 | H78: -1615 | I78: -2021 | J78: -15153 | K78: 0 | L78: -1230 | M78: -1925 | N78: -1588 | O78: -26690 | P78: -2100 | Q78: -520
A79: 84220500 | B79: ПерсоналСтажеры | C79: 0 | D79: 0 | E79: 0 | F79: 0 | G79: 0 | H79: 0 | I79: 0 | J79: 0 | K79: 0 | L79: 0 | M79: 0 | N79: 0 | O79: 0 | P79: 0 | Q79: 0
... A82: 84220900 | B82: ПЕРСОН | C82: 0 | D82: 0 | E82: 0 | F82: 0 | G82: 0 | H82: 0 | I82: 0 | J82: 0 | K82: 0 | L82: 0 | M82: 0 | N82: 0 | O82: 0 | P82: 0 | Q82: 0
A83: 1
A84: 1 | B84: 10. Аренда помещений | C84: -2712638.1 | D84: -0.00020631971 | E84: -527771.38 | F84: -546728.34 | G84: -546728.34 | H84: -546728.34 | I84: -544681.67 | J84: -544681.67 | K84: -549251.56 | L84: -553015 | M84: -553015 | N84: -553015 | O84: -636254.44 | P84: -802733.33 | Q84: -802733.33
A85: 84160200 | B85: Аренда помещений | C85: -2712638.1 | D85: -0.00020631971 | E85: -527771.38 | F85: -546728.34 | G85: -546728.34 | H85: -546728.34 | I85: -544681.67 | J85: -544681.67 | K85: -549251.56 | L85: -553015 | M85: -553015 | N85: -553015 | O85: -636254.44 | P85: -802733.33 | Q85: -802733.33
A86: 1
A87: 1 | B87: 11. Коммунальные услуги | C87: -2366326.6 | D87: -0.00017997971 | E87: -576479.15 | F87: -473116.58 | G87: -427975.76 | H87: -387136.41 | I87: -501618.75 | J87: -688326.16 | K87: -1068295 | L87: -736300.45 | M87: -699207.97 | N87: -648509.29 | O87: -687353.45 | P87: -791744.72 | Q87: -757382.46
A88: 84030100 | B88: КомУслВода | C88: 0 | D88: 0 | E88: 0 | F88: 0 | G88: 0 | H88: 0 | I88: 0 | J88: 0 | K88: 0 | L88: 0 | M88: 0 | N88: 0 | O88: 0 | P88: -10255.3 | Q88: 0
A89: 84030200 | B89: КомУслВывОтходМус | C89: -56463 | D89: -4.294502e-06 | E89: -11844.25 | F89: -10384 | G89: -11357.5 | H89: -11519.75 | I89: -11357.5 | J89: -16225 | K89: -16874 | L89: -17523 | M89: -16225 | N89: -16062.75 | O89: -14278 | P89: -16225 | Q89: -18009.75
A90: 84030300 | B90: КомУслГаз | C90: 0 | D90: 0 | E90: 0 | F90: 0 | G90: 0 | H90: 0 | I90: 0 | J90: 0 | K90: 0 | L90: 0 | M90: 0 | N90: 0 | O90: 0 | P90: 0 | Q90: 0
A91: 84030400 | B91: КомУслОтопление | C91: 0 | D91: 0 | E91: 0 | F91: 0 | G91: 0 | H91: 0 | I91: 0 | J91: 0 | K91: 0 | L91: 0 | M91: 0 | N91: 0 | O91: 0 | P91: 0 | Q91: 0
A92: 84030500 | B92: КомУслЭлектроэн | C92: -2245684.6 | D92: -0.00017080384 | E92: -562724.21 | F92: -460821.89 | G92: -414707.57 | H92: -373705.97 | I92: -433725 | J92: -503544.13 | K92: -547727.67 | L92: -693058.13 | M92: -573127.47 | N92: -630535.86 | O92: -591769.8 | P92: -614456.03 | Q92: -737462.02
A93: 84030600 | B93: ЭксплуатПрочиеКомун | C93: -9553.45 | D93: -7.2662292e-07 | E93: -1910.69 | F93: -1910.69 | G93: -1910.69 | H93: -1910.69 | I93: -1910.69 | J93: -1910.68 | K93: -1910.68 | L93: -1910.68 | M93: -1910.68 | N93: -1910.68 | O93: -1910.68 | P93: -1910.68 | Q93: -1910.69
A94: 84030800 | B94: КомУслЭлВозмещГенер. | C94: 0 | D94: 0 | E94: 0 | F94: 0 | G94: 0 | H94: 0 | I94: 0 | J94: 0 | K94: 0 | L94: 0 | M94: 0 | N94: 0 | O94: 0 | P94: 0 | Q94: 0
A95: 80300100 | B95: РасхГСМ Тех.ИПр.нужд | C95: -54625.56 | D95: -4.1547487e-06 | E95: 0 | F95: 0 | G95: 0 | H95: 0 | I95: -54625.56 | J95: -166646.35 | K95: -501782.6 | L95: -23808.64 | M95: -107944.82 | N95: 0 | O95: -79394.97 | P95: -148897.71 | Q95: 0
A96: 1
A97: 1 | B97: 12. Логистика | C97: 0 | D97: 0 | E97: 0 | F97: 0 | G97: 0 | H97: 0 | I97: 0 | J97: -29159.37 | K97: 0 | L97: 0 | M97: -55496.76 | N97: -58705.25 | O97: -58514.95 | P97: -60436.91 | Q97: -56200.06
A98: 84020100 | B98: Транспортные услуги | C98: 0 | D98: 0 | E98: 0 | F98: 0 | G98: 0 | H98: 0 | I98: 0 | J98: -23503.04 | K98: 0 | L98: 0 | M98: -49032.03 | N98: -49275.86 | O98: -48571.17 | P98: -51579.71 | Q98: -50892.66
A99: 84020200 | B99: Логистика | C99: 0 | D99: 0 | E99: 0 | F99: 0 | G99: 0 | H99: 0 | I99: 0 | J99: 0 | K99: 0 | L99: 0 | M99: 0 | N99: 0 | O99: 0 | P99: 0 | Q99: 0
A100: 84020300 | B100: ПрочУслСкладХоз | C100: 0 | D100: 0 | E100: 0 | F100: 0 | G100: 0 | H100: 0 | I100: 0 | J100: -5656.33 | K100: 0 | L100: 0 | M100: -6464.73 | N100: -9429.39 | O100: -9943.78 | P100: -8857.2 | Q100: -5307.4
A101: 1
A102: 1 | B102: 13. Материалы | C102: -2940390.4 | D102: -0.00022364225 | E102: -393617.72 | F102: -644135.2 | G102: -658396.49 | H102: -602795.07 | I102: -641445.97 | J102: -665620.16 | K102: -838310.06 | L102: -723271.74 | M102: -694332.87 | N102: -1185581.1 | O102: -828794.03 | P102: -1003799.2 | Q102: -709486.92
...

Sheet ФАКТ 2025
E1: 45658 | F1: 45689 | G1: 45717 | H1: 45748 | I1: 45778 | J1: 45809 | K1: 45839 | L1: 45870 | M1: 45901 | N1: 45931 | O1: 45962 | P1: 45992
A2: КЛО_МРЦ | B2: Киев,Фора МРЦ Оросительная,5 | C2: ИТОГО 2025 | D2: % К ОБОРОТУ | E2: 45658 | F2: 45689 | G2: 45717 | H2: 45748 | I2: 45778 | J2: 45809 | K2: 45839 | L2: 45870 | M2: 45901 | N2: 45931 | O2: 45962 | P2: 45992
A3: Доходы
A4: Код | B4: 1. Выручка | C4: 56312.5 | D4: 1.6139912e-06 | E4: 56312.5 | F4: 43272.3 | G4: 43860.04 | H4: 42136.95 | I4: 133672.61 | J4: 0 | K4: 0 | L4: 0 | M4: 0 | N4: 0 | O4: 0 | P4: 0
A5: 70200000 | B5: ДоходРеалТовара | C5: 56312.5 | D5: 1.6139912e-06 | E5: 56312.5 | F5: 43272.3 | G5: 43860.04 | H5: 42136.95 | I5: 133672.61 | J5: 0 | K5: 0 | L5: 0 | M5: 0 | N5: 0 | O5: 0 | P5: 0
A6: 70200001 | B6: ДоходРеалПрогрЛояльн | C6: 0 | D6: 0 | E6: 0 | F6: 0 | G6: 0 | H6: 0 | I6: 0 | J6: 0 | K6: 0 | L6: 0 | M6: 0 | N6: 0 | O6: 0 | P6: 0
A7: 70200002 | B7: ДоходРеалТВаучера | C7: 0 | D7: 0 | E7: 0 | F7: 0 | G7: 0 | H7: 0 | I7: 0 | J7: 0 | K7: 0 | L7: 0 | M7: 0 | N7: 0 | O7: 0 | P7: 0
A8: 70200003 | B8: ДоходРеалТовКомиссия | C8: 0 | D8: 0 | E8: 0 | F8: 0 | G8: 0 | H8: 0 | I8: 0 | J8: 0 | K8: 0 | L8: 0 | M8: 0 | N8: 0 | O8: 0 | P8: 0
A9: 70200004 | B9: ДоходРеалАгентсДог | C9: 0 | D9: 0 | E9: 0 | F9: 0 | G9: 0 | H9: 0 | I9: 0 | J9: 0 | K9: 0 | L9: 0 | M9: 0 | N9: 0 | O9: 0 | P9: 0
A10: 70200009 | B10: Недополучен.выручка | C10: 0 | D10: 0 | E10: 0 | F10: 0 | G10: 0 | H10: 0 | I10: 0 | J10: 0 | K10: 0 | L10: 0 | M10: 0 | N10: 0 | O10: 0 | P10: 0
A11: 70200200 | B11: ДоходРеалТовЭкспорт | C11: 0 | D11: 0 | E11: 0 | F11: 0 | G11: 0 | H11: 0 | I11: 0 | J11: 0 | K11: 0 | L11: 0 | M11: 0 | N11: 0 | O11: 0 | P11: 0
A12: 70400000 | B12: ВычетыДоходТовар | C12: 0 | D12: 0 | E12: 0 | F12: 0 | G12: 0 | H12: 0 | I12: 0 | J12: 0 | K12: 0 | L12: 0 | M12: 0 | N12: 0 | O12: 0 | P12: 0
A13: 70430000 | B13: ВычетыДоходАгентсДог | C13: 0 | D13: 0 | E13: 0 | F13: 0 | G13: 0 | H13: 0 | I13: 0 | J13: 0 | K13: 0 | L13: 0 | M13: 0 | N13: 0 | O13: 0 | P13: 0
A14: 1
A15: 1 | B15: 2. Себестоимость | C15: -63168.81 | D15: -1.8105022e-06 | E15: -63168.81 | F15: -27005.75 | G15: -51602.41 | H15: -62649.3 | I15: -108767.59 | J15: 0 | K15: 0 | L15: 0 | M15: 0 | N15: 0 | O15: 0 | P15: 0
A16: 90200000 | B16: СебестРеализТоваров | C16: 0 | D16: 0 | E16: 0 | F16: -27.4 | G16: 0 | H16: 0 | I16: -19296.99 | J16: 0 | K16: 0 | L16: 0 | M16: 0 | N16: 0 | O16: 0 | P16: 0
A17: 90200001 | B17: СебестРеалТоваровПро | C17: -63168.81 | D17: -1.8105022e-06 | E17: -63168.81 | F17: -26978.35 | G17: -51602.41 | H17: -62649.3 | I17: -89470.6 | J17: 0 | K17: 0 | L17: 0 | M17: 0 | N17: 0 | O17: 0 | P17: 0
A18: 1
A19: 1 | B19: 3. Валовая маржа | C19: -6856.31 | D19: -1.9651097e-07 | E19: -6856.31 | F19: 16266.55 | G19: -7742.37 | H19: -20512.35 | I19: 24905.02 | J19: 0 | K19: 0 | L19: 0 | M19: 0 | N19: 0 | O19: 0 | P19: 0
A20: 1
A21: 1 | B21: 4. Бонусы | C21: 0 | D21: 0 | E21: 0 | F21: 0 | G21: 0 | H21: 0 | I21: 0 | J21: 0 | K21: 0 | L21: 0 | M21: 0 | N21: 0 | O21: 0 | P21: 0
A22: 71900700 | B22: ДоходОтБонусов | C22: 0 | D22: 0 | E22: 0 | F22: 0 | G22: 0 | H22: 0 | I22: 0 | J22: 0 | K22: 0 | L22: 0 | M22: 0 | N22: 0 | O22: 0 | P22: 0
A23: 1
A24: 1 | B24: 5. Прочее - Доходы | C24: 3105094.5 | D24: 8.8996142e-05 | E24: 3105094.5 | F24: 1605268.9 | G24: 1724627.5 | H24: 1546722.8 | I24: 2920354.5 | J24: 0 | K24: 0 | L24: 0 | M24: 0 | N24: 0 | O24: 0 | P24: 0
A25: 70300000 | B25: ДоходРеалРабУсл | C25: 0 | D25: 0 | E25: 0 | F25: 0 | G25: 0 | H25: 0 | I25: 0 | J25: 0 | K25: 0 | L25: 0 | M25: 0 | N25: 0 | O25: 0 | P25: 0
A26: 70300200 | B26: ДохРазмРеклСобствНН | C26: 0 | D26: 0 | E26: 0 | F26: 0 | G26: 0 | H26: 0 | I26: 0 | J26: 0 | K26: 0 | L26: 0 | M26: 0 | N26: 0 | O26: 0 | P26: 0
A27: 70300700 | B27: ДохРеалУслЛогист | C27: 0 | D27: 0 | E27: 0 | F27: 0 | G27: 0 | H27: 0 | I27: 0 | J27: 0 | K27: 0 | L27: 0 | M27: 0 | N27: 0 | O27: 0 | P27: 0
A28: 70300800 | B28: ДоходДогКомиссии | C28: 0 | D28: 0 | E28: 0 | F28: 0 | G28: 0 | H28: 0 | I28: 0 | J28: 0 | K28: 0 | L28: 0 | M28: 0 | N28: 0 | O28: 0 | P28: 0
A29: 70300900 | B29: ДоходУслугКонечнПотр | C29: 0 | D29: 0 | E29: 0 | F29: 0 | G29: 0 | H29: 0 | I29: 0 | J29: 0 | K29: 0 | L29: 0 | M29: 0 | N29: 0 | O29: 0 | P29: 0
A30: 71200000 | B30: ДохРеалПрочОбАкт | C30: 0 | D30: 0 | E30: 0 | F30: 0 | G30: 0 | H30: 0 | I30: 0 | J30: 0 | K30: 0 | L30: 0 | M30: 0 | N30: 0 | O30: 0 | P30: 0
A31: 71200100 | B31: ДохРеалМакулатуры | C31: 0 | D31: 0 | E31: 0 | F31: 0 | G31: 9912 | H31: 13862.8 | I31: 12950 | J31: 0 | K31: 0 | L31: 0 | M31: 0 | N31: 0 | O31: 0 | P31: 0
A32: 71300000 | B32: ДохАренОборудован | C32: 0 | D32: 0 | E32: 0 | F32: 0 | G32: 0 | H32: 0 | I32: 0 | J32: 0 | K32: 0 | L32: 0 | M32: 0 | N32: 0 | O32: 0 | P32: 0
A33: 71300200 | B33: ДохАренТранспорта | C33: 0 | D33: 0 | E33: 0 | F33: 0 | G33: 0 | H33: 0 | I33: 0 | J33: 0 | K33: 0 | L33: 0 | M33: 0 | N33: 0 | O33: 0 | P33: 0
A34: 71500000 | B34: ПолучШтрафПени | C34: 0 | D34: 0 | E34: 0 | F34: 0 | G34: 0 | H34: 0 | I34: 0 | J34: 0 | K34: 0 | L34: 0 | M34: 0 | N34: 0 | O34: 0 | P34: 0
A35: 71500100 | B35: ОтримШтрафиПеніКомер
A36: 71700000 | B36: ДохСписКредЗадолж | C36: 0 | D36: 0 | E36: 0 | F36: 0 | G36: 0 | H36: 0 | I36: 0 | J36: 0 | K36: 0 | L36: 0 | M36: 0 | N36: 0 | O36: 0 | P36: 0
A37: 71800000 | B37: ДохБесплПолОборАкт | C37: 0 | D37: 0 | E37: 0 | F37: 0 | G37: 0 | H37: 0 | I37: 0 | J37: 0 | K37: 0 | L37: 0 | M37: 0 | N37: 0 | O37: 0 | P37: 0
A38: 71800400 | B38: ДохБесплПолАктив.РЦ | C38: 0 | D38: 0 | E38: 0 | F38: 0 | G38: 0 | H38: 0 | I38: 0 | J38: 0 | K38: 0 | L38: 0 | M38: 0 | N38: 0 | O38: 0 | P38: 0
A39: 71900000 | B39: ПрочДоходОперДеят | C39: 3105094.5 | D39: 8.8996142e-05 | E39: 3105094.5 | F39: 1605268.9 | G39: 1714715.5 | H39: 1532860 | I39: 2907404.5 | J39: 0 | K39: 0 | L39: 0 | M39: 0 | N39: 0 | O39: 0 | P39: 0
A40: 71900100 | B40: ПрочДоход% банка | C40: 0 | D40: 0 | E40: 0 | F40: 0 | G40: 0 | H40: 0 | I40: 0 | J40: 0 | K40: 0 | L40: 0 | M40: 0 | N40: 0 | O40: 0 | P40: 0
A41: 71900500 | B41: ПрДоходИзлишки кассы | C41: 0 | D41: 0 | E41: 0 | F41: 0 | G41: 0 | H41: 0 | I41: 0 | J41: 0 | K41: 0 | L41: 0 | M41: 0 | N41: 0 | O41: 0 | P41: 0
A42: 71900600 | B42: Доход гостинич услуг | C42: 0 | D42: 0 | E42: 0 | F42: 0 | G42: 0 | H42: 0 | I42: 0 | J42: 0 | K42: 0 | L42: 0 | M42: 0 | N42: 0 | O42: 0 | P42: 0
A43: 71900900 | B43: ДохідСтраховВідшк
A44: 71901000 | B44: ІнДоход%депозит | C44: 0 | D44: 0 | E44: 0 | F44: 0 | G44: 0 | H44: 0 | I44: 0 | J44: 0 | K44: 0 | L44: 0 | M44: 0 | N44: 0 | O44: 0 | P44: 0
A45: 1
A46: 1 | B46: 6. Прочие доходы аренда | C46: 5000 | D46: 1.4330666e-07 | E46: 5000 | F46: 5000 | G46: 5000 | H46: 5000 | I46: 5000 | J46: 0 | K46: 0 | L46: 0 | M46: 0 | N46: 0 | O46: 0 | P46: 0
A47: 71300100 | B47: ДохАренПомещений | C47: 5000 | D47: 1.4330666e-07 | E47: 5000 | F47: 5000 | G47: 5000 | H47: 5000 | I47: 0 | J47: 0 | K47: 0 | L47: 0 | M47: 0 | N47: 0 | O47: 0 | P47: 0
A48: 71900400 | B48: ВозмещКомЭксплЗатрат | C48: 0 | D48: 0 | E48: 0 | F48: 0 | G48: 0 | H48: 0 | I48: 0 | J48: 0 | K48: 0 | L48: 0 | M48: 0 | N48: 0 | O48: 0 | P48: 0
A49: 1
A50: 1 | B50: Валовая прибыль | C50: 3103238.2 | D50: 8.8942938e-05 | E50: 3103238.2 | F50: 1626535.4 | G50: 1721885.1 | H50: 1531210.4 | I50: 2950259.5 | J50: 0 | K50: 0 | L50: 0 | M50: 0 | N50: 0 | O50: 0 | P50: 0
A51: Затраты
A52: 1 | B52: 7. Списания и переучеты | C52: -1544187 | D52: -4.4258455e-05 | E52: -1544187 | F52: -3615388.6 | G52: -2556959.6 | H52: -3083264.3 | I52: -2599827.5 | J52: 0 | K52: 0 | L52: 0 | M52: 0 | N52: 0 | O52: 0 | P52: 0
A53: 80810000 | B53: РасхТоварПереуч | C53: 2987.1 | D53: 8.5614263e-08 | E53: 2987.1 | F53: 32732.23 | H53: 2632.71 | I53: 129902.97 | J53: 0 | K53: 0 | L53: 0 | M53: 0 | N53: 0 | O53: 0 | P53: 0
A54: 80810001 | B54: РасхМатПереучетПроиз | C54: 1930883.7 | D54: 5.5341696e-05 | E54: 1930883.7 | F54: -1270673.2 | H54: -1069338.6 | I54: -234045.08 | J54: 0 | K54: 0 | L54: 0 | M54: 0 | N54: 0 | O54: 0 | P54: 0
A55: 80820000 | B55: РасхТоварПотериСпис | C55: 0 | D55: 0 | E55: 0 | F55: 0 | H55: 0 | I55: -1677.76 | J55: 0 | K55: 0 | L55: 0 | M55: 0 | N55: 0 | O55: 0 | P55: 0
A56: 80820001 | B56: РасхМатПотПоСписПр | C56: -3478057.7 | D56: -9.9685765e-05 | E56: -3478057.7 | F56: -2377447.6 | H56: -2016558.4 | I56: -2494007.6 | J56: 0 | K56: 0 | L56: 0 | M56: 0 | N56: 0 | O56: 0 | P56: 0
A57: 1
A58: 1 | B58: 8. ФОТ, в т.ч. налоги | C58: -7050050.5 | D58: -0.00020206383 | E58: -7050050.5 | F58: -7376629.3 | H58: -8085705.2 | I58: -8853555 | J58: 0 | K58: 0 | L58: 0 | M58: 0 | N58: 0 | O58: 0 | P58: 0
A59: 81100000 | B59: РасхОплТрОклады | C59: -5920748 | D59: -0.00016969652 | E59: -5920748 | F59: -6161991.5 | H59: -6848666.5 | I59: -7608611.2 | J59: 0 | K59: 0 | L59: 0 | M59: 0 | N59: 0 | O59: 0 | P59: 0
A60: 81100100 | B60: Оплата Моб,ТРО | C60: -67990 | D60: -1.9486839e-06 | E60: -67990 | F60: -67990 | H60: -67990 | I60: -73220 | J60: 0 | K60: 0 | L60: 0 | M60: 0 | N60: 0 | O60: 0 | P60: 0
A61: 81200000 | B61: ПремииПоощрения | C61: 0 | D61: 0 | E61: 0 | F61: 0 | H61: 0 | I61: 0 | J61: 0 | K61: 0 | L61: 0 | M61: 0 | N61: 0 | O61: 0 | P61: 0
A62: 81400000 | B62: Оплата отпусков | C62: -217999.17 | D62: -6.2481465e-06 | E62: -217999.17 | F62: -261604.75 | H62: -275502.66 | I62: -197810.03 | J62: 0 | K62: 0 | L62: 0 | M62: 0 | N62: 0 | O62: 0 | P62: 0
A63: 81500000 | B63: ПрочРасхНаОплТр | C63: 0 | D63: 0 | E63: 0 | F63: 0 | H63: 0 | I63: 0 | J63: 0 | K63: 0 | L63: 0 | M63: 0 | N63: 0 | O63: 0 | P63: 0
A64: 81500100 | B64: СПД и директорство | C64: 0 | D64: 0 | E64: 0 | F64: 0 | H64: 0 | I64: 0 | J64: 0 | K64: 0 | L64: 0 | M64: 0 | N64: 0 | O64: 0 | P64: 0
A65: 82100000 | B65: Налоги на ФОТ | C65: -843313.31 | D65: -2.4170482e-05 | E65: -843313.31 | F65: -885042.98 | H65: -893545.99 | I65: -973913.79 | J65: 0 | K65: 0 | L65: 0 | M65: 0 | N65: 0 | O65: 0 | P65: 0
A66: 84210100 | B66: УслЦенБумагИС | C66: 0 | D66: 0 | E66: 0 | F66: 0 | H66: 0 | I66: 0 | J66: 0 | K66: 0 | L66: 0 | M66: 0 | N66: 0 | O66: 0 | P66: 0
A67: 1
A68: 1 | B68: 9. Персонал | C68: -35546.97 | D68: -1.0188235e-06 | E68: -35546.97 | F68: -46808.71 | H68: -65225.32 | I68: -68319.83 | J68: 0 | K68: 0 | L68: 0 | M68: 0 | N68: 0 | O68: 0 | P68: 0
A69: 81300000 | B69: КомпенсацВыплаты | C69: 0 | D69: 0 | E69: 0 | F69: 0 | H69: 0 | I69: 0 | J69: 0 | K69: 0 | L69: 0 | M69: 0 | N69: 0 | O69: 0 | P69: 0
A70: 81300100 | B70: КомпЗаИспЛичнТр | C70: 0 | D70: 0 | E70: 0 | F70: 0 | H70: -4500 | I70: -4500 | J70: 0 | K70: 0 | L70: 0 | M70: 0 | N70: 0 | O70: 0 | P70: 0
A71: 81300200 | B71: КомпКвартир | C71: 0 | D71: 0 | E71: 0 | F71: 0 | H71: 0 | I71: 0 | J71: 0 | K71: 0 | L71: 0 | M71: 0 | N71: 0 | O71: 0 | P71: 0
A72: 81300300 | B72: МатПомощьСотр | C72: 0 | D72: 0 | E72: 0 | F72: 0 | H72: 0 | I72: -6000 | J72: 0 | K72: 0 | L72: 0 | M72: 0 | N72: 0 | O72: 0 | P72: 0
A73: 81300400 | B73: МатПомНаПогребен | C73: 0 | D73: 0 | E73: 0 | F73: 0 | H73: 0 | I73: 0 | J73: 0 | K73: 0 | L73: 0 | M73: 0 | N73: 0 | O73: 0 | P73: 0
A74: 82400000 | B74: ОтчислНаИндивСтрах | C74: 0 | D74: 0 | E74: 0 | F74: 0 | H74: 0 | I74: 0 | J74: 0 | K74: 0 | L74: 0 | M74: 0 | N74: 0 | O74: 0 | P74: 0
A75: 84220100 | B75: ПерсоналПоиск | C75: 0 | D75: 0 | E75: 0 | F75: 0 | H75: 0 | I75: 0 | J75: 0 | K75: 0 | L75: 0 | M75: 0 | N75: 0 | O75: 0 | P75: 0
A76: 84220200 | B76: ПерсоналОбучВнутр | C76: 0 | D76: 0 | E76: 0 | F76: 0 | H76: 0 | I76: 0 | J76: 0 | K76: 0 | L76: 0 | M76: 0 | N76: 0 | O76: 0 | P76: 0
A77: 84220300 | B77: ПерсоналОбучВнешн | C77: 0 | D77: 0 | E77: 0 | F77: 0 | H77: -11885 | I77: 0 | J77: 0 | K77: 0 | L77: 0 | M77: 0 | N77: 0 | O77: 0 | P77: 0
A78: 84220400 | B78: Персонал медосмотры | C78: -520 | D78: -1.4903892e-08 | E78: -520 | F78: -3680 | H78: -4760 | I78: -13250 | J78: 0 | K78: 0 | L78: 0 | M78: 0 | N78: 0 | O78: 0 | P78: 0
A79: 84220500 | B79: ПерсоналСтажеры | C79: 0 | D79: 0 | E79: 0 | F79: 0 | H79: 0 | I79: 0 | J79: 0 | K79: 0 | L79: 0 | M79: 0 | N79: 0 | O79: 0 | P79: 0
... A82: 84220900 | B82: ПЕРСОН | C82: 0 | D82: 0 | E82: 0 | F82: 0 | H82: 0 | I82: 0 | J82: 0 | K82: 0 | L82: 0 | M82: 0 | N82: 0 | O82: 0 | P82: 0
A83: 1
A84: 1 | B84: 10. Аренда помещений | C84: -802733.33 | D84: -2.3007406e-05 | E84: -802733.33 | F84: -802733.33 | H84: -802733.33 | I84: -823566.66 | J84: 0 | K84: 0 | L84: 0 | M84: 0 | N84: 0 | O84: 0 | P84: 0
A85: 84160200 | B85: Аренда помещений | C85: -802733.33 | D85: -2.3007406e-05 | E85: -802733.33 | F85: -802733.33 | H85: -802733.33 | I85: -823566.66 | J85: 0 | K85: 0 | L85: 0 | M85: 0 | N85: 0 | O85: 0 | P85: 0
A86: 1
A87: 1 | B87: 11. Коммунальные услуги | C87: -757382.46 | D87: -2.170759e-05 | E87: -757382.46 | F87: -746300.23 | H87: -564883.64 | I87: -490833.02 | J87: 0 | K87: 0 | L87: 0 | M87: 0 | N87: 0 | O87: 0 | P87: 0
A88: 84030100 | B88: КомУслВода | C88: 0 | D88: 0 | E88: 0 | F88: 0 | H88: 0 | I88: 0 | J88: 0 | K88: 0 | L88: 0 | M88: 0 | N88: 0 | O88: 0 | P88: 0
A89: 84030200 | B89: КомУслВывОтходМус | C89: -18009.75 | D89: -5.1618341e-07 | E89: -18009.75 | F89: -15576 | H89: -16874 | I89: -17523 | J89: 0 | K89: 0 | L89: 0 | M89: 0 | N89: 0 | O89: 0 | P89: 0
A90: 84030300 | B90: КомУслГаз | C90: 0 | D90: 0 | E90: 0 | F90: 0 | H90: 0 | I90: 0 | J90: 0 | K90: 0 | L90: 0 | M90: 0 | N90: 0 | O90: 0 | P90: 0
A91: 84030400 | B91: КомУслОтопление | C91: 0 | D91: 0 | E91: 0 | F91: 0 | H91: 0 | I91: 0 | J91: 0 | K91: 0 | L91: 0 | M91: 0 | N91: 0 | O91: 0 | P91: 0
A92: 84030500 | B92: КомУслЭлектроэн | C92: -737462.02 | D92: -2.1136643e-05 | E92: -737462.02 | F92: -728813.54 | H92: -546098.95 | I92: -471399.33 | J92: 0 | K92: 0 | L92: 0 | M92: 0 | N92: 0 | O92: 0 | P92: 0
A93: 84030600 | B93: ЭксплуатПрочиеКомун | C93: -1910.69 | D93: -5.4762919e-08 | E93: -1910.69 | F93: -1910.69 | H93: -1910.69 | I93: -1910.69 | J93: 0 | K93: 0 | L93: 0 | M93: 0 | N93: 0 | O93: 0 | P93: 0
A94: 84030800 | B94: КомУслЭлВозмещГенер. | C94: 0 | D94: 0 | E94: 0 | F94: 0 | H94: 0 | I94: 0 | J94: 0 | K94: 0 | L94: 0 | M94: 0 | N94: 0 | O94: 0 | P94: 0
A95: 80300100 | B95: РасхГСМ Тех.ИПр.нужд | C95: 0 | D95: 0 | E95: 0 | F95: 0 | H95: 0 | I95: 0 | J95: 0 | K95: 0 | L95: 0 | M95: 0 | N95: 0 | O95: 0 | P95: 0
A96: 1
A97: 1 | B97: 12. Логистика | C97: -56200.06 | D97: -1.6107685e-06 | E97: -56200.06 | F97: -52453.51 | H97: -65502.92 | I97: -60441.65 | J97: 0 | K97: 0 | L97: 0 | M97: 0 | N97: 0 | O97: 0 | P97: 0
A98: 84020100 | B98: Транспортные услуги | C98: -50892.66 | D98: -1.4586514e-06 | E98: -50892.66 | F98: -45886.14 | H98: -54455.31 | I98: -53296.58 | J98: 0 | K98: 0 | L98: 0 | M98: 0 | N98: 0 | O98: 0 | P98: 0
A99: 84020200 | B99: Логистика | C99: 0 | D99: 0 | E99: 0 | F99: 0 | H99: 0 | I99: 0 | J99: 0 | K99: 0 | L99: 0 | M99: 0 | N99: 0 | O99: 0 | P99: 0
A100: 84020300 | B100: ПрочУслСкладХоз | C100: -5307.4 | D100: -1.5211715e-07 | E100: -5307.4 | F100: -6567.37 | H100: -11047.61 | I100: -7145.07 | J100: 0 | K100: 0 | L100: 0 | M100: 0 | N100: 0 | O100: 0 | P100: 0
A101: 1
A102: 1 | B102: 13. Материалы | C102: -709486.92 | D102: -2.033484e-05 | E102: -709486.92 | F102: -864172 | H102: -1082284.4 | I102: -1219663.3 | J102: 0 | K102: 0 | L102: 0 | M102: 0 | N102: 0 | O102: 0 | P102: 0
...

Sheet квітень
A1: КЛО_МРЦ | B1: Киев,Фора МРЦ Оросительная,5 | C1: ИТОГО 2024 | D1: % К ОБОРОТУ | E1: 45658 | F1: 45689 | G1: 45717 | H1: 45383 | I1: 45778 | J1: 45809 | K1: 45839 | L1: 45870 | M1: 45901 | N1: 45931 | O1: 45962 | P1: 45992
A2: Доходы
A3: Код | B3: 1. Выручка | C3: 185581.79 | D3: 4.1113201e-06 | E3: 56312.5 | F3: 43272.3 | G3: 43860.04 | H3: 42136.95 | I3: 0 | J3: 0 | K3: 0 | L3: 0 | M3: 0 | N3: 0 | O3: 0 | P3: 0
A4: 70200000 | B4: ДоходРеалТовара | C4: 185581.79 | D4: 4.1113201e-06 | E4: 56312.5 | F4: 43272.3 | G4: 43860.04 | H4: 42136.95 | I4: 0 | J4: 0 | K4: 0 | L4: 0 | M4: 0 | N4: 0 | O4: 0 | P4: 0
A5: 70200001 | B5: ДоходРеалПрогрЛояльн | C5: 0 | D5: 0 | E5: 0 | F5: 0 | G5: 0 | H5: 0 | I5: 0 | J5: 0 | K5: 0 | L5: 0 | M5: 0 | N5: 0 | O5: 0 | P5: 0
A6: 70200002 | B6: ДоходРеалТВаучера | C6: 0 | D6: 0 | E6: 0 | F6: 0 | G6: 0 | H6: 0 | I6: 0 | J6: 0 | K6: 0 | L6: 0 | M6: 0 | N6: 0 | O6: 0 | P6: 0
A7: 70200003 | B7: ДоходРеалТовКомиссия | C7: 0 | D7: 0 | E7: 0 | F7: 0 | G7: 0 | H7: 0 | I7: 0 | J7: 0 | K7: 0 | L7: 0 | M7: 0 | N7: 0 | O7: 0 | P7: 0
A8: 70200004 | B8: ДоходРеалАгентсДог | C8: 0 | D8: 0 | E8: 0 | F8: 0 | G8: 0 | H8: 0 | I8: 0 | J8: 0 | K8: 0 | L8: 0 | M8: 0 | N8: 0 | O8: 0 | P8: 0
A9: 70200009 | B9: Недополучен.выручка | C9: 0 | D9: 0 | E9: 0 | F9: 0 | G9: 0 | H9: 0 | I9: 0 | J9: 0 | K9: 0 | L9: 0 | M9: 0 | N9: 0 | O9: 0 | P9: 0
A10: 70200200 | B10: ДоходРеалТовЭкспорт | C10: 0 | D10: 0 | E10: 0 | F10: 0 | G10: 0 | H10: 0 | I10: 0 | J10: 0 | K10: 0 | L10: 0 | M10: 0 | N10: 0 | O10: 0 | P10: 0
A11: 70400000 | B11: ВычетыДоходТовар | C11: 0 | D11: 0 | E11: 0 | F11: 0 | G11: 0 | H11: 0 | I11: 0 | J11: 0 | K11: 0 | L11: 0 | M11: 0 | N11: 0 | O11: 0 | P11: 0
A12: 70430000 | B12: ВычетыДоходАгентсДог | C12: 0 | D12: 0 | E12: 0 | F12: 0 | G12: 0 | H12: 0 | I12: 0 | J12: 0 | K12: 0 | L12: 0 | M12: 0 | N12: 0 | O12: 0 | P12: 0
A13: 1
A14: 1 | B14: 2. Себестоимость | C14: -204426.27 | D14: -4.0635167e-06 | E14: -63168.81 | F14: -27005.75 | G14: -51602.41 | H14: -62649.3 | I14: 0 | J14: 0 | K14: 0 | L14: 0 | M14: 0 | N14: 0 | O14: 0 | P14: 0
A15: 90200000 | B15: СебестРеализТоваров | C15: -27.4 | D15: -7.8532048e-10 | E15: 0 | F15: -27.4 | G15: 0 | H15: 0 | I15: 0 | J15: 0 | K15: 0 | L15: 0 | M15: 0 | N15: 0 | O15: 0 | P15: 0
A16: 90200001 | B16: СебестРеалТоваровПро | C16: -204398.87 | D16: -4.0627314e-06 | E16: -63168.81 | F16: -26978.35 | G16: -51602.41 | H16: -62649.3 | I16: 0 | J16: 0 | K16: 0 | L16: 0 | M16: 0 | N16: 0 | O16: 0 | P16: 0
A17: 1
A18: 1 | B18: 3. Валовая маржа | C18: -18844.48 | D18: 4.7803375e-08 | E18: -6856.31 | F18: 16266.55 | G18: -7742.37 | H18: -20512.35 | I18: 0 | J18: 0 | K18: 0 | L18: 0 | M18: 0 | N18: 0 | O18: 0 | P18: 0
A19: 1
A20: 1 | B20: 4. Бонусы | C20: 0 | D20: 0 | E20: 0 | F20: 0 | G20: 0 | H20: 0 | I20: 0 | J20: 0 | K20: 0 | L20: 0 | M20: 0 | N20: 0 | O20: 0 | P20: 0
A21: 71900700 | B21: ДоходОтБонусов | C21: 0 | D21: 0 | E21: 0 | F21: 0 | G21: 0 | H21: 0 | I21: 0 | J21: 0 | K21: 0 | L21: 0 | M21: 0 | N21: 0 | O21: 0 | P21: 0
A22: 1
A23: 1 | B23: 5. Прочее - Доходы | C23: 7981713.7 | D23: 0 | E23: 3105094.5 | F23: 1605268.9 | G23: 1724627.5 | H23: 1546722.8 | I23: 0 | J23: 0 | K23: 0 | L23: 0 | M23: 0 | N23: 0 | O23: 0 | P23: 0
A24: 70300000 | B24: ДоходРеалРабУсл | C24: 0 | D24: 0 | E24: 0 | F24: 0 | G24: 0 | H24: 0 | I24: 0 | J24: 0 | K24: 0 | L24: 0 | M24: 0 | N24: 0 | O24: 0 | P24: 0
A25: 70300200 | B25: ДохРазмРеклСобствНН | C25: 0 | D25: 0 | E25: 0 | F25: 0 | G25: 0 | H25: 0 | I25: 0 | J25: 0 | K25: 0 | L25: 0 | M25: 0 | N25: 0 | O25: 0 | P25: 0
A26: 70300700 | B26: ДохРеалУслЛогист | C26: 0 | D26: 0 | E26: 0 | F26: 0 | G26: 0 | H26: 0 | I26: 0 | J26: 0 | K26: 0 | L26: 0 | M26: 0 | N26: 0 | O26: 0 | P26: 0
A27: 70300800 | B27: ДоходДогКомиссии | C27: 0 | D27: 0 | E27: 0 | F27: 0 | G27: 0 | H27: 0 | I27: 0 | J27: 0 | K27: 0 | L27: 0 | M27: 0 | N27: 0 | O27: 0 | P27: 0
A28: 70300900 | B28: ДоходУслугКонечнПотр | C28: 0 | D28: 0 | E28: 0 | F28: 0 | G28: 0 | H28: 0 | I28: 0 | J28: 0 | K28: 0 | L28: 0 | M28: 0 | N28: 0 | O28: 0 | P28: 0
A29: 71200000 | B29: ДохРеалПрочОбАкт | C29: 0 | D29: 0 | E29: 0 | F29: 0 | G29: 0 | H29: 0 | I29: 0 | J29: 0 | K29: 0 | L29: 0 | M29: 0 | N29: 0 | O29: 0 | P29: 0
A30: 71200100 | B30: ДохРеалМакулатуры | C30: 23774.8 | D30: 2.8409112e-07 | E30: 0 | F30: 0 | G30: 9912 | H30: 13862.8 | I30: 0 | J30: 0 | K30: 0 | L30: 0 | M30: 0 | N30: 0 | O30: 0 | P30: 0
A31: 71300000 | B31: ДохАренОборудован | C31: 0 | D31: 0 | E31: 0 | F31: 0 | G31: 0 | H31: 0 | I31: 0 | J31: 0 | K31: 0 | L31: 0 | M31: 0 | N31: 0 | O31: 0 | P31: 0
A32: 71300200 | B32: ДохАренТранспорта | C32: 0 | D32: 0 | E32: 0 | F32: 0 | G32: 0 | H32: 0 | I32: 0 | J32: 0 | K32: 0 | L32: 0 | M32: 0 | N32: 0 | O32: 0 | P32: 0
A33: 71500000 | B33: ПолучШтрафПени | C33: 0 | D33: 0 | E33: 0 | F33: 0 | G33: 0 | H33: 0 | I33: 0 | J33: 0 | K33: 0 | L33: 0 | M33: 0 | N33: 0 | O33: 0 | P33: 0
A34: 71500100 | B34: ОтримШтрафиПеніКомер | D34: 0
A35: 71700000 | B35: ДохСписКредЗадолж | C35: 0 | D35: 0 | E35: 0 | F35: 0 | G35: 0 | H35: 0 | I35: 0 | J35: 0 | K35: 0 | L35: 0 | M35: 0 | N35: 0 | O35: 0 | P35: 0
A36: 71800000 | B36: ДохБесплПолОборАкт | C36: 0 | D36: 0 | E36: 0 | F36: 0 | G36: 0 | H36: 0 | I36: 0 | J36: 0 | K36: 0 | L36: 0 | M36: 0 | N36: 0 | O36: 0 | P36: 0
A37: 71800400 | B37: ДохБесплПолАктив.РЦ | C37: 0 | D37: 0 | E37: 0 | F37: 0 | G37: 0 | H37: 0 | I37: 0 | J37: 0 | K37: 0 | L37: 0 | M37: 0 | N37: 0 | O37: 0 | P37: 0
A38: 71900000 | B38: ПрочДоходОперДеят | C38: 7957938.9 | D38: 0 | E38: 3105094.5 | F38: 1605268.9 | G38: 1714715.5 | H38: 1532860 | I38: 0 | J38: 0 | K38: 0 | L38: 0 | M38: 0 | N38: 0 | O38: 0 | P38: 0
A39: 71900100 | B39: ПрочДоход% банка | C39: 0 | D39: 0 | E39: 0 | F39: 0 | G39: 0 | H39: 0 | I39: 0 | J39: 0 | K39: 0 | L39: 0 | M39: 0 | N39: 0 | O39: 0 | P39: 0
A40: 71900500 | B40: ПрДоходИзлишки кассы | C40: 0 | D40: 0 | E40: 0 | F40: 0 | G40: 0 | H40: 0 | I40: 0 | J40: 0 | K40: 0 | L40: 0 | M40: 0 | N40: 0 | O40: 0 | P40: 0
A41: 71900600 | B41: Доход гостинич услуг | C41: 0 | D41: 0 | E41: 0 | F41: 0 | G41: 0 | H41: 0 | I41: 0 | J41: 0 | K41: 0 | L41: 0 | M41: 0 | N41: 0 | O41: 0 | P41: 0
A42: 71900900 | B42: ДохідСтраховВідшк | D42: 0
A43: 71901000 | B43: ІнДоход%депозит | C43: 0 | D43: 0 | E43: 0 | F43: 0 | G43: 0 | H43: 0 | I43: 0 | J43: 0 | K43: 0 | L43: 0 | M43: 0 | N43: 0 | O43: 0 | P43: 0
A44: 1
A45: 1 | B45: 6. Прочие доходы аренда | C45: 20000 | D45: 4.2991997e-07 | E45: 5000 | F45: 5000 | G45: 5000 | H45: 5000 | I45: 0 | J45: 0 | K45: 0 | L45: 0 | M45: 0 | N45: 0 | O45: 0 | P45: 0
A46: 71300100 | B46: ДохАренПомещений | C46: 20000 | D46: 4.2991997e-07 | E46: 5000 | F46: 5000 | G46: 5000 | H46: 5000 | I46: 0 | J46: 0 | K46: 0 | L46: 0 | M46: 0 | N46: 0 | O46: 0 | P46: 0
A47: 71900400 | B47: ВозмещКомЭксплЗатрат | C47: 0 | D47: 0 | E47: 0 | F47: 0 | G47: 0 | H47: 0 | I47: 0 | J47: 0 | K47: 0 | L47: 0 | M47: 0 | N47: 0 | O47: 0 | P47: 0
A48: 1
A49: 1 | B49: Валовая прибыль | C49: 7982869.2 | D49: 0.00018491313 | E49: 3103238.2 | F49: 1626535.4 | G49: 1721885.1 | H49: 1531210.4 | I49: 0 | J49: 0 | K49: 0 | L49: 0 | M49: 0 | N49: 0 | O49: 0 | P49: 0
A50: Затраты
A51: 1 | B51: 7. Списания и переучеты | C51: -10799799 | D51: -3.8829612e-06 | E51: -1544187 | F51: -3615388.6 | G51: -2556959.6 | H51: -3083264.3 | I51: 0 | J51: 0 | K51: 0 | L51: 0 | M51: 0 | N51: 0 | O51: 0 | P51: 0
A52: 80810000 | B52: РасхТоварПереуч | C52: 42131.1 | D52: 0 | E52: 2987.1 | F52: 32732.23 | G52: 3779.06 | H52: 2632.71 | I52: 0 | J52: 0 | K52: 0 | L52: 0 | M52: 0 | N52: 0 | O52: 0 | P52: 0
A53: 80810001 | B53: РасхМатПереучетПроиз | C53: -760261.03 | D53: 0 | E53: 1930883.7 | F53: -1270673.2 | G53: -351132.89 | H53: -1069338.6 | I53: 0 | J53: 0 | K53: 0 | L53: 0 | M53: 0 | N53: 0 | O53: 0 | P53: 0
A54: 80820000 | B54: РасхТоварПотериСпис | C54: 0 | D54: 0 | E54: 0 | F54: 0 | G54: 0 | H54: 0 | I54: 0 | J54: 0 | K54: 0 | L54: 0 | M54: 0 | N54: 0 | O54: 0 | P54: 0
A55: 80820001 | B55: РасхМатПотПоСписПр | C55: -10081670 | D55: 0 | E55: -3478057.7 | F55: -2377447.6 | G55: -2209605.7 | H55: -2016558.4 | I55: 0 | J55: 0 | K55: 0 | L55: 0 | M55: 0 | N55: 0 | O55: 0 | P55: 0
A56: 1
A57: 1 | B57: 8. ФОТ, в т.ч. налоги | C57: -31119080 | D57: -3.8829612e-06 | E57: -8062860.9 | F57: -7376629.3 | G57: -7593884.1 | H57: -8085705.2 | I57: 0 | J57: 0 | K57: 0 | L57: 0 | M57: 0 | N57: 0 | O57: 0 | P57: 0
A58: 81100000 | B58: РасхОплТрОклады | C58: -26414098 | D58: 0 | E58: -6933558.5 | F58: -6161991.5 | G58: -6469881 | H58: -6848666.5 | I58: 0 | J58: 0 | K58: 0 | L58: 0 | M58: 0 | N58: 0 | O58: 0 | P58: 0
A59: 81100100 | B59: Оплата Моб,ТРО | C59: -271960 | D59: 0 | E59: -67990 | F59: -67990 | G59: -67990 | H59: -67990 | I59: 0 | J59: 0 | K59: 0 | L59: 0 | M59: 0 | N59: 0 | O59: 0 | P59: 0
A60: 81200000 | B60: ПремииПоощрения | C60: 0 | D60: 0 | E60: 0 | F60: 0 | G60: 0 | H60: 0 | I60: 0 | J60: 0 | K60: 0 | L60: 0 | M60: 0 | N60: 0 | O60: 0 | P60: 0
A61: 81400000 | B61: Оплата отпусков | C61: -965639.31 | D61: 0 | E61: -217999.17 | F61: -261604.75 | G61: -210532.73 | H61: -275502.66 | I61: 0 | J61: 0 | K61: 0 | L61: 0 | M61: 0 | N61: 0 | O61: 0 | P61: 0
A62: 81500000 | B62: ПрочРасхНаОплТр | C62: 0 | D62: 0 | E62: 0 | F62: 0 | G62: 0 | H62: 0 | I62: 0 | J62: 0 | K62: 0 | L62: 0 | M62: 0 | N62: 0 | O62: 0 | P62: 0
A63: 81500100 | B63: СПД и директорство | C63: 0 | D63: 0 | E63: 0 | F63: 0 | G63: 0 | H63: 0 | I63: 0 | J63: 0 | K63: 0 | L63: 0 | M63: 0 | N63: 0 | O63: 0 | P63: 0
A64: 82100000 | B64: Налоги на ФОТ | C64: -3467382.7 | D64: 0 | E64: -843313.31 | F64: -885042.98 | G64: -845480.46 | H64: -893545.99 | I64: 0 | J64: 0 | K64: 0 | L64: 0 | M64: 0 | N64: 0 | O64: 0 | P64: 0
A65: 84210100 | B65: УслЦенБумагИС | C65: 0 | D65: 0 | E65: 0 | F65: 0 | G65: 0 | H65: 0 | I65: 0 | J65: 0 | K65: 0 | L65: 0 | M65: 0 | N65: 0 | O65: 0 | P65: 0
A66: 1
A67: 1 | B67: 9. Персонал | C67: -200702.67 | D67: 0 | E67: -35546.97 | F67: -46808.71 | G67: -53121.67 | H67: -65225.32 | I67: 0 | J67: 0 | K67: 0 | L67: 0 | M67: 0 | N67: 0 | O67: 0 | P67: 0
A68: 81300000 | B68: КомпенсацВыплаты | C68: 0 | D68: 0 | E68: 0 | F68: 0 | G68: 0 | H68: 0 | I68: 0 | J68: 0 | K68: 0 | L68: 0 | M68: 0 | N68: 0 | O68: 0 | P68: 0
A69: 81300100 | B69: КомпЗаИспЛичнТр | C69: -9000 | D69: 0 | E69: 0 | F69: 0 | G69: -4500 | H69: -4500 | I69: 0 | J69: 0 | K69: 0 | L69: 0 | M69: 0 | N69: 0 | O69: 0 | P69: 0
A70: 81300200 | B70: КомпКвартир | C70: 0 | D70: 0 | E70: 0 | F70: 0 | G70: 0 | H70: 0 | I70: 0 | J70: 0 | K70: 0 | L70: 0 | M70: 0 | N70: 0 | O70: 0 | P70: 0
A71: 81300300 | B71: МатПомощьСотр | C71: 0 | D71: 0 | E71: 0 | F71: 0 | G71: 0 | H71: 0 | I71: 0 | J71: 0 | K71: 0 | L71: 0 | M71: 0 | N71: 0 | O71: 0 | P71: 0
A72: 81300400 | B72: МатПомНаПогребен | C72: 0 | D72: 0 | E72: 0 | F72: 0 | G72: 0 | H72: 0 | I72: 0 | J72: 0 | K72: 0 | L72: 0 | M72: 0 | N72: 0 | O72: 0 | P72: 0
A73: 82400000 | B73: ОтчислНаИндивСтрах | C73: 0 | D73: 0 | E73: 0 | F73: 0 | G73: 0 | H73: 0 | I73: 0 | J73: 0 | K73: 0 | L73: 0 | M73: 0 | N73: 0 | O73: 0 | P73: 0
A74: 84220100 | B74: ПерсоналПоиск | C74: 0 | D74: 0 | E74: 0 | F74: 0 | G74: 0 | H74: 0 | I74: 0 | J74: 0 | K74: 0 | L74: 0 | M74: 0 | N74: 0 | O74: 0 | P74: 0
A75: 84220200 | B75: ПерсоналОбучВнутр | C75: 0 | D75: 0 | E75: 0 | F75: 0 | G75: 0 | H75: 0 | I75: 0 | J75: 0 | K75: 0 | L75: 0 | M75: 0 | N75: 0 | O75: 0 | P75: 0
A76: 84220300 | B76: ПерсоналОбучВнешн | C76: -11885 | D76: 0 | E76: 0 | F76: 0 | G76: 0 | H76: -11885 | I76: 0 | J76: 0 | K76: 0 | L76: 0 | M76: 0 | N76: 0 | O76: 0 | P76: 0
A77: 84220400 | B77: Персонал медосмотры | C77: -14190 | D77: 0 | E77: -520 | F77: -3680 | G77: -5230 | H77: -4760 | I77: 0 | J77: 0 | K77: 0 | L77: 0 | M77: 0 | N77: 0 | O77: 0 | P77: 0
A78: 84220500 | B78: ПерсоналСтажеры | C78: 0 | D78: 0 | E78: 0 | F78: 0 | G78: 0 | H78: 0 | I78: 0 | J78: 0 | K78: 0 | L78: 0 | M78: 0 | N78: 0 | O78: 0 | P78: 0
... A81: 84220900 | B81: ПЕРСОН | C81: 0 | D81: 0 | E81: 0 | F81: 0 | G81: 0 | H81: 0 | I81: 0 | J81: 0 | K81: 0 | L81: 0 | M81: 0 | N81: 0 | O81: 0 | P81: 0
A82: 1
A83: 1 | B83: 10. Аренда помещений | C83: -3210933.3 | D83: 0 | E83: -802733.33 | F83: -802733.33 | G83: -802733.33 | H83: -802733.33 | I83: 0 | J83: 0 | K83: 0 | L83: 0 | M83: 0 | N83: 0 | O83: 0 | P83: 0
A84: 84160200 | B84: Аренда помещений | C84: -3210933.3 | D84: 0 | E84: -802733.33 | F84: -802733.33 | G84: -802733.33 | H84: -802733.33 | I84: 0 | J84: 0 | K84: 0 | L84: 0 | M84: 0 | N84: 0 | O84: 0 | P84: 0
A85: 1
A86: 1 | B86: 11. Коммунальные услуги | C86: -2788643.9 | D86: -6.373593e-05 | E86: -757382.46 | F86: -746300.23 | G86: -720077.57 | H86: -564883.64 | I86: 0 | J86: 0 | K86: 0 | L86: 0 | M86: 0 | N86: 0 | O86: 0 | P86: 0
A87: 84030100 | B87: КомУслВода | C87: 0 | D87: 0 | E87: 0 | F87: 0 | G87: 0 | H87: 0 | I87: 0 | J87: 0 | K87: 0 | L87: 0 | M87: 0 | N87: 0 | O87: 0 | P87: 0
A88: 84030200 | B88: КомУслВывОтходМус | C88: -67333.75 | D88: -1.4462436e-06 | E88: -18009.75 | F88: -15576 | G88: -16874 | H88: -16874 | I88: 0 | J88: 0 | K88: 0 | L88: 0 | M88: 0 | N88: 0 | O88: 0 | P88: 0
A89: 84030300 | B89: КомУслГаз | C89: 0 | D89: 0 | E89: 0 | F89: 0 | G89: 0 | H89: 0 | I89: 0 | J89: 0 | K89: 0 | L89: 0 | M89: 0 | N89: 0 | O89: 0 | P89: 0
A90: 84030400 | B90: КомУслОтопление | C90: 0 | D90: -4.3387308e-06 | E90: 0 | F90: 0 | G90: 0 | H90: 0 | I90: 0 | J90: 0 | K90: 0 | L90: 0 | M90: 0 | N90: 0 | O90: 0 | P90: 0
A91: 84030500 | B91: КомУслЭлектроэн | C91: -2713667.4 | D91: -5.7849745e-06 | E91: -737462.02 | F91: -728813.54 | G91: -701292.88 | H91: -546098.95 | I91: 0 | J91: 0 | K91: 0 | L91: 0 | M91: 0 | N91: 0 | O91: 0 | P91: 0
A92: 84030600 | B92: ЭксплуатПрочиеКомун | C92: -7642.76 | D92: -7.2312181e-06 | E92: -1910.69 | F92: -1910.69 | G92: -1910.69 | H92: -1910.69 | I92: 0 | J92: 0 | K92: 0 | L92: 0 | M92: 0 | N92: 0 | O92: 0 | P92: 0
A93: 84030800 | B93: КомУслЭлВозмещГенер. | C93: 0 | D93: -8.6774617e-06 | E93: 0 | F93: 0 | G93: 0 | H93: 0 | I93: 0 | J93: 0 | K93: 0 | L93: 0 | M93: 0 | N93: 0 | O93: 0 | P93: 0
A94: 80300100 | B94: РасхГСМ Тех.ИПр.нужд | C94: 0 | D94: -1.0123705e-05 | E94: 0 | F94: 0 | G94: 0 | H94: 0 | I94: 0 | J94: 0 | K94: 0 | L94: 0 | M94: 0 | N94: 0 | O94: 0 | P94: 0
A95: 1
A96: 1 | B96: 12. Логистика | C96: -234653.84 | D96: -4.8480906e-06 | E96: -56200.06 | F96: -52453.51 | G96: -60497.35 | H96: -65502.92 | I96: 0 | J96: 0 | K96: 0 | L96: 0 | M96: 0 | N96: 0 | O96: 0 | P96: 0
A97: 84020100 | B97: Транспортные услуги | C97: -204746.77 | D97: -4.3075533e-06 | E97: -50892.66 | F97: -45886.14 | G97: -53512.66 | H97: -54455.31 | I97: 0 | J97: 0 | K97: 0 | L97: 0 | M97: 0 | N97: 0 | O97: 0 | P97: 0
A98: 84020200 | B98: Логистика | C98: 0 | D98: 0 | E98: 0 | F98: 0 | G98: 0 | H98: 0 | I98: 0 | J98: 0 | K98: 0 | L98: 0 | M98: 0 | N98: 0 | O98: 0 | P98: 0
A99: 84020300 | B99: ПрочУслСкладХоз | C99: -29907.07 | D99: -5.4053723e-07 | E99: -5307.4 | F99: -6567.37 | G99: -6984.69 | H99: -11047.61 | I99: 0 | J99: 0 | K99: 0 | L99: 0 | M99: 0 | N99: 0 | O99: 0 | P99: 0
A100: 1
A101: 1 | B101: 13. Материалы | C101: -3466184.1 | D101: -6.8325738e-05 | E101: -709486.92 | F101: -864172 | G101: -810240.72 | H101: -1082284.4 | I101: 0 | J101: 0 | K101: 0 | L101: 0 | M101: 0 | N101: 0 | O101: 0 | P101: 0
A102: 80300000 | B102: РасхТоплСмазочМатер | C102: -53469.61 | D102: -1.1774648e-06 | E102: -15973.81 | F102: -12592.88 | G102: -12515.31 | H102: -12387.61 | I102: 0 | J102: 0 | K102: 0 | L102: 0 | M102: 0 | N102: 0 | O102: 0 | P102: 0
...

Sheet червень
I1: 45658 | J1: 45689 | K1: 45717 | L1: 45748 | M1: 45778 | N1: 45809 | O1: 45839 | P1: 45870 | Q1: 45901 | R1: 45931 | S1: 45962 | T1: 45992
A2: 2 | E2: КЛО_МРЦ | F2: Киев,Фора МРЦ Оросительная,5 | G2: ИТОГО 2024 | H2: % К ОБОРОТУ | I2: 45658 | J2: 45689 | K2: 45717 | L2: 45383 | M2: 45778 | N2: 45809 | O2: 45839 | P2: 45870 | Q2: 45901 | R2: 45931 | S2: 45962 | T2: 45992
A3: 3 | B3: КЛО_МРЦДоходы | E3: Доходы
A4: 4 | C4: mapping Бюджет | D4: Разбивка по Офисам | E4: Код | F4: 1. Выручка | G4: 348023.38 | H4: 4.1113201e-06 | I4: 56312.5 | J4: 43272.3 | K4: 43860.04 | L4: 42136.95 | M4: 133672.61 | N4: 28768.98 | O4: 0 | P4: 0 | Q4: 0 | R4: 0 | S4: 0 | T4: 0
A5: 5 | B5: КЛО_МРЦ70200000 | C5: Валовая прибыль (без бонусов) | D5: ВСЕ | E5: 70200000 | F5: ДоходРеалТовара | G5: 348023.38 | H5: 4.1113201e-06 | I5: 56312.5 | J5: 43272.3 | K5: 43860.04 | L5: 42136.95 | M5: 133672.61 | N5: 28768.98 | O5: 0 | P5: 0 | Q5: 0 | R5: 0 | S5: 0 | T5: 0
A6: 6 | B6: КЛО_МРЦ70200001 | C6: Валовая прибыль (без бонусов) | D6: МАРКЕТИНГ | E6: 70200001 | F6: ДоходРеалПрогрЛояльн | G6: 0 | H6: 0 | I6: 0 | J6: 0 | K6: 0 | L6: 0 | M6: 0 | N6: 0 | O6: 0 | P6: 0 | Q6: 0 | R6: 0 | S6: 0 | T6: 0
A7: 7 | B7: КЛО_МРЦ70200002 | C7: Валовая прибыль (без бонусов) | D7: МАРКЕТИНГ | E7: 70200002 | F7: ДоходРеалТВаучера | G7: 0 | H7: 0 | I7: 0 | J7: 0 | K7: 0 | L7: 0 | M7: 0 | N7: 0 | O7: 0 | P7: 0 | Q7: 0 | R7: 0 | S7: 0 | T7: 0
A8: 8 | B8: КЛО_МРЦ70200003 | C8: Валовая прибыль (без бонусов) | E8: 70200003 | F8: ДоходРеалТовКомиссия | G8: 0 | H8: 0 | I8: 0 | J8: 0 | K8: 0 | L8: 0 | M8: 0 | N8: 0 | O8: 0 | P8: 0 | Q8: 0 | R8: 0 | S8: 0 | T8: 0
A9: 9 | B9: КЛО_МРЦ70200004 | C9: Валовая прибыль (без бонусов) | D9: Дирекция | E9: 70200004 | F9: ДоходРеалАгентсДог | G9: 0 | H9: 0 | I9: 0 | J9: 0 | K9: 0 | L9: 0 | M9: 0 | N9: 0 | O9: 0 | P9: 0 | Q9: 0 | R9: 0 | S9: 0 | T9: 0
A10: 10 | B10: КЛО_МРЦ70200009 | C10: Валовая прибыль (без бонусов) | D10: Дирекция | E10: 70200009 | F10: Недополучен.выручка | G10: 0 | H10: 0 | I10: 0 | J10: 0 | K10: 0 | L10: 0 | M10: 0 | N10: 0 | O10: 0 | P10: 0 | Q10: 0 | R10: 0 | S10: 0 | T10: 0
A11: 11 | B11: КЛО_МРЦ70200200 | C11: Валовая прибыль (без бонусов) | D11: Дирекция | E11: 70200200 | F11: ДоходРеалТовЭкспорт | G11: 0 | H11: 0 | I11: 0 | J11: 0 | K11: 0 | L11: 0 | M11: 0 | N11: 0 | O11: 0 | P11: 0 | Q11: 0 | R11: 0 | S11: 0 | T11: 0
A12: 12 | B12: КЛО_МРЦ70400000 | C12: Валовая прибыль (без бонусов) | D12: Дирекция | E12: 70400000 | F12: ВычетыДоходТовар | G12: 0 | H12: 0 | I12: 0 | J12: 0 | K12: 0 | L12: 0 | M12: 0 | N12: 0 | O12: 0 | P12: 0 | Q12: 0 | R12: 0 | S12: 0 | T12: 0
A13: 13 | B13: КЛО_МРЦ70430000 | C13: Валовая прибыль (без бонусов) | D13: Дирекция | E13: 70430000 | F13: ВычетыДоходАгентсДог | G13: 0 | H13: 0 | I13: 0 | J13: 0 | K13: 0 | L13: 0 | M13: 0 | N13: 0 | O13: 0 | P13: 0 | Q13: 0 | R13: 0 | S13: 0 | T13: 0
A14: 14 | E14: 1
A15: 15 | E15: 1 | F15: 2. Себестоимость | G15: -355115.64 | H15: -4.0635167e-06 | I15: -63168.81 | J15: -27005.75 | K15: -51602.41 | L15: -62649.3 | M15: -108767.59 | N15: -41921.78 | O15: 0 | P15: 0 | Q15: 0 | R15: 0 | S15: 0 | T15: 0
A16: 16 | B16: КЛО_МРЦ90200000 | C16: Валовая прибыль (без бонусов) | D16: КЛО | E16: 90200000 | F16: СебестРеализТоваров | G16: -19324.39 | H16: -7.8532048e-10 | I16: 0 | J16: -27.4 | K16: 0 | L16: 0 | M16: -19296.99 | N16: 0 | O16: 0 | P16: 0 | Q16: 0 | R16: 0 | S16: 0 | T16: 0
A17: 17 | B17: КЛО_МРЦ90200001 | C17: Валовая прибыль (без бонусов) | D17: КЛО | E17: 90200001 | F17: СебестРеалТоваровПро | G17: -335791.25 | H17: -4.0627314e-06 | I17: -63168.81 | J17: -26978.35 | K17: -51602.41 | L17: -62649.3 | M17: -89470.6 | N17: -41921.78 | O17: 0 | P17: 0 | Q17: 0 | R17: 0 | S17: 0 | T17: 0
A18: 18 | E18: 1
A19: 19 | E19: 1 | F19: 3. Валовая маржа | G19: -7092.26 | H19: 4.7803375e-08 | I19: -6856.31 | J19: 16266.55 | K19: -7742.37 | L19: -20512.35 | M19: 24905.02 | N19: -13152.8 | O19: 0 | P19: 0 | Q19: 0 | R19: 0 | S19: 0 | T19: 0
A20: 20 | E20: 1
A21: 21 | E21: 1 | F21: 4. Бонусы | G21: 0 | H21: 0 | I21: 0 | J21: 0 | K21: 0 | L21: 0 | M21: 0 | N21: 0 | O21: 0 | P21: 0 | Q21: 0 | R21: 0 | S21: 0 | T21: 0
A22: 22 | B22: КЛО_МРЦ71900700 | C22: Бонусы | D22: КЛО | E22: 71900700 | F22: ДоходОтБонусов | G22: 0 | H22: 0 | I22: 0 | J22: 0 | K22: 0 | L22: 0 | M22: 0 | N22: 0 | O22: 0 | P22: 0 | Q22: 0 | R22: 0 | S22: 0 | T22: 0
A23: 23 | E23: 1
A24: 24 | E24: 1 | F24: 5. Прочее - Доходы | G24: 13044252 | H24: 0 | I24: 3105094.5 | J24: 1605268.9 | K24: 1724627.5 | L24: 1546722.8 | M24: 2920354.5 | N24: 2142183.6 | O24: 0 | P24: 0 | Q24: 0 | R24: 0 | S24: 0 | T24: 0
A25: 25 | B25: КЛО_МРЦ70300000 | C25: Прочие доходы | D25: МАРКЕТИНГ | E25: 70300000 | F25: ДоходРеалРабУсл | G25: 0 | H25: 0 | I25: 0 | J25: 0 | K25: 0 | L25: 0 | M25: 0 | N25: 0 | O25: 0 | P25: 0 | Q25: 0 | R25: 0 | S25: 0 | T25: 0
A26: 26 | B26: КЛО_МРЦ70300200 | C26: Прочие доходы | D26: МАРКЕТИНГ | E26: 70300200 | F26: ДохРазмРеклСобствНН | G26: 0 | H26: 0 | I26: 0 | J26: 0 | K26: 0 | L26: 0 | M26: 0 | N26: 0 | O26: 0 | P26: 0 | Q26: 0 | R26: 0 | S26: 0 | T26: 0
A27: 27 | B27: КЛО_МРЦ70300700 | C27: Прочие доходы | D27: КЛО | E27: 70300700 | F27: ДохРеалУслЛогист | G27: 0 | H27: 0 | I27: 0 | J27: 0 | K27: 0 | L27: 0 | M27: 0 | N27: 0 | O27: 0 | P27: 0 | Q27: 0 | R27: 0 | S27: 0 | T27: 0
A28: 28 | B28: КЛО_МРЦ70300800 | C28: Прочие доходы | D28: ОПЕРАЦИОННЫЙ | E28: 70300800 | F28: ДоходДогКомиссии | G28: 0 | H28: 0 | I28: 0 | J28: 0 | K28: 0 | L28: 0 | M28: 0 | N28: 0 | O28: 0 | P28: 0 | Q28: 0 | R28: 0 | S28: 0 | T28: 0
A29: 29 | B29: КЛО_МРЦ70300900 | C29: Прочие доходы | D29: ОПЕРАЦИОННЫЙ | E29: 70300900 | F29: ДоходУслугКонечнПотр | G29: 0 | H29: 0 | I29: 0 | J29: 0 | K29: 0 | L29: 0 | M29: 0 | N29: 0 | O29: 0 | P29: 0 | Q29: 0 | R29: 0 | S29: 0 | T29: 0
A30: 30 | B30: КЛО_МРЦ71200000 | C30: Прочие доходы | D30: Дирекция | E30: 71200000 | F30: ДохРеалПрочОбАкт | G30: 0 | H30: 0 | I30: 0 | J30: 0 | K30: 0 | L30: 0 | M30: 0 | N30: 0 | O30: 0 | P30: 0 | Q30: 0 | R30: 0 | S30: 0 | T30: 0
A31: 31 | B31: КЛО_МРЦ71200100 | C31: Прочие доходы | D31: ОПЕРАЦИОННЫЙ+СБ | E31: 71200100 | F31: ДохРеалМакулатуры | G31: 36724.8 | H31: 2.8409112e-07 | I31: 0 | J31: 0 | K31: 9912 | L31: 13862.8 | M31: 12950 | N31: 0 | O31: 0 | P31: 0 | Q31: 0 | R31: 0 | S31: 0 | T31: 0
A32: 32 | B32: КЛО_МРЦ71300000 | C32: Прочие доходы | E32: 71300000 | F32: ДохАренОборудован | G32: 0 | H32: 0 | I32: 0 | J32: 0 | K32: 0 | L32: 0 | M32: 0 | N32: 0 | O32: 0 | P32: 0 | Q32: 0 | R32: 0 | S32: 0 | T32: 0
A33: 33 | B33: КЛО_МРЦ71300200 | C33: Прочие доходы | E33: 71300200 | F33: ДохАренТранспорта | G33: 0 | H33: 0 | I33: 0 | J33: 0 | K33: 0 | L33: 0 | M33: 0 | N33: 0 | O33: 0 | P33: 0 | Q33: 0 | R33: 0 | S33: 0 | T33: 0
A34: 34 | B34: КЛО_МРЦ71500000 | C34: Прочие доходы | D34: КЛО | E34: 71500000 | F34: ПолучШтрафПени | G34: 0 | H34: 0 | I34: 0 | J34: 0 | K34: 0 | L34: 0 | M34: 0 | N34: 0 | O34: 0 | P34: 0 | Q34: 0 | R34: 0 | S34: 0 | T34: 0
A35: 35 | B35: КЛО_МРЦ71500100 | C35: Прочие доходы | E35: 71500100 | F35: ОтримШтрафиПеніКомер | H35: 0
A36: 36 | B36: КЛО_МРЦ71700000 | C36: Прочие доходы | E36: 71700000 | F36: ДохСписКредЗадолж | G36: 0 | H36: 0 | I36: 0 | J36: 0 | K36: 0 | L36: 0 | M36: 0 | N36: 0 | O36: 0 | P36: 0 | Q36: 0 | R36: 0 | S36: 0 | T36: 0
A37: 37 | B37: КЛО_МРЦ71800000 | C37: Прочие доходы | D37: 0 | E37: 71800000 | F37: ДохБесплПолОборАкт | G37: 0 | H37: 0 | I37: 0 | J37: 0 | K37: 0 | L37: 0 | M37: 0 | N37: 0 | O37: 0 | P37: 0 | Q37: 0 | R37: 0 | S37: 0 | T37: 0
A38: 38 | B38: КЛО_МРЦ71800400 | C38: Прочие доходы | E38: 71800400 | F38: ДохБесплПолАктив.РЦ | G38: 0 | H38: 0 | I38: 0 | J38: 0 | K38: 0 | L38: 0 | M38: 0 | N38: 0 | O38: 0 | P38: 0 | Q38: 0 | R38: 0 | S38: 0 | T38: 0
A39: 39 | B39: КЛО_МРЦ71900000 | C39: Прочие доходы | D39: ВСЕ | E39: 71900000 | F39: ПрочДоходОперДеят | G39: 13007527 | H39: 0 | I39: 3105094.5 | J39: 1605268.9 | K39: 1714715.5 | L39: 1532860 | M39: 2907404.5 | N39: 2142183.6 | O39: 0 | P39: 0 | Q39: 0 | R39: 0 | S39: 0 | T39: 0
A40: 40 | B40: КЛО_МРЦ71900100 | C40: Прочие доходы | D40: ФИНАНСОВЫЙ | E40: 71900100 | F40: ПрочДоход% банка | G40: 0 | H40: 0 | I40: 0 | J40: 0 | K40: 0 | L40: 0 | M40: 0 | N40: 0 | O40: 0 | P40: 0 | Q40: 0 | R40: 0 | S40: 0 | T40: 0
A41: 41 | B41: КЛО_МРЦ71900500 | C41: Прочие доходы | D41: ОПЕРАЦИОННЫЙ+СБ | E41: 71900500 | F41: ПрДоходИзлишки кассы | G41: 0 | H41: 0 | I41: 0 | J41: 0 | K41: 0 | L41: 0 | M41: 0 | N41: 0 | O41: 0 | P41: 0 | Q41: 0 | R41: 0 | S41: 0 | T41: 0
A42: 42 | B42: КЛО_МРЦ71900600 | C42: Прочие доходы | D42: АДМИН | E42: 71900600 | F42: Доход гостинич услуг | G42: 0 | H42: 0 | I42: 0 | J42: 0 | K42: 0 | L42: 0 | M42: 0 | N42: 0 | O42: 0 | P42: 0 | Q42: 0 | R42: 0 | S42: 0 | T42: 0
A43: 43 | B43: КЛО_МРЦ71900900 | C43: Прочие доходы | E43: 71900900 | F43: ДохідСтраховВідшк | H43: 0
A44: 44 | B44: КЛО_МРЦ71901000 | C44: Прочие доходы | D44: АДМИН | E44: 71901000 | F44: ІнДоход%депозит | G44: 0 | H44: 0 | I44: 0 | J44: 0 | K44: 0 | L44: 0 | M44: 0 | N44: 0 | O44: 0 | P44: 0 | Q44: 0 | R44: 0 | S44: 0 | T44: 0
A45: 45 | C45: Прочие доходы | E45: 1
A46: 46 | E46: 1 | F46: 6. Прочие доходы аренда | G46: 30000 | H46: 4.2991997e-07 | I46: 5000 | J46: 5000 | K46: 5000 | L46: 5000 | M46: 5000 | N46: 5000 | O46: 0 | P46: 0 | Q46: 0 | R46: 0 | S46: 0 | T46: 0
A47: 47 | B47: КЛО_МРЦ71300100 | C47: Прочие доходы аренда | D47: АДМИН | E47: 71300100 | F47: ДохАренПомещений | G47: 30000 | H47: 4.2991997e-07 | I47: 5000 | J47: 5000 | K47: 5000 | L47: 5000 | M47: 5000 | N47: 5000 | O47: 0 | P47: 0 | Q47: 0 | R47: 0 | S47: 0 | T47: 0
A48: 48 | B48: КЛО_МРЦ71900400 | C48: Прочие доходы аренда | D48: АДМИН | E48: 71900400 | F48: ВозмещКомЭксплЗатрат | G48: 0 | H48: 0 | I48: 0 | J48: 0 | K48: 0 | L48: 0 | M48: 0 | N48: 0 | O48: 0 | P48: 0 | Q48: 0 | R48: 0 | S48: 0 | T48: 0
A49: 49 | E49: 1
A50: 50 | E50: 1 | F50: Валовая прибыль | G50: 13067160 | H50: 0.00018491313 | I50: 3103238.2 | J50: 1626535.4 | K50: 1721885.1 | L50: 1531210.4 | M50: 2950259.5 | N50: 2134030.8 | O50: 0 | P50: 0 | Q50: 0 | R50: 0 | S50: 0 | T50: 0
A51: 51 | E51: Затраты
A52: 52 | E52: 1 | F52: 7. Списания и переучеты | G52: -16065059 | H52: -3.8829612e-06 | I52: -1544187 | J52: -3615388.6 | K52: -2556959.6 | L52: -3083264.3 | M52: -2599827.5 | N52: -2665431.5 | O52: 0 | P52: 0 | Q52: 0 | R52: 0 | S52: 0 | T52: 0
A53: 53 | B53: КЛО_МРЦ80810000 | C53: Списания и переучеты | D53: КЛО+Опер+СБ | E53: 80810000 | F53: РасхТоварПереуч | G53: 172766.77 | H53: 0 | I53: 2987.1 | J53: 32732.23 | K53: 3779.06 | L53: 2632.71 | M53: 129902.97 | N53: 732.7 | O53: 0 | P53: 0 | Q53: 0 | R53: 0 | S53: 0 | T53: 0
A54: 54 | B54: КЛО_МРЦ80810001 | C54: Списания и переучеты | D54: КЛО+Опер+СБ | E54: 80810001 | F54: РасхМатПереучетПроиз | G54: -1231825.1 | H54: 0 | I54: 1930883.7 | J54: -1270673.2 | K54: -351132.89 | L54: -1069338.6 | M54: -234045.08 | N54: -237518.97 | O54: 0 | P54: 0 | Q54: 0 | R54: 0 | S54: 0 | T54: 0
A55: 55 | B55: КЛО_МРЦ80820000 | C55: Списания и переучеты | D55: КЛО+Опер+СБ | E55: 80820000 | F55: РасхТоварПотериСпис | G55: -1828.81 | H55: 0 | I55: 0 | J55: 0 | K55: 0 | L55: 0 | M55: -1677.76 | N55: -151.05 | O55: 0 | P55: 0 | Q55: 0 | R55: 0 | S55: 0 | T55: 0
A56: 56 | B56: КЛО_МРЦ80820001 | C56: Списания и переучеты | D56: КЛО+Опер+СБ | E56: 80820001 | F56: РасхМатПотПоСписПр | G56: -15004171 | H56: 0 | I56: -3478057.7 | J56: -2377447.6 | K56: -2209605.7 | L56: -2016558.4 | M56: -2494007.6 | N56: -2428494.2 | O56: 0 | P56: 0 | Q56: 0 | R56: 0 | S56: 0 | T56: 0
A57: 57 | E57: 1
A58: 58 | E58: 1 | F58: 8. ФОТ, в т.ч. налоги | G58: -48669803 | H58: -3.8829612e-06 | I58: -8062860.9 | J58: -7376629.3 | K58: -7593884.1 | L58: -8085705.2 | M58: -8853555 | N58: -8697168.5 | O58: 0 | P58: 0 | Q58: 0 | R58: 0 | S58: 0 | T58: 0
A59: 59 | B59: КЛО_МРЦ81100000 | C59: ФОТ, в т.ч. налоги | D59: HR+ВСЕ | E59: 81100000 | F59: РасхОплТрОклады | G59: -41475966 | H59: 0 | I59: -6933558.5 | J59: -6161991.5 | K59: -6469881 | L59: -6848666.5 | M59: -7608611.2 | N59: -7453257.3 | O59: 0 | P59: 0 | Q59: 0 | R59: 0 | S59: 0 | T59: 0
A60: 60 | B60: КЛО_МРЦ81100100 | C60: ФОТ, в т.ч. налоги | D60: HR+ВСЕ | E60: 81100100 | F60: Оплата Моб,ТРО | G60: -418400 | H60: 0 | I60: -67990 | J60: -67990 | K60: -67990 | L60: -67990 | M60: -73220 | N60: -73220 | O60: 0 | P60: 0 | Q60: 0 | R60: 0 | S60: 0 | T60: 0
A61: 61 | B61: КЛО_МРЦ81200000 | C61: ФОТ, в т.ч. налоги | D61: HR+ВСЕ | E61: 81200000 | F61: ПремииПоощрения | G61: 0 | H61: 0 | I61: 0 | J61: 0 | K61: 0 | L61: 0 | M61: 0 | N61: 0 | O61: 0 | P61: 0 | Q61: 0 | R61: 0 | S61: 0 | T61: 0
A62: 62 | B62: КЛО_МРЦ81400000 | C62: ФОТ, в т.ч. налоги | D62: HR+ВСЕ | E62: 81400000 | F62: Оплата отпусков | G62: -1443714.1 | H62: 0 | I62: -217999.17 | J62: -261604.75 | K62: -210532.73 | L62: -275502.66 | M62: -197810.03 | N62: -280264.76 | O62: 0 | P62: 0 | Q62: 0 | R62: 0 | S62: 0 | T62: 0
A63: 63 | B63: КЛО_МРЦ81500000 | C63: ФОТ, в т.ч. налоги | D63: HR+ВСЕ | E63: 81500000 | F63: ПрочРасхНаОплТр | G63: 0 | H63: 0 | I63: 0 | J63: 0 | K63: 0 | L63: 0 | M63: 0 | N63: 0 | O63: 0 | P63: 0 | Q63: 0 | R63: 0 | S63: 0 | T63: 0
A64: 64 | B64: КЛО_МРЦ81500100 | C64: ФОТ, в т.ч. налоги | D64: ФИНАНСОВЫЙ | E64: 81500100 | F64: СПД и директорство | G64: 0 | H64: 0 | I64: 0 | J64: 0 | K64: 0 | L64: 0 | M64: 0 | N64: 0 | O64: 0 | P64: 0 | Q64: 0 | R64: 0 | S64: 0 | T64: 0
A65: 65 | B65: КЛО_МРЦ82100000 | C65: ФОТ, в т.ч. налоги | D65: HR+ВСЕ | E65: 82100000 | F65: Налоги на ФОТ | G65: -5331723 | H65: 0 | I65: -843313.31 | J65: -885042.98 | K65: -845480.46 | L65: -893545.99 | M65: -973913.79 | N65: -890426.44 | O65: 0 | P65: 0 | Q65: 0 | R65: 0 | S65: 0 | T65: 0
A66: 66 | B66: КЛО_МРЦ84210100 | C66: ФОТ, в т.ч. налоги | D66: HR+ВСЕ | E66: 84210100 | F66: УслЦенБумагИС | G66: 0 | H66: 0 | I66: 0 | J66: 0 | K66: 0 | L66: 0 | M66: 0 | N66: 0 | O66: 0 | P66: 0 | Q66: 0 | R66: 0 | S66: 0 | T66: 0
A67: 67 | E67: 1
A68: 68 | E68: 1 | F68: 9. Персонал | G68: -302858.81 | H68: 0 | I68: -35546.97 | J68: -46808.71 | K68: -53121.67 | L68: -65225.32 | M68: -68319.83 | N68: -33836.31 | O68: 0 | P68: 0 | Q68: 0 | R68: 0 | S68: 0 | T68: 0
A69: 69 | B69: КЛО_МРЦ81300000 | C69: ФОТ, в т.ч. налоги | D69: HR+ВСЕ | E69: 81300000 | F69: КомпенсацВыплаты | G69: 0 | H69: 0 | I69: 0 | J69: 0 | K69: 0 | L69: 0 | M69: 0 | N69: 0 | O69: 0 | P69: 0 | Q69: 0 | R69: 0 | S69: 0 | T69: 0
A70: 70 | B70: КЛО_МРЦ81300100 | C70: ФОТ, в т.ч. налоги | D70: HR+ВСЕ | E70: 81300100 | F70: КомпЗаИспЛичнТр | G70: -13500 | H70: 0 | I70: 0 | J70: 0 | K70: -4500 | L70: -4500 | M70: -4500 | N70: 0 | O70: 0 | P70: 0 | Q70: 0 | R70: 0 | S70: 0 | T70: 0
A71: 71 | B71: КЛО_МРЦ81300200 | C71: ФОТ, в т.ч. налоги | D71: HR+ВСЕ | E71: 81300200 | F71: КомпКвартир | G71: 0 | H71: 0 | I71: 0 | J71: 0 | K71: 0 | L71: 0 | M71: 0 | N71: 0 | O71: 0 | P71: 0 | Q71: 0 | R71: 0 | S71: 0 | T71: 0
A72: 72 | B72: КЛО_МРЦ81300300 | C72: ФОТ, в т.ч. налоги | D72: HR+ВСЕ | E72: 81300300 | F72: МатПомощьСотр | G72: -6000 | H72: 0 | I72: 0 | J72: 0 | K72: 0 | L72: 0 | M72: -6000 | N72: 0 | O72: 0 | P72: 0 | Q72: 0 | R72: 0 | S72: 0 | T72: 0
A73: 73 | B73: КЛО_МРЦ81300400 | C73: ФОТ, в т.ч. налоги | D73: HR+ВСЕ | E73: 81300400 | F73: МатПомНаПогребен | G73: 0 | H73: 0 | I73: 0 | J73: 0 | K73: 0 | L73: 0 | M73: 0 | N73: 0 | O73: 0 | P73: 0 | Q73: 0 | R73: 0 | S73: 0 | T73: 0
A74: 74 | B74: КЛО_МРЦ82400000 | C74: ФОТ, в т.ч. налоги | D74: HR+ВСЕ | E74: 82400000 | F74: ОтчислНаИндивСтрах | G74: 0 | H74: 0 | I74: 0 | J74: 0 | K74: 0 | L74: 0 | M74: 0 | N74: 0 | O74: 0 | P74: 0 | Q74: 0 | R74: 0 | S74: 0 | T74: 0
A75: 75 | B75: КЛО_МРЦ84220100 | C75: Персонал | D75: HR | E75: 84220100 | F75: ПерсоналПоиск | G75: 0 | H75: 0 | I75: 0 | J75: 0 | K75: 0 | L75: 0 | M75: 0 | N75: 0 | O75: 0 | P75: 0 | Q75: 0 | R75: 0 | S75: 0 | T75: 0
A76: 76 | B76: КЛО_МРЦ84220200 | C76: Персонал | D76: HR | E76: 84220200 | F76: ПерсоналОбучВнутр | G76: 0 | H76: 0 | I76: 0 | J76: 0 | K76: 0 | L76: 0 | M76: 0 | N76: 0 | O76: 0 | P76: 0 | Q76: 0 | R76: 0 | S76: 0 | T76: 0
A77: 77 | B77: КЛО_МРЦ84220300 | C77: Персонал | D77: HR | E77: 84220300 | F77: ПерсоналОбучВнешн | G77: -11885 | H77: 0 | I77: 0 | J77: 0 | K77: 0 | L77: -11885 | M77: 0 | N77: 0 | O77: 0 | P77: 0 | Q77: 0 | R77: 0 | S77: 0 | T77: 0
A78: 78 | B78: КЛО_МРЦ84220400 | C78: Персонал | D78: HR | E78: 84220400 | F78: Персонал медосмотры | G78: -28020 | H78: 0 | I78: -520 | J78: -3680 | K78: -5230 | L78: -4760 | M78: -13250 | N78: -580 | O78: 0 | P78: 0 | Q78: 0 | R78: 0 | S78: 0 | T78: 0
A79: 79 | B79: КЛО_МРЦ84220500 | C79: Персонал | D79: HR | E79: 84220500 | F79: ПерсоналСтажеры | G79: 0 | H79: 0 | I79: 0 | J79: 0 | K79: 0 | L79: 0 | M79: 0 | N79: 0 | O79: 0 | P79: 0 | Q79: 0 | R79: 0 | S79: 0 | T79: 0
A80: 80 | B80: КЛО_МРЦ84220700 | C80: Персонал | D80: HR | E80: 84220700 | F80: Персонал прочее | G80: -243453.81 | H80: 0 | I80: -35026.97 | J80: -43128.71 | K80: -43391.67 | L80: -44080.32 | M80: -44569.83 | N80: -33256.31 | O80: 0 | P80: 0 | Q80: 0 | R80: 0 | S80: 0 | T80: 0
... A82: 82 | B82: КЛО_МРЦ84220900 | C82: Персонал | D82: HR | E82: 84220900 | F82: ПЕРСОН | G82: 0 | H82: 0 | I82: 0 | J82: 0 | K82: 0 | L82: 0 | M82: 0 | N82: 0 | O82: 0 | P82: 0 | Q82: 0 | R82: 0 | S82: 0 | T82: 0
A83: 83 | E83: 1
A84: 84 | E84: 1 | F84: 10. Аренда помещений | G84: -4858066.6 | H84: 0 | I84: -802733.33 | J84: -802733.33 | K84: -802733.33 | L84: -802733.33 | M84: -823566.66 | N84: -823566.66 | O84: 0 | P84: 0 | Q84: 0 | R84: 0 | S84: 0 | T84: 0
A85: 85 | B85: КЛО_МРЦ84160200 | C85: Аренда помещений | D85: АДМИН | E85: 84160200 | F85: Аренда помещений | G85: -4858066.6 | H85: 0 | I85: -802733.33 | J85: -802733.33 | K85: -802733.33 | L85: -802733.33 | M85: -823566.66 | N85: -823566.66 | O85: 0 | P85: 0 | Q85: 0 | R85: 0 | S85: 0 | T85: 0
A86: 86 | E86: 1
A87: 87 | E87: 1 | F87: 11. Коммунальные услуги | G87: -3733471.8 | H87: -6.373593e-05 | I87: -757382.46 | J87: -746300.23 | K87: -720077.57 | L87: -564883.64 | M87: -490833.02 | N87: -453994.9 | O87: 0 | P87: 0 | Q87: 0 | R87: 0 | S87: 0 | T87: 0
A88: 88 | B88: КЛО_МРЦ84030100 | C88: Коммунальные услуги | D88: АДМИН+Опер | E88: 84030100 | F88: КомУслВода | G88: 0 | H88: 0 | I88: 0 | J88: 0 | K88: 0 | L88: 0 | M88: 0 | N88: 0 | O88: 0 | P88: 0 | Q88: 0 | R88: 0 | S88: 0 | T88: 0
A89: 89 | B89: КЛО_МРЦ84030200 | C89: Коммунальные услуги | D89: АДМИН+Опер | E89: 84030200 | F89: КомУслВывОтходМус | G89: -101081.75 | H89: -1.4462436e-06 | I89: -18009.75 | J89: -15576 | K89: -16874 | L89: -16874 | M89: -17523 | N89: -16225 | O89: 0 | P89: 0 | Q89: 0 | R89: 0 | S89: 0 | T89: 0
A90: 90 | B90: КЛО_МРЦ84030300 | C90: Коммунальные услуги | D90: АДМИН+Опер | E90: 84030300 | F90: КомУслГаз | G90: 0 | H90: 0 | I90: 0 | J90: 0 | K90: 0 | L90: 0 | M90: 0 | N90: 0 | O90: 0 | P90: 0 | Q90: 0 | R90: 0 | S90: 0 | T90: 0
A91: 91 | B91: КЛО_МРЦ84030400 | C91: Коммунальные услуги | D91: АДМИН+Опер | E91: 84030400 | F91: КомУслОтопление | G91: 0 | H91: -4.3387308e-06 | I91: 0 | J91: 0 | K91: 0 | L91: 0 | M91: 0 | N91: 0 | O91: 0 | P91: 0 | Q91: 0 | R91: 0 | S91: 0 | T91: 0
A92: 92 | B92: КЛО_МРЦ84030500 | C92: Коммунальные услуги | D92: АДМИН+Опер | E92: 84030500 | F92: КомУслЭлектроэн | G92: -3620925.9 | H92: -5.7849745e-06 | I92: -737462.02 | J92: -728813.54 | K92: -701292.88 | L92: -546098.95 | M92: -471399.33 | N92: -435859.21 | O92: 0 | P92: 0 | Q92: 0 | R92: 0 | S92: 0 | T92: 0
A93: 93 | B93: КЛО_МРЦ84030600 | C93: Коммунальные услуги | D93: АДМИН+Опер | E93: 84030600 | F93: ЭксплуатПрочиеКомун | G93: -11464.14 | H93: -7.2312181e-06 | I93: -1910.69 | J93: -1910.69 | K93: -1910.69 | L93: -1910.69 | M93: -1910.69 | N93: -1910.69 | O93: 0 | P93: 0 | Q93: 0 | R93: 0 | S93: 0 | T93: 0
A94: 94 | B94: КЛО_МРЦ84030800 | C94: Коммунальные услуги | D94: АДМИН+Опер | E94: 84030800 | F94: КомУслЭлВозмещГенер. | G94: 0 | H94: -8.6774617e-06 | I94: 0 | J94: 0 | K94: 0 | L94: 0 | M94: 0 | N94: 0 | O94: 0 | P94: 0 | Q94: 0 | R94: 0 | S94: 0 | T94: 0
A95: 95 | B95: КЛО_МРЦ80300100 | C95: Коммунальные услуги | D95: АДМИН+Опер | E95: 80300100 | F95: РасхГСМ Тех.ИПр.нужд | G95: 0 | H95: -1.0123705e-05 | I95: 0 | J95: 0 | K95: 0 | L95: 0 | M95: 0 | N95: 0 | O95: 0 | P95: 0 | Q95: 0 | R95: 0 | S95: 0 | T95: 0
A96: 96 | E96: 1
A97: 97 | E97: 1 | F97: 12. Логистика | G97: -357334.72 | H97: -4.8480906e-06 | I97: -56200.06 | J97: -52453.51 | K97: -60497.35 | L97: -65502.92 | M97: -60441.65 | N97: -62239.23 | O97: 0 | P97: 0 | Q97: 0 | R97: 0 | S97: 0 | T97: 0
A98: 98 | B98: КЛО_МРЦ84020100 | C98: Логистика | D98: КЛО | E98: 84020100 | F98: Транспортные услуги | G98: -313895.02 | H98: -4.3075533e-06 | I98: -50892.66 | J98: -45886.14 | K98: -53512.66 | L98: -54455.31 | M98: -53296.58 | N98: -55851.67 | O98: 0 | P98: 0 | Q98: 0 | R98: 0 | S98: 0 | T98: 0
A99: 99 | B99: КЛО_МРЦ84020200 | C99: Логистика | D99: КЛО | E99: 84020200 | F99: Логистика | G99: 0 | H99: 0 | I99: 0 | J99: 0 | K99: 0 | L99: 0 | M99: 0 | N99: 0 | O99: 0 | P99: 0 | Q99: 0 | R99: 0 | S99: 0 | T99: 0
A100: 100 | B100: КЛО_МРЦ84020300 | C100: Логистика | D100: КЛО | E100: 84020300 | F100: ПрочУслСкладХоз | G100: -43439.7 | H100: -5.4053723e-07 | I100: -5307.4 | J100: -6567.37 | K100: -6984.69 | L100: -11047.61 | M100: -7145.07 | N100: -6387.56 | O100: 0 | P100: 0 | Q100: 0 | R100: 0 | S100: 0 | T100: 0
A101: 101 | E101: 1
...

Sheet липень
I1: 45658 | J1: 45689 | K1: 45717 | L1: 45748 | M1: 45778 | N1: 45809 | O1: 45839 | P1: 45870 | Q1: 45901 | R1: 45931 | S1: 45962 | T1: 45992
A2: 2 | E2: КЛО_МРЦ | F2: Киев,Фора МРЦ Оросительная,5 | G2: ИТОГО 2024 | H2: % К ОБОРОТУ | I2: 45658 | J2: 45689 | K2: 45717 | L2: 45383 | M2: 45778 | N2: 45809 | O2: 45839 | P2: 45870 | Q2: 45901 | R2: 45931 | S2: 45962 | T2: 45992
A3: 3 | B3: КЛО_МРЦДоходы | E3: Доходы
A4: 4 | C4: mapping Бюджет | D4: Разбивка по Офисам | E4: Код | F4: 1. Выручка | G4: 410966 | H4: 4.1113201e-06 | I4: 56312.5 | J4: 43272.3 | K4: 43860.04 | L4: 42136.95 | M4: 133672.61 | N4: 28768.98 | O4: 62942.62 | P4: 0 | Q4: 0 | R4: 0 | S4: 0 | T4: 0
A5: 5 | B5: КЛО_МРЦ70200000 | C5: Валовая прибыль (без бонусов) | D5: ВСЕ | E5: 70200000 | F5: ДоходРеалТовара | G5: 410966 | H5: 4.1113201e-06 | I5: 56312.5 | J5: 43272.3 | K5: 43860.04 | L5: 42136.95 | M5: 133672.61 | N5: 28768.98 | O5: 62942.62 | P5: 0 | Q5: 0 | R5: 0 | S5: 0 | T5: 0
A6: 6 | B6: КЛО_МРЦ70200001 | C6: Валовая прибыль (без бонусов) | D6: МАРКЕТИНГ | E6: 70200001 | F6: ДоходРеалПрогрЛояльн | G6: 0 | H6: 0 | I6: 0 | J6: 0 | K6: 0 | L6: 0 | M6: 0 | N6: 0 | O6: 0 | P6: 0 | Q6: 0 | R6: 0 | S6: 0 | T6: 0
A7: 7 | B7: КЛО_МРЦ70200002 | C7: Валовая прибыль (без бонусов) | D7: МАРКЕТИНГ | E7: 70200002 | F7: ДоходРеалТВаучера | G7: 0 | H7: 0 | I7: 0 | J7: 0 | K7: 0 | L7: 0 | M7: 0 | N7: 0 | O7: 0 | P7: 0 | Q7: 0 | R7: 0 | S7: 0 | T7: 0
A8: 8 | B8: КЛО_МРЦ70200003 | C8: Валовая прибыль (без бонусов) | E8: 70200003 | F8: ДоходРеалТовКомиссия | G8: 0 | H8: 0 | I8: 0 | J8: 0 | K8: 0 | L8: 0 | M8: 0 | N8: 0 | O8: 0 | P8: 0 | Q8: 0 | R8: 0 | S8: 0 | T8: 0
A9: 9 | B9: КЛО_МРЦ70200004 | C9: Валовая прибыль (без бонусов) | D9: Дирекция | E9: 70200004 | F9: ДоходРеалАгентсДог | G9: 0 | H9: 0 | I9: 0 | J9: 0 | K9: 0 | L9: 0 | M9: 0 | N9: 0 | O9: 0 | P9: 0 | Q9: 0 | R9: 0 | S9: 0 | T9: 0
A10: 10 | B10: КЛО_МРЦ70200009 | C10: Валовая прибыль (без бонусов) | D10: Дирекция | E10: 70200009 | F10: Недополучен.выручка | G10: 0 | H10: 0 | I10: 0 | J10: 0 | K10: 0 | L10: 0 | M10: 0 | N10: 0 | O10: 0 | P10: 0 | Q10: 0 | R10: 0 | S10: 0 | T10: 0
A11: 11 | B11: КЛО_МРЦ70200200 | C11: Валовая прибыль (без бонусов) | D11: Дирекция | E11: 70200200 | F11: ДоходРеалТовЭкспорт | G11: 0 | H11: 0 | I11: 0 | J11: 0 | K11: 0 | L11: 0 | M11: 0 | N11: 0 | O11: 0 | P11: 0 | Q11: 0 | R11: 0 | S11: 0 | T11: 0
A12: 12 | B12: КЛО_МРЦ70400000 | C12: Валовая прибыль (без бонусов) | D12: Дирекция | E12: 70400000 | F12: ВычетыДоходТовар | G12: 0 | H12: 0 | I12: 0 | J12: 0 | K12: 0 | L12: 0 | M12: 0 | N12: 0 | O12: 0 | P12: 0 | Q12: 0 | R12: 0 | S12: 0 | T12: 0
A13: 13 | B13: КЛО_МРЦ70430000 | C13: Валовая прибыль (без бонусов) | D13: Дирекция | E13: 70430000 | F13: ВычетыДоходАгентсДог | G13: 0 | H13: 0 | I13: 0 | J13: 0 | K13: 0 | L13: 0 | M13: 0 | N13: 0 | O13: 0 | P13: 0 | Q13: 0 | R13: 0 | S13: 0 | T13: 0
A14: 14 | E14: 1
A15: 15 | E15: 1 | F15: 2. Себестоимость | G15: -443532.91 | H15: -4.0635167e-06 | I15: -63168.81 | J15: -27005.75 | K15: -51602.41 | L15: -62649.3 | M15: -108767.59 | N15: -41921.78 | O15: -88417.27 | P15: 0 | Q15: 0 | R15: 0 | S15: 0 | T15: 0
A16: 16 | B16: КЛО_МРЦ90200000 | C16: Валовая прибыль (без бонусов) | D16: КЛО | E16: 90200000 | F16: СебестРеализТоваров | G16: -19324.39 | H16: -7.8532048e-10 | I16: 0 | J16: -27.4 | K16: 0 | L16: 0 | M16: -19296.99 | N16: 0 | O16: 0 | P16: 0 | Q16: 0 | R16: 0 | S16: 0 | T16: 0
A17: 17 | B17: КЛО_МРЦ90200001 | C17: Валовая прибыль (без бонусов) | D17: КЛО | E17: 90200001 | F17: СебестРеалТоваровПро | G17: -424208.52 | H17: -4.0627314e-06 | I17: -63168.81 | J17: -26978.35 | K17: -51602.41 | L17: -62649.3 | M17: -89470.6 | N17: -41921.78 | O17: -88417.27 | P17: 0 | Q17: 0 | R17: 0 | S17: 0 | T17: 0
A18: 18 | E18: 1
A19: 19 | E19: 1 | F19: 3. Валовая маржа | G19: -32566.91 | H19: 4.7803375e-08 | I19: -6856.31 | J19: 16266.55 | K19: -7742.37 | L19: -20512.35 | M19: 24905.02 | N19: -13152.8 | O19: -25474.65 | P19: 0 | Q19: 0 | R19: 0 | S19: 0 | T19: 0
A20: 20 | E20: 1
A21: 21 | E21: 1 | F21: 4. Бонусы | G21: 0 | H21: 0 | I21: 0 | J21: 0 | K21: 0 | L21: 0 | M21: 0 | N21: 0 | O21: 0 | P21: 0 | Q21: 0 | R21: 0 | S21: 0 | T21: 0
A22: 22 | B22: КЛО_МРЦ71900700 | C22: Бонусы | D22: КЛО | E22: 71900700 | F22: ДоходОтБонусов | G22: 0 | H22: 0 | I22: 0 | J22: 0 | K22: 0 | L22: 0 | M22: 0 | N22: 0 | O22: 0 | P22: 0 | Q22: 0 | R22: 0 | S22: 0 | T22: 0
A23: 23 | E23: 1
A24: 24 | E24: 1 | F24: 5. Прочее - Доходы | G24: 14938470 | H24: 0 | I24: 3105094.5 | J24: 1605268.9 | K24: 1724627.5 | L24: 1546722.8 | M24: 2920354.5 | N24: 2142183.6 | O24: 1894218 | P24: 0 | Q24: 0 | R24: 0 | S24: 0 | T24: 0
A25: 25 | B25: КЛО_МРЦ70300000 | C25: Прочие доходы | D25: МАРКЕТИНГ | E25: 70300000 | F25: ДоходРеалРабУсл | G25: 0 | H25: 0 | I25: 0 | J25: 0 | K25: 0 | L25: 0 | M25: 0 | N25: 0 | O25: 0 | P25: 0 | Q25: 0 | R25: 0 | S25: 0 | T25: 0
A26: 26 | B26: КЛО_МРЦ70300200 | C26: Прочие доходы | D26: МАРКЕТИНГ | E26: 70300200 | F26: ДохРазмРеклСобствНН | G26: 0 | H26: 0 | I26: 0 | J26: 0 | K26: 0 | L26: 0 | M26: 0 | N26: 0 | O26: 0 | P26: 0 | Q26: 0 | R26: 0 | S26: 0 | T26: 0
A27: 27 | B27: КЛО_МРЦ70300700 | C27: Прочие доходы | D27: КЛО | E27: 70300700 | F27: ДохРеалУслЛогист | G27: 0 | H27: 0 | I27: 0 | J27: 0 | K27: 0 | L27: 0 | M27: 0 | N27: 0 | O27: 0 | P27: 0 | Q27: 0 | R27: 0 | S27: 0 | T27: 0
A28: 28 | B28: КЛО_МРЦ70300800 | C28: Прочие доходы | D28: ОПЕРАЦИОННЫЙ | E28: 70300800 | F28: ДоходДогКомиссии | G28: 0 | H28: 0 | I28: 0 | J28: 0 | K28: 0 | L28: 0 | M28: 0 | N28: 0 | O28: 0 | P28: 0 | Q28: 0 | R28: 0 | S28: 0 | T28: 0
A29: 29 | B29: КЛО_МРЦ70300900 | C29: Прочие доходы | D29: ОПЕРАЦИОННЫЙ | E29: 70300900 | F29: ДоходУслугКонечнПотр | G29: 0 | H29: 0 | I29: 0 | J29: 0 | K29: 0 | L29: 0 | M29: 0 | N29: 0 | O29: 0 | P29: 0 | Q29: 0 | R29: 0 | S29: 0 | T29: 0
A30: 30 | B30: КЛО_МРЦ71200000 | C30: Прочие доходы | D30: Дирекция | E30: 71200000 | F30: ДохРеалПрочОбАкт | G30: 0 | H30: 0 | I30: 0 | J30: 0 | K30: 0 | L30: 0 | M30: 0 | N30: 0 | O30: 0 | P30: 0 | Q30: 0 | R30: 0 | S30: 0 | T30: 0
A31: 31 | B31: КЛО_МРЦ71200100 | C31: Прочие доходы | D31: ОПЕРАЦИОННЫЙ+СБ | E31: 71200100 | F31: ДохРеалМакулатуры | G31: 45166.8 | H31: 2.8409112e-07 | I31: 0 | J31: 0 | K31: 9912 | L31: 13862.8 | M31: 12950 | N31: 0 | O31: 8442 | P31: 0 | Q31: 0 | R31: 0 | S31: 0 | T31: 0
A32: 32 | B32: КЛО_МРЦ71300000 | C32: Прочие доходы | E32: 71300000 | F32: ДохАренОборудован | G32: 0 | H32: 0 | I32: 0 | J32: 0 | K32: 0 | L32: 0 | M32: 0 | N32: 0 | O32: 0 | P32: 0 | Q32: 0 | R32: 0 | S32: 0 | T32: 0
A33: 33 | B33: КЛО_МРЦ71300200 | C33: Прочие доходы | E33: 71300200 | F33: ДохАренТранспорта | G33: 0 | H33: 0 | I33: 0 | J33: 0 | K33: 0 | L33: 0 | M33: 0 | N33: 0 | O33: 0 | P33: 0 | Q33: 0 | R33: 0 | S33: 0 | T33: 0
A34: 34 | B34: КЛО_МРЦ71500000 | C34: Прочие доходы | D34: КЛО | E34: 71500000 | F34: ПолучШтрафПени | G34: 0 | H34: 0 | I34: 0 | J34: 0 | K34: 0 | L34: 0 | M34: 0 | N34: 0 | O34: 0 | P34: 0 | Q34: 0 | R34: 0 | S34: 0 | T34: 0
A35: 35 | B35: КЛО_МРЦ71500100 | C35: Прочие доходы | E35: 71500100 | F35: ОтримШтрафиПеніКомер | H35: 0
A36: 36 | B36: КЛО_МРЦ71700000 | C36: Прочие доходы | E36: 71700000 | F36: ДохСписКредЗадолж | G36: 0 | H36: 0 | I36: 0 | J36: 0 | K36: 0 | L36: 0 | M36: 0 | N36: 0 | O36: 0 | P36: 0 | Q36: 0 | R36: 0 | S36: 0 | T36: 0
A37: 37 | B37: КЛО_МРЦ71800000 | C37: Прочие доходы | D37: 0 | E37: 71800000 | F37: ДохБесплПолОборАкт | G37: 0 | H37: 0 | I37: 0 | J37: 0 | K37: 0 | L37: 0 | M37: 0 | N37: 0 | O37: 0 | P37: 0 | Q37: 0 | R37: 0 | S37: 0 | T37: 0
A38: 38 | B38: КЛО_МРЦ71800400 | C38: Прочие доходы | E38: 71800400 | F38: ДохБесплПолАктив.РЦ | G38: 0 | H38: 0 | I38: 0 | J38: 0 | K38: 0 | L38: 0 | M38: 0 | N38: 0 | O38: 0 | P38: 0 | Q38: 0 | R38: 0 | S38: 0 | T38: 0
A39: 39 | B39: КЛО_МРЦ71900000 | C39: Прочие доходы | D39: ВСЕ | E39: 71900000 | F39: ПрочДоходОперДеят | G39: 14893303 | H39: 0 | I39: 3105094.5 | J39: 1605268.9 | K39: 1714715.5 | L39: 1532860 | M39: 2907404.5 | N39: 2142183.6 | O39: 1885776 | P39: 0 | Q39: 0 | R39: 0 | S39: 0 | T39: 0
A40: 40 | B40: КЛО_МРЦ71900100 | C40: Прочие доходы | D40: ФИНАНСОВЫЙ | E40: 71900100 | F40: ПрочДоход% банка | G40: 0 | H40: 0 | I40: 0 | J40: 0 | K40: 0 | L40: 0 | M40: 0 | N40: 0 | O40: 0 | P40: 0 | Q40: 0 | R40: 0 | S40: 0 | T40: 0
A41: 41 | B41: КЛО_МРЦ71900500 | C41: Прочие доходы | D41: ОПЕРАЦИОННЫЙ+СБ | E41: 71900500 | F41: ПрДоходИзлишки кассы | G41: 0 | H41: 0 | I41: 0 | J41: 0 | K41: 0 | L41: 0 | M41: 0 | N41: 0 | O41: 0 | P41: 0 | Q41: 0 | R41: 0 | S41: 0 | T41: 0
A42: 42 | B42: КЛО_МРЦ71900600 | C42: Прочие доходы | D42: АДМИН | E42: 71900600 | F42: Доход гостинич услуг | G42: 0 | H42: 0 | I42: 0 | J42: 0 | K42: 0 | L42: 0 | M42: 0 | N42: 0 | O42: 0 | P42: 0 | Q42: 0 | R42: 0 | S42: 0 | T42: 0
A43: 43 | B43: КЛО_МРЦ71900900 | C43: Прочие доходы | E43: 71900900 | F43: ДохідСтраховВідшк | H43: 0
A44: 44 | B44: КЛО_МРЦ71901000 | C44: Прочие доходы | D44: АДМИН | E44: 71901000 | F44: ІнДоход%депозит | G44: 0 | H44: 0 | I44: 0 | J44: 0 | K44: 0 | L44: 0 | M44: 0 | N44: 0 | O44: 0 | P44: 0 | Q44: 0 | R44: 0 | S44: 0 | T44: 0
A45: 45 | C45: Прочие доходы | E45: 1
A46: 46 | E46: 1 | F46: 6. Прочие доходы аренда | G46: 35000 | H46: 4.2991997e-07 | I46: 5000 | J46: 5000 | K46: 5000 | L46: 5000 | M46: 5000 | N46: 5000 | O46: 5000 | P46: 0 | Q46: 0 | R46: 0 | S46: 0 | T46: 0
A47: 47 | B47: КЛО_МРЦ71300100 | C47: Прочие доходы аренда | D47: АДМИН | E47: 71300100 | F47: ДохАренПомещений | G47: 35000 | H47: 4.2991997e-07 | I47: 5000 | J47: 5000 | K47: 5000 | L47: 5000 | M47: 5000 | N47: 5000 | O47: 5000 | P47: 0 | Q47: 0 | R47: 0 | S47: 0 | T47: 0
A48: 48 | B48: КЛО_МРЦ71900400 | C48: Прочие доходы аренда | D48: АДМИН | E48: 71900400 | F48: ВозмещКомЭксплЗатрат | G48: 0 | H48: 0 | I48: 0 | J48: 0 | K48: 0 | L48: 0 | M48: 0 | N48: 0 | O48: 0 | P48: 0 | Q48: 0 | R48: 0 | S48: 0 | T48: 0
A49: 49 | E49: 1
A50: 50 | E50: 1 | F50: Валовая прибыль | G50: 14940903 | H50: 0.00018491313 | I50: 3103238.2 | J50: 1626535.4 | K50: 1721885.1 | L50: 1531210.4 | M50: 2950259.5 | N50: 2134030.8 | O50: 1873743.4 | P50: 0 | Q50: 0 | R50: 0 | S50: 0 | T50: 0
A51: 51 | E51: Затраты
A52: 52 | E52: 1 | F52: 7. Списания и переучеты | G52: -19989261 | H52: -3.8829612e-06 | I52: -1544187 | J52: -3615388.6 | K52: -2556959.6 | L52: -3083264.3 | M52: -2599827.5 | N52: -2665431.5 | O52: -3924202.8 | P52: 0 | Q52: 0 | R52: 0 | S52: 0 | T52: 0
A53: 53 | B53: КЛО_МРЦ80810000 | C53: Списания и переучеты | D53: КЛО+Опер+СБ | E53: 80810000 | F53: РасхТоварПереуч | G53: 251518.69 | H53: 0 | I53: 2987.1 | J53: 32732.23 | K53: 3779.06 | L53: 2632.71 | M53: 129902.97 | N53: 732.7 | O53: 78751.92 | P53: 0 | Q53: 0 | R53: 0 | S53: 0 | T53: 0
A54: 54 | B54: КЛО_МРЦ80810001 | C54: Списания и переучеты | D54: КЛО+Опер+СБ | E54: 80810001 | F54: РасхМатПереучетПроиз | G54: -1756944.6 | H54: 0 | I54: 1930883.7 | J54: -1270673.2 | K54: -351132.89 | L54: -1069338.6 | M54: -234045.08 | N54: -237518.97 | O54: -525119.56 | P54: 0 | Q54: 0 | R54: 0 | S54: 0 | T54: 0
A55: 55 | B55: КЛО_МРЦ80820000 | C55: Списания и переучеты | D55: КЛО+Опер+СБ | E55: 80820000 | F55: РасхТоварПотериСпис | G55: -2130.92 | H55: 0 | I55: 0 | J55: 0 | K55: 0 | L55: 0 | M55: -1677.76 | N55: -151.05 | O55: -302.11 | P55: 0 | Q55: 0 | R55: 0 | S55: 0 | T55: 0
A56: 56 | B56: КЛО_МРЦ80820001 | C56: Списания и переучеты | D56: КЛО+Опер+СБ | E56: 80820001 | F56: РасхМатПотПоСписПр | G56: -18481704 | H56: 0 | I56: -3478057.7 | J56: -2377447.6 | K56: -2209605.7 | L56: -2016558.4 | M56: -2494007.6 | N56: -2428494.2 | O56: -3477533 | P56: 0 | Q56: 0 | R56: 0 | S56: 0 | T56: 0
A57: 57 | E57: 1
A58: 58 | E58: 1 | F58: 8. ФОТ, в т.ч. налоги | G58: -58173546 | H58: -3.8829612e-06 | I58: -8062860.9 | J58: -7376629.3 | K58: -7593884.1 | L58: -8085705.2 | M58: -8853555 | N58: -8697168.5 | O58: -9503743.3 | P58: 0 | Q58: 0 | R58: 0 | S58: 0 | T58: 0
A59: 59 | B59: КЛО_МРЦ81100000 | C59: ФОТ, в т.ч. налоги | D59: HR+ВСЕ | E59: 81100000 | F59: РасхОплТрОклады | G59: -49762842 | H59: 0 | I59: -6933558.5 | J59: -6161991.5 | K59: -6469881 | L59: -6848666.5 | M59: -7608611.2 | N59: -7453257.3 | O59: -8286876 | P59: 0 | Q59: 0 | R59: 0 | S59: 0 | T59: 0
A60: 60 | B60: КЛО_МРЦ81100100 | C60: ФОТ, в т.ч. налоги | D60: HR+ВСЕ | E60: 81100100 | F60: Оплата Моб,ТРО | G60: -491620 | H60: 0 | I60: -67990 | J60: -67990 | K60: -67990 | L60: -67990 | M60: -73220 | N60: -73220 | O60: -73220 | P60: 0 | Q60: 0 | R60: 0 | S60: 0 | T60: 0
A61: 61 | B61: КЛО_МРЦ81200000 | C61: ФОТ, в т.ч. налоги | D61: HR+ВСЕ | E61: 81200000 | F61: ПремииПоощрения | G61: 0 | H61: 0 | I61: 0 | J61: 0 | K61: 0 | L61: 0 | M61: 0 | N61: 0 | O61: 0 | P61: 0 | Q61: 0 | R61: 0 | S61: 0 | T61: 0
A62: 62 | B62: КЛО_МРЦ81400000 | C62: ФОТ, в т.ч. налоги | D62: HR+ВСЕ | E62: 81400000 | F62: Оплата отпусков | G62: -1711100.2 | H62: 0 | I62: -217999.17 | J62: -261604.75 | K62: -210532.73 | L62: -275502.66 | M62: -197810.03 | N62: -280264.76 | O62: -267386.09 | P62: 0 | Q62: 0 | R62: 0 | S62: 0 | T62: 0
A63: 63 | B63: КЛО_МРЦ81500000 | C63: ФОТ, в т.ч. налоги | D63: HR+ВСЕ | E63: 81500000 | F63: ПрочРасхНаОплТр | G63: 0 | H63: 0 | I63: 0 | J63: 0 | K63: 0 | L63: 0 | M63: 0 | N63: 0 | O63: 0 | P63: 0 | Q63: 0 | R63: 0 | S63: 0 | T63: 0
A64: 64 | B64: КЛО_МРЦ81500100 | C64: ФОТ, в т.ч. налоги | D64: ФИНАНСОВЫЙ | E64: 81500100 | F64: СПД и директорство | G64: 0 | H64: 0 | I64: 0 | J64: 0 | K64: 0 | L64: 0 | M64: 0 | N64: 0 | O64: 0 | P64: 0 | Q64: 0 | R64: 0 | S64: 0 | T64: 0
A65: 65 | B65: КЛО_МРЦ82100000 | C65: ФОТ, в т.ч. налоги | D65: HR+ВСЕ | E65: 82100000 | F65: Налоги на ФОТ | G65: -6207984.2 | H65: 0 | I65: -843313.31 | J65: -885042.98 | K65: -845480.46 | L65: -893545.99 | M65: -973913.79 | N65: -890426.44 | O65: -876261.22 | P65: 0 | Q65: 0 | R65: 0 | S65: 0 | T65: 0
A66: 66 | B66: КЛО_МРЦ84210100 | C66: ФОТ, в т.ч. налоги | D66: HR+ВСЕ | E66: 84210100 | F66: УслЦенБумагИС | G66: 0 | H66: 0 | I66: 0 | J66: 0 | K66: 0 | L66: 0 | M66: 0 | N66: 0 | O66: 0 | P66: 0 | Q66: 0 | R66: 0 | S66: 0 | T66: 0
A67: 67 | E67: 1
A68: 68 | E68: 1 | F68: 9. Персонал | G68: -334364.3 | H68: 0 | I68: -35546.97 | J68: -46808.71 | K68: -53121.67 | L68: -65225.32 | M68: -68319.83 | N68: -33836.31 | O68: -31505.49 | P68: 0 | Q68: 0 | R68: 0 | S68: 0 | T68: 0
A69: 69 | B69: КЛО_МРЦ81300000 | C69: ФОТ, в т.ч. налоги | D69: HR+ВСЕ | E69: 81300000 | F69: КомпенсацВыплаты | G69: 0 | H69: 0 | I69: 0 | J69: 0 | K69: 0 | L69: 0 | M69: 0 | N69: 0 | O69: 0 | P69: 0 | Q69: 0 | R69: 0 | S69: 0 | T69: 0
A70: 70 | B70: КЛО_МРЦ81300100 | C70: ФОТ, в т.ч. налоги | D70: HR+ВСЕ | E70: 81300100 | F70: КомпЗаИспЛичнТр | G70: -15144 | H70: 0 | I70: 0 | J70: 0 | K70: -4500 | L70: -4500 | M70: -4500 | N70: 0 | O70: -1644 | P70: 0 | Q70: 0 | R70: 0 | S70: 0 | T70: 0
A71: 71 | B71: КЛО_МРЦ81300200 | C71: ФОТ, в т.ч. налоги | D71: HR+ВСЕ | E71: 81300200 | F71: КомпКвартир | G71: 0 | H71: 0 | I71: 0 | J71: 0 | K71: 0 | L71: 0 | M71: 0 | N71: 0 | O71: 0 | P71: 0 | Q71: 0 | R71: 0 | S71: 0 | T71: 0
A72: 72 | B72: КЛО_МРЦ81300300 | C72: ФОТ, в т.ч. налоги | D72: HR+ВСЕ | E72: 81300300 | F72: МатПомощьСотр | G72: -6000 | H72: 0 | I72: 0 | J72: 0 | K72: 0 | L72: 0 | M72: -6000 | N72: 0 | O72: 0 | P72: 0 | Q72: 0 | R72: 0 | S72: 0 | T72: 0
A73: 73 | B73: КЛО_МРЦ81300400 | C73: ФОТ, в т.ч. налоги | D73: HR+ВСЕ | E73: 81300400 | F73: МатПомНаПогребен | G73: 0 | H73: 0 | I73: 0 | J73: 0 | K73: 0 | L73: 0 | M73: 0 | N73: 0 | O73: 0 | P73: 0 | Q73: 0 | R73: 0 | S73: 0 | T73: 0
A74: 74 | B74: КЛО_МРЦ82400000 | C74: ФОТ, в т.ч. налоги | D74: HR+ВСЕ | E74: 82400000 | F74: ОтчислНаИндивСтрах | G74: 0 | H74: 0 | I74: 0 | J74: 0 | K74: 0 | L74: 0 | M74: 0 | N74: 0 | O74: 0 | P74: 0 | Q74: 0 | R74: 0 | S74: 0 | T74: 0
A75: 75 | B75: КЛО_МРЦ84220100 | C75: Персонал | D75: HR | E75: 84220100 | F75: ПерсоналПоиск | G75: 0 | H75: 0 | I75: 0 | J75: 0 | K75: 0 | L75: 0 | M75: 0 | N75: 0 | O75: 0 | P75: 0 | Q75: 0 | R75: 0 | S75: 0 | T75: 0
A76: 76 | B76: КЛО_МРЦ84220200 | C76: Персонал | D76: HR | E76: 84220200 | F76: ПерсоналОбучВнутр | G76: 0 | H76: 0 | I76: 0 | J76: 0 | K76: 0 | L76: 0 | M76: 0 | N76: 0 | O76: 0 | P76: 0 | Q76: 0 | R76: 0 | S76: 0 | T76: 0
A77: 77 | B77: КЛО_МРЦ84220300 | C77: Персонал | D77: HR | E77: 84220300 | F77: ПерсоналОбучВнешн | G77: -11885 | H77: 0 | I77: 0 | J77: 0 | K77: 0 | L77: -11885 | M77: 0 | N77: 0 | O77: 0 | P77: 0 | Q77: 0 | R77: 0 | S77: 0 | T77: 0
A78: 78 | B78: КЛО_МРЦ84220400 | C78: Персонал | D78: HR | E78: 84220400 | F78: Персонал медосмотры | G78: -28020 | H78: 0 | I78: -520 | J78: -3680 | K78: -5230 | L78: -4760 | M78: -13250 | N78: -580 | O78: 0 | P78: 0 | Q78: 0 | R78: 0 | S78: 0 | T78: 0
A79: 79 | B79: КЛО_МРЦ84220500 | C79: Персонал | D79: HR | E79: 84220500 | F79: ПерсоналСтажеры | G79: 0 | H79: 0 | I79: 0 | J79: 0 | K79: 0 | L79: 0 | M79: 0 | N79: 0 | O79: 0 | P79: 0 | Q79: 0 | R79: 0 | S79: 0 | T79: 0
A80: 80 | B80: КЛО_МРЦ84220700 | C80: Персонал | D80: HR | E80: 84220700 | F80: Персонал прочее | G80: -273315.3 | H80: 0 | I80: -35026.97 | J80: -43128.71 | K80: -43391.67 | L80: -44080.32 | M80: -44569.83 | N80: -33256.31 | O80: -29861.49 | P80: 0 | Q80: 0 | R80: 0 | S80: 0 | T80: 0
... A82: 82 | B82: КЛО_МРЦ84220900 | C82: Персонал | D82: HR | E82: 84220900 | F82: ПЕРСОН | G82: 0 | H82: 0 | I82: 0 | J82: 0 | K82: 0 | L82: 0 | M82: 0 | N82: 0 | O82: 0 | P82: 0 | Q82: 0 | R82: 0 | S82: 0 | T82: 0
A83: 83 | E83: 1
A84: 84 | E84: 1 | F84: 10. Аренда помещений | G84: -5686203.2 | H84: 0 | I84: -802733.33 | J84: -802733.33 | K84: -802733.33 | L84: -802733.33 | M84: -823566.66 | N84: -823566.66 | O84: -828136.56 | P84: 0 | Q84: 0 | R84: 0 | S84: 0 | T84: 0
A85: 85 | B85: КЛО_МРЦ84160200 | C85: Аренда помещений | D85: АДМИН | E85: 84160200 | F85: Аренда помещений | G85: -5686203.2 | H85: 0 | I85: -802733.33 | J85: -802733.33 | K85: -802733.33 | L85: -802733.33 | M85: -823566.66 | N85: -823566.66 | O85: -828136.56 | P85: 0 | Q85: 0 | R85: 0 | S85: 0 | T85: 0
A86: 86 | E86: 1
A87: 87 | E87: 1 | F87: 11. Коммунальные услуги | G87: -4308405.1 | H87: -6.373593e-05 | I87: -757382.46 | J87: -746300.23 | K87: -720077.57 | L87: -564883.64 | M87: -490833.02 | N87: -453994.9 | O87: -574933.27 | P87: 0 | Q87: 0 | R87: 0 | S87: 0 | T87: 0
A88: 88 | B88: КЛО_МРЦ84030100 | C88: Коммунальные услуги | D88: АДМИН+Опер | E88: 84030100 | F88: КомУслВода | G88: 0 | H88: 0 | I88: 0 | J88: 0 | K88: 0 | L88: 0 | M88: 0 | N88: 0 | O88: 0 | P88: 0 | Q88: 0 | R88: 0 | S88: 0 | T88: 0
A89: 89 | B89: КЛО_МРЦ84030200 | C89: Коммунальные услуги | D89: АДМИН+Опер | E89: 84030200 | F89: КомУслВывОтходМус | G89: -118604.75 | H89: -1.4462436e-06 | I89: -18009.75 | J89: -15576 | K89: -16874 | L89: -16874 | M89: -17523 | N89: -16225 | O89: -17523 | P89: 0 | Q89: 0 | R89: 0 | S89: 0 | T89: 0
A90: 90 | B90: КЛО_МРЦ84030300 | C90: Коммунальные услуги | D90: АДМИН+Опер | E90: 84030300 | F90: КомУслГаз | G90: 0 | H90: 0 | I90: 0 | J90: 0 | K90: 0 | L90: 0 | M90: 0 | N90: 0 | O90: 0 | P90: 0 | Q90: 0 | R90: 0 | S90: 0 | T90: 0
A91: 91 | B91: КЛО_МРЦ84030400 | C91: Коммунальные услуги | D91: АДМИН+Опер | E91: 84030400 | F91: КомУслОтопление | G91: 0 | H91: -4.3387308e-06 | I91: 0 | J91: 0 | K91: 0 | L91: 0 | M91: 0 | N91: 0 | O91: 0 | P91: 0 | Q91: 0 | R91: 0 | S91: 0 | T91: 0
A92: 92 | B92: КЛО_МРЦ84030500 | C92: Коммунальные услуги | D92: АДМИН+Опер | E92: 84030500 | F92: КомУслЭлектроэн | G92: -4176425.5 | H92: -5.7849745e-06 | I92: -737462.02 | J92: -728813.54 | K92: -701292.88 | L92: -546098.95 | M92: -471399.33 | N92: -435859.21 | O92: -555499.58 | P92: 0 | Q92: 0 | R92: 0 | S92: 0 | T92: 0
A93: 93 | B93: КЛО_МРЦ84030600 | C93: Коммунальные услуги | D93: АДМИН+Опер | E93: 84030600 | F93: ЭксплуатПрочиеКомун | G93: -13374.83 | H93: -7.2312181e-06 | I93: -1910.69 | J93: -1910.69 | K93: -1910.69 | L93: -1910.69 | M93: -1910.69 | N93: -1910.69 | O93: -1910.69 | P93: 0 | Q93: 0 | R93: 0 | S93: 0 | T93: 0
A94: 94 | B94: КЛО_МРЦ84030800 | C94: Коммунальные услуги | D94: АДМИН+Опер | E94: 84030800 | F94: КомУслЭлВозмещГенер. | G94: 0 | H94: -8.6774617e-06 | I94: 0 | J94: 0 | K94: 0 | L94: 0 | M94: 0 | N94: 0 | O94: 0 | P94: 0 | Q94: 0 | R94: 0 | S94: 0 | T94: 0
A95: 95 | B95: КЛО_МРЦ80300100 | C95: Коммунальные услуги | D95: АДМИН+Опер | E95: 80300100 | F95: РасхГСМ Тех.ИПр.нужд | G95: 0 | H95: -1.0123705e-05 | I95: 0 | J95: 0 | K95: 0 | L95: 0 | M95: 0 | N95: 0 | O95: 0 | P95: 0 | Q95: 0 | R95: 0 | S95: 0 | T95: 0
A96: 96 | E96: 1
A97: 97 | E97: 1 | F97: 12. Логистика | G97: -428680.9 | H97: -4.8480906e-06 | I97: -56200.06 | J97: -52453.51 | K97: -60497.35 | L97: -65502.92 | M97: -60441.65 | N97: -62239.23 | O97: -71346.18 | P97: 0 | Q97: 0 | R97: 0 | S97: 0 | T97: 0
A98: 98 | B98: КЛО_МРЦ84020100 | C98: Логистика | D98: КЛО | E98: 84020100 | F98: Транспортные услуги | G98: -378031 | H98: -4.3075533e-06 | I98: -50892.66 | J98: -45886.14 | K98: -53512.66 | L98: -54455.31 | M98: -53296.58 | N98: -55851.67 | O98: -64135.98 | P98: 0 | Q98: 0 | R98: 0 | S98: 0 | T98: 0
A99: 99 | B99: КЛО_МРЦ84020200 | C99: Логистика | D99: КЛО | E99: 84020200 | F99: Логистика | G99: 0 | H99: 0 | I99: 0 | J99: 0 | K99: 0 | L99: 0 | M99: 0 | N99: 0 | O99: 0 | P99: 0 | Q99: 0 | R99: 0 | S99: 0 | T99: 0
A100: 100 | B100: КЛО_МРЦ84020300 | C100: Логистика | D100: КЛО | E100: 84020300 | F100: ПрочУслСкладХоз | G100: -50649.9 | H100: -5.4053723e-07 | I100: -5307.4 | J100: -6567.37 | K100: -6984.69 | L100: -11047.61 | M100: -7145.07 | N100: -6387.56 | O100: -7210.2 | P100: 0 | Q100: 0 | R100: 0 | S100: 0 | T100: 0
A101: 101 | E101: 1
...

Sheet вересень
I1: 45658 | J1: 45689 | K1: 45717 | L1: 45748 | M1: 45778 | N1: 45809 | O1: 45839 | P1: 45870 | Q1: 45901 | R1: 45931 | S1: 45962 | T1: 45992
A2: 2 | E2: КЛО_МРЦ | F2: Киев,Фора МРЦ Оросительная,5 | G2: ИТОГО 2024 | H2: % К ОБОРОТУ | I2: 45658 | J2: 45689 | K2: 45717 | L2: 45383 | M2: 45778 | N2: 45809 | O2: 45839 | P2: 45870 | Q2: 45901 | R2: 45931 | S2: 45962 | T2: 45992
A3: 3 | B3: КЛО_МРЦДоходы | E3: Доходы
A4: 4 | C4: mapping Бюджет | D4: Разбивка по Офисам | E4: Код | F4: 1. Выручка | G4: 583523.2 | H4: 4.1113201e-06 | I4: 56312.5 | J4: 43272.3 | K4: 43860.04 | L4: 42136.95 | M4: 133672.61 | N4: 28768.98 | O4: 62942.62 | P4: 105747.07 | Q4: 66810.13 | R4: 0 | S4: 0 | T4: 0
A5: 5 | B5: КЛО_МРЦ70200000 | C5: Валовая прибыль (без бонусов) | D5: ВСЕ | E5: 70200000 | F5: ДоходРеалТовара | G5: 583523.2 | H5: 4.1113201e-06 | I5: 56312.5 | J5: 43272.3 | K5: 43860.04 | L5: 42136.95 | M5: 133672.61 | N5: 28768.98 | O5: 62942.62 | P5: 105747.07 | Q5: 66810.13 | R5: 0 | S5: 0 | T5: 0
A6: 6 | B6: КЛО_МРЦ70200001 | C6: Валовая прибыль (без бонусов) | D6: МАРКЕТИНГ | E6: 70200001 | F6: ДоходРеалПрогрЛояльн | G6: 0 | H6: 0 | I6: 0 | J6: 0 | K6: 0 | L6: 0 | M6: 0 | N6: 0 | O6: 0 | P6: 0 | Q6: 0 | R6: 0 | S6: 0 | T6: 0
A7: 7 | B7: КЛО_МРЦ70200002 | C7: Валовая прибыль (без бонусов) | D7: МАРКЕТИНГ | E7: 70200002 | F7: ДоходРеалТВаучера | G7: 0 | H7: 0 | I7: 0 | J7: 0 | K7: 0 | L7: 0 | M7: 0 | N7: 0 | O7: 0 | P7: 0 | Q7: 0 | R7: 0 | S7: 0 | T7: 0
A8: 8 | B8: КЛО_МРЦ70200003 | C8: Валовая прибыль (без бонусов) | E8: 70200003 | F8: ДоходРеалТовКомиссия | G8: 0 | H8: 0 | I8: 0 | J8: 0 | K8: 0 | L8: 0 | M8: 0 | N8: 0 | O8: 0 | P8: 0 | Q8: 0 | R8: 0 | S8: 0 | T8: 0
A9: 9 | B9: КЛО_МРЦ70200004 | C9: Валовая прибыль (без бонусов) | D9: Дирекция | E9: 70200004 | F9: ДоходРеалАгентсДог | G9: 0 | H9: 0 | I9: 0 | J9: 0 | K9: 0 | L9: 0 | M9: 0 | N9: 0 | O9: 0 | P9: 0 | Q9: 0 | R9: 0 | S9: 0 | T9: 0
A10: 10 | B10: КЛО_МРЦ70200009 | C10: Валовая прибыль (без бонусов) | D10: Дирекция | E10: 70200009 | F10: Недополучен.выручка | G10: 0 | H10: 0 | I10: 0 | J10: 0 | K10: 0 | L10: 0 | M10: 0 | N10: 0 | O10: 0 | P10: 0 | Q10: 0 | R10: 0 | S10: 0 | T10: 0
A11: 11 | B11: КЛО_МРЦ70200200 | C11: Валовая прибыль (без бонусов) | D11: Дирекция | E11: 70200200 | F11: ДоходРеалТовЭкспорт | G11: 0 | H11: 0 | I11: 0 | J11: 0 | K11: 0 | L11: 0 | M11: 0 | N11: 0 | O11: 0 | P11: 0 | Q11: 0 | R11: 0 | S11: 0 | T11: 0
A12: 12 | B12: КЛО_МРЦ70400000 | C12: Валовая прибыль (без бонусов) | D12: Дирекция | E12: 70400000 | F12: ВычетыДоходТовар | G12: 0 | H12: 0 | I12: 0 | J12: 0 | K12: 0 | L12: 0 | M12: 0 | N12: 0 | O12: 0 | P12: 0 | Q12: 0 | R12: 0 | S12: 0 | T12: 0
A13: 13 | B13: КЛО_МРЦ70430000 | C13: Валовая прибыль (без бонусов) | D13: Дирекция | E13: 70430000 | F13: ВычетыДоходАгентсДог | G13: 0 | H13: 0 | I13: 0 | J13: 0 | K13: 0 | L13: 0 | M13: 0 | N13: 0 | O13: 0 | P13: 0 | Q13: 0 | R13: 0 | S13: 0 | T13: 0
A14: 14 | E14: 1
A15: 15 | E15: 1 | F15: 2. Себестоимость | G15: -870181.49 | H15: -4.0635167e-06 | I15: -63168.81 | J15: -27005.75 | K15: -51602.41 | L15: -62649.3 | M15: -108767.59 | N15: -41921.78 | O15: -88417.27 | P15: -332714.32 | Q15: -93934.26 | R15: 0 | S15: 0 | T15: 0
A16: 16 | B16: КЛО_МРЦ90200000 | C16: Валовая прибыль (без бонусов) | D16: КЛО | E16: 90200000 | F16: СебестРеализТоваров | G16: -293622.97 | H16: -7.8532048e-10 | I16: 0 | J16: -27.4 | K16: 0 | L16: 0 | M16: -19296.99 | N16: 0 | O16: 0 | P16: -274298.58 | Q16: 0 | R16: 0 | S16: 0 | T16: 0
A17: 17 | B17: КЛО_МРЦ90200001 | C17: Валовая прибыль (без бонусов) | D17: КЛО | E17: 90200001 | F17: СебестРеалТоваровПро | G17: -576558.52 | H17: -4.0627314e-06 | I17: -63168.81 | J17: -26978.35 | K17: -51602.41 | L17: -62649.3 | M17: -89470.6 | N17: -41921.78 | O17: -88417.27 | P17: -58415.74 | Q17: -93934.26 | R17: 0 | S17: 0 | T17: 0
A18: 18 | E18: 1
A19: 19 | E19: 1 | F19: 3. Валовая маржа | G19: -286658.29 | H19: 4.7803375e-08 | I19: -6856.31 | J19: 16266.55 | K19: -7742.37 | L19: -20512.35 | M19: 24905.02 | N19: -13152.8 | O19: -25474.65 | P19: -226967.25 | Q19: -27124.13 | R19: 0 | S19: 0 | T19: 0
A20: 20 | E20: 1
A21: 21 | E21: 1 | F21: 4. Бонусы | G21: 0 | H21: 0 | I21: 0 | J21: 0 | K21: 0 | L21: 0 | M21: 0 | N21: 0 | O21: 0 | P21: 0 | Q21: 0 | R21: 0 | S21: 0 | T21: 0
A22: 22 | B22: КЛО_МРЦ71900700 | C22: Бонусы | D22: КЛО | E22: 71900700 | F22: ДоходОтБонусов | G22: 0 | H22: 0 | I22: 0 | J22: 0 | K22: 0 | L22: 0 | M22: 0 | N22: 0 | O22: 0 | P22: 0 | Q22: 0 | R22: 0 | S22: 0 | T22: 0
A23: 23 | E23: 1
A24: 24 | E24: 1 | F24: 5. Прочее - Доходы | G24: 19980900 | H24: 0 | I24: 3105094.5 | J24: 1605268.9 | K24: 1724627.5 | L24: 1546722.8 | M24: 2920354.5 | N24: 2142183.6 | O24: 1894218 | P24: 2368853 | Q24: 2673577.7 | R24: 0 | S24: 0 | T24: 0
A25: 25 | B25: КЛО_МРЦ70300000 | C25: Прочие доходы | D25: МАРКЕТИНГ | E25: 70300000 | F25: ДоходРеалРабУсл | G25: 0 | H25: 0 | I25: 0 | J25: 0 | K25: 0 | L25: 0 | M25: 0 | N25: 0 | O25: 0 | P25: 0 | Q25: 0 | R25: 0 | S25: 0 | T25: 0
A26: 26 | B26: КЛО_МРЦ70300200 | C26: Прочие доходы | D26: МАРКЕТИНГ | E26: 70300200 | F26: ДохРазмРеклСобствНН | G26: 0 | H26: 0 | I26: 0 | J26: 0 | K26: 0 | L26: 0 | M26: 0 | N26: 0 | O26: 0 | P26: 0 | Q26: 0 | R26: 0 | S26: 0 | T26: 0
A27: 27 | B27: КЛО_МРЦ70300700 | C27: Прочие доходы | D27: КЛО | E27: 70300700 | F27: ДохРеалУслЛогист | G27: 0 | H27: 0 | I27: 0 | J27: 0 | K27: 0 | L27: 0 | M27: 0 | N27: 0 | O27: 0 | P27: 0 | Q27: 0 | R27: 0 | S27: 0 | T27: 0
A28: 28 | B28: КЛО_МРЦ70300800 | C28: Прочие доходы | D28: ОПЕРАЦИОННЫЙ | E28: 70300800 | F28: ДоходДогКомиссии | G28: 0 | H28: 0 | I28: 0 | J28: 0 | K28: 0 | L28: 0 | M28: 0 | N28: 0 | O28: 0 | P28: 0 | Q28: 0 | R28: 0 | S28: 0 | T28: 0
A29: 29 | B29: КЛО_МРЦ70300900 | C29: Прочие доходы | D29: ОПЕРАЦИОННЫЙ | E29: 70300900 | F29: ДоходУслугКонечнПотр | G29: 0 | H29: 0 | I29: 0 | J29: 0 | K29: 0 | L29: 0 | M29: 0 | N29: 0 | O29: 0 | P29: 0 | Q29: 0 | R29: 0 | S29: 0 | T29: 0
A30: 30 | B30: КЛО_МРЦ71200000 | C30: Прочие доходы | D30: Дирекция | E30: 71200000 | F30: ДохРеалПрочОбАкт | G30: 0 | H30: 0 | I30: 0 | J30: 0 | K30: 0 | L30: 0 | M30: 0 | N30: 0 | O30: 0 | P30: 0 | Q30: 0 | R30: 0 | S30: 0 | T30: 0
A31: 31 | B31: КЛО_МРЦ71200100 | C31: Прочие доходы | D31: ОПЕРАЦИОННЫЙ+СБ | E31: 71200100 | F31: ДохРеалМакулатуры | G31: 79886.8 | H31: 2.8409112e-07 | I31: 0 | J31: 0 | K31: 9912 | L31: 13862.8 | M31: 12950 | N31: 0 | O31: 8442 | P31: 17626 | Q31: 17094 | R31: 0 | S31: 0 | T31: 0
A32: 32 | B32: КЛО_МРЦ71300000 | C32: Прочие доходы | E32: 71300000 | F32: ДохАренОборудован | G32: 0 | H32: 0 | I32: 0 | J32: 0 | K32: 0 | L32: 0 | M32: 0 | N32: 0 | O32: 0 | P32: 0 | Q32: 0 | R32: 0 | S32: 0 | T32: 0
A33: 33 | B33: КЛО_МРЦ71300200 | C33: Прочие доходы | E33: 71300200 | F33: ДохАренТранспорта | G33: 0 | H33: 0 | I33: 0 | J33: 0 | K33: 0 | L33: 0 | M33: 0 | N33: 0 | O33: 0 | P33: 0 | Q33: 0 | R33: 0 | S33: 0 | T33: 0
A34: 34 | B34: КЛО_МРЦ71500000 | C34: Прочие доходы | D34: КЛО | E34: 71500000 | F34: ПолучШтрафПени | G34: 0 | H34: 0 | I34: 0 | J34: 0 | K34: 0 | L34: 0 | M34: 0 | N34: 0 | O34: 0 | P34: 0 | Q34: 0 | R34: 0 | S34: 0 | T34: 0
A35: 35 | B35: КЛО_МРЦ71500100 | C35: Прочие доходы | E35: 71500100 | F35: ОтримШтрафиПеніКомер | H35: 0
A36: 36 | B36: КЛО_МРЦ71700000 | C36: Прочие доходы | E36: 71700000 | F36: ДохСписКредЗадолж | G36: 0 | H36: 0 | I36: 0 | J36: 0 | K36: 0 | L36: 0 | M36: 0 | N36: 0 | O36: 0 | P36: 0 | Q36: 0 | R36: 0 | S36: 0 | T36: 0
A37: 37 | B37: КЛО_МРЦ71800000 | C37: Прочие доходы | D37: 0 | E37: 71800000 | F37: ДохБесплПолОборАкт | G37: 0 | H37: 0 | I37: 0 | J37: 0 | K37: 0 | L37: 0 | M37: 0 | N37: 0 | O37: 0 | P37: 0 | Q37: 0 | R37: 0 | S37: 0 | T37: 0
A38: 38 | B38: КЛО_МРЦ71800400 | C38: Прочие доходы | E38: 71800400 | F38: ДохБесплПолАктив.РЦ | G38: 0 | H38: 0 | I38: 0 | J38: 0 | K38: 0 | L38: 0 | M38: 0 | N38: 0 | O38: 0 | P38: 0 | Q38: 0 | R38: 0 | S38: 0 | T38: 0
A39: 39 | B39: КЛО_МРЦ71900000 | C39: Прочие доходы | D39: ВСЕ | E39: 71900000 | F39: ПрочДоходОперДеят | G39: 19901014 | H39: 0 | I39: 3105094.5 | J39: 1605268.9 | K39: 1714715.5 | L39: 1532860 | M39: 2907404.5 | N39: 2142183.6 | O39: 1885776 | P39: 2351227 | Q39: 2656483.7 | R39: 0 | S39: 0 | T39: 0
A40: 40 | B40: КЛО_МРЦ71900100 | C40: Прочие доходы | D40: ФИНАНСОВЫЙ | E40: 71900100 | F40: ПрочДоход% банка | G40: 0 | H40: 0 | I40: 0 | J40: 0 | K40: 0 | L40: 0 | M40: 0 | N40: 0 | O40: 0 | P40: 0 | Q40: 0 | R40: 0 | S40: 0 | T40: 0
A41: 41 | B41: КЛО_МРЦ71900500 | C41: Прочие доходы | D41: ОПЕРАЦИОННЫЙ+СБ | E41: 71900500 | F41: ПрДоходИзлишки кассы | G41: 0 | H41: 0 | I41: 0 | J41: 0 | K41: 0 | L41: 0 | M41: 0 | N41: 0 | O41: 0 | P41: 0 | Q41: 0 | R41: 0 | S41: 0 | T41: 0
A42: 42 | B42: КЛО_МРЦ71900600 | C42: Прочие доходы | D42: АДМИН | E42: 71900600 | F42: Доход гостинич услуг | G42: 0 | H42: 0 | I42: 0 | J42: 0 | K42: 0 | L42: 0 | M42: 0 | N42: 0 | O42: 0 | P42: 0 | Q42: 0 | R42: 0 | S42: 0 | T42: 0
A43: 43 | B43: КЛО_МРЦ71900900 | C43: Прочие доходы | E43: 71900900 | F43: ДохідСтраховВідшк | H43: 0
A44: 44 | B44: КЛО_МРЦ71901000 | C44: Прочие доходы | D44: АДМИН | E44: 71901000 | F44: ІнДоход%депозит | G44: 0 | H44: 0 | I44: 0 | J44: 0 | K44: 0 | L44: 0 | M44: 0 | N44: 0 | O44: 0 | P44: 0 | Q44: 0 | R44: 0 | S44: 0 | T44: 0
A45: 45 | C45: Прочие доходы | E45: 1
A46: 46 | E46: 1 | F46: 6. Прочие доходы аренда | G46: 45000 | H46: 4.2991997e-07 | I46: 5000 | J46: 5000 | K46: 5000 | L46: 5000 | M46: 5000 | N46: 5000 | O46: 5000 | P46: 5000 | Q46: 5000 | R46: 0 | S46: 0 | T46: 0
A47: 47 | B47: КЛО_МРЦ71300100 | C47: Прочие доходы аренда | D47: АДМИН | E47: 71300100 | F47: ДохАренПомещений | G47: 45000 | H47: 4.2991997e-07 | I47: 5000 | J47: 5000 | K47: 5000 | L47: 5000 | M47: 5000 | N47: 5000 | O47: 5000 | P47: 5000 | Q47: 5000 | R47: 0 | S47: 0 | T47: 0
A48: 48 | B48: КЛО_МРЦ71900400 | C48: Прочие доходы аренда | D48: АДМИН | E48: 71900400 | F48: ВозмещКомЭксплЗатрат | G48: 0 | H48: 0 | I48: 0 | J48: 0 | K48: 0 | L48: 0 | M48: 0 | N48: 0 | O48: 0 | P48: 0 | Q48: 0 | R48: 0 | S48: 0 | T48: 0
A49: 49 | E49: 1
A50: 50 | E50: 1 | F50: Валовая прибыль | G50: 19739242 | H50: 0.00018491313 | I50: 3103238.2 | J50: 1626535.4 | K50: 1721885.1 | L50: 1531210.4 | M50: 2950259.5 | N50: 2134030.8 | O50: 1873743.4 | P50: 2146885.8 | Q50: 2651453.6 | R50: 0 | S50: 0 | T50: 0
A51: 51 | E51: Затраты
A52: 52 | E52: 1 | F52: 7. Списания и переучеты | G52: -28684211 | H52: -3.8829612e-06 | I52: -1544187 | J52: -3615388.6 | K52: -2556959.6 | L52: -3083264.3 | M52: -2599827.5 | N52: -2665431.5 | O52: -3924202.8 | P52: -5065904 | Q52: -3629045.4 | R52: 0 | S52: 0 | T52: 0
A53: 53 | B53: КЛО_МРЦ80810000 | C53: Списания и переучеты | D53: КЛО+Опер+СБ | E53: 80810000 | F53: РасхТоварПереуч | G53: 517343.71 | H53: 0 | I53: 2987.1 | J53: 32732.23 | K53: 3779.06 | L53: 2632.71 | M53: 129902.97 | N53: 732.7 | O53: 78751.92 | P53: 263206.78 | Q53: 2618.24 | R53: 0 | S53: 0 | T53: 0
A54: 54 | B54: КЛО_МРЦ80810001 | C54: Списания и переучеты | D54: КЛО+Опер+СБ | E54: 80810001 | F54: РасхМатПереучетПроиз | G54: -5908825 | H54: 0 | I54: 1930883.7 | J54: -1270673.2 | K54: -351132.89 | L54: -1069338.6 | M54: -234045.08 | N54: -237518.97 | O54: -525119.56 | P54: -3023846.6 | Q54: -1128033.8 | R54: 0 | S54: 0 | T54: 0
A55: 55 | B55: КЛО_МРЦ80820000 | C55: Списания и переучеты | D55: КЛО+Опер+СБ | E55: 80820000 | F55: РасхТоварПотериСпис | G55: -255161.69 | H55: 0 | I55: 0 | J55: 0 | K55: 0 | L55: 0 | M55: -1677.76 | N55: -151.05 | O55: -302.11 | P55: -253030.77 | Q55: 0 | R55: 0 | S55: 0 | T55: 0
A56: 56 | B56: КЛО_МРЦ80820001 | C56: Списания и переучеты | D56: КЛО+Опер+СБ | E56: 80820001 | F56: РасхМатПотПоСписПр | G56: -23037568 | H56: 0 | I56: -3478057.7 | J56: -2377447.6 | K56: -2209605.7 | L56: -2016558.4 | M56: -2494007.6 | N56: -2428494.2 | O56: -3477533 | P56: -2052233.4 | Q56: -2503629.8 | R56: 0 | S56: 0 | T56: 0
A57: 57 | E57: 1
A58: 58 | E58: 1 | F58: 8. ФОТ, в т.ч. налоги | G58: -75212476 | H58: -3.8829612e-06 | I58: -8062860.9 | J58: -7376629.3 | K58: -7593884.1 | L58: -8085705.2 | M58: -8853555 | N58: -8697168.5 | O58: -9503743.3 | P58: -8321180.7 | Q58: -8717748.5 | R58: 0 | S58: 0 | T58: 0
A59: 59 | B59: КЛО_МРЦ81100000 | C59: ФОТ, в т.ч. налоги | D59: HR+ВСЕ | E59: 81100000 | F59: РасхОплТрОклады | G59: -64608913 | H59: 0 | I59: -6933558.5 | J59: -6161991.5 | K59: -6469881 | L59: -6848666.5 | M59: -7608611.2 | N59: -7453257.3 | O59: -8286876 | P59: -7265122.4 | Q59: -7580948.2 | R59: 0 | S59: 0 | T59: 0
A60: 60 | B60: КЛО_МРЦ81100100 | C60: ФОТ, в т.ч. налоги | D60: HR+ВСЕ | E60: 81100100 | F60: Оплата Моб,ТРО | G60: -627600 | H60: 0 | I60: -67990 | J60: -67990 | K60: -67990 | L60: -67990 | M60: -73220 | N60: -73220 | O60: -73220 | P60: -67990 | Q60: -67990 | R60: 0 | S60: 0 | T60: 0
A61: 61 | B61: КЛО_МРЦ81200000 | C61: ФОТ, в т.ч. налоги | D61: HR+ВСЕ | E61: 81200000 | F61: ПремииПоощрения | G61: 0 | H61: 0 | I61: 0 | J61: 0 | K61: 0 | L61: 0 | M61: 0 | N61: 0 | O61: 0 | P61: 0 | Q61: 0 | R61: 0 | S61: 0 | T61: 0
A62: 62 | B62: КЛО_МРЦ81400000 | C62: ФОТ, в т.ч. налоги | D62: HR+ВСЕ | E62: 81400000 | F62: Оплата отпусков | G62: -2133341.8 | H62: 0 | I62: -217999.17 | J62: -261604.75 | K62: -210532.73 | L62: -275502.66 | M62: -197810.03 | N62: -280264.76 | O62: -267386.09 | P62: -172470.97 | Q62: -249770.64 | R62: 0 | S62: 0 | T62: 0
A63: 63 | B63: КЛО_МРЦ81500000 | C63: ФОТ, в т.ч. налоги | D63: HR+ВСЕ | E63: 81500000 | F63: ПрочРасхНаОплТр | G63: 0 | H63: 0 | I63: 0 | J63: 0 | K63: 0 | L63: 0 | M63: 0 | N63: 0 | O63: 0 | P63: 0 | Q63: 0 | R63: 0 | S63: 0 | T63: 0
A64: 64 | B64: КЛО_МРЦ81500100 | C64: ФОТ, в т.ч. налоги | D64: ФИНАНСОВЫЙ | E64: 81500100 | F64: СПД и директорство | G64: 0 | H64: 0 | I64: 0 | J64: 0 | K64: 0 | L64: 0 | M64: 0 | N64: 0 | O64: 0 | P64: 0 | Q64: 0 | R64: 0 | S64: 0 | T64: 0
A65: 65 | B65: КЛО_МРЦ82100000 | C65: ФОТ, в т.ч. налоги | D65: HR+ВСЕ | E65: 82100000 | F65: Налоги на ФОТ | G65: -7842621.2 | H65: 0 | I65: -843313.31 | J65: -885042.98 | K65: -845480.46 | L65: -893545.99 | M65: -973913.79 | N65: -890426.44 | O65: -876261.22 | P65: -815597.36 | Q65: -819039.64 | R65: 0 | S65: 0 | T65: 0
A66: 66 | B66: КЛО_МРЦ84210100 | C66: ФОТ, в т.ч. налоги | D66: HR+ВСЕ | E66: 84210100 | F66: УслЦенБумагИС | G66: 0 | H66: 0 | I66: 0 | J66: 0 | K66: 0 | L66: 0 | M66: 0 | N66: 0 | O66: 0 | P66: 0 | Q66: 0 | R66: 0 | S66: 0 | T66: 0
A67: 67 | E67: 1
A68: 68 | E68: 1 | F68: 9. Персонал | G68: -406017.9 | H68: 0 | I68: -35546.97 | J68: -46808.71 | K68: -53121.67 | L68: -65225.32 | M68: -68319.83 | N68: -33836.31 | O68: -31505.49 | P68: -28743.91 | Q68: -42909.69 | R68: 0 | S68: 0 | T68: 0
A69: 69 | B69: КЛО_МРЦ81300000 | C69: ФОТ, в т.ч. налоги | D69: HR+ВСЕ | E69: 81300000 | F69: КомпенсацВыплаты | G69: 0 | H69: 0 | I69: 0 | J69: 0 | K69: 0 | L69: 0 | M69: 0 | N69: 0 | O69: 0 | P69: 0 | Q69: 0 | R69: 0 | S69: 0 | T69: 0
A70: 70 | B70: КЛО_МРЦ81300100 | C70: ФОТ, в т.ч. налоги | D70: HR+ВСЕ | E70: 81300100 | F70: КомпЗаИспЛичнТр | G70: -15144 | H70: 0 | I70: 0 | J70: 0 | K70: -4500 | L70: -4500 | M70: -4500 | N70: 0 | O70: -1644 | P70: 0 | Q70: 0 | R70: 0 | S70: 0 | T70: 0
A71: 71 | B71: КЛО_МРЦ81300200 | C71: ФОТ, в т.ч. налоги | D71: HR+ВСЕ | E71: 81300200 | F71: КомпКвартир | G71: 0 | H71: 0 | I71: 0 | J71: 0 | K71: 0 | L71: 0 | M71: 0 | N71: 0 | O71: 0 | P71: 0 | Q71: 0 | R71: 0 | S71: 0 | T71: 0
A72: 72 | B72: КЛО_МРЦ81300300 | C72: ФОТ, в т.ч. налоги | D72: HR+ВСЕ | E72: 81300300 | F72: МатПомощьСотр | G72: -6000 | H72: 0 | I72: 0 | J72: 0 | K72: 0 | L72: 0 | M72: -6000 | N72: 0 | O72: 0 | P72: 0 | Q72: 0 | R72: 0 | S72: 0 | T72: 0
A73: 73 | B73: КЛО_МРЦ81300400 | C73: ФОТ, в т.ч. налоги | D73: HR+ВСЕ | E73: 81300400 | F73: МатПомНаПогребен | G73: 0 | H73: 0 | I73: 0 | J73: 0 | K73: 0 | L73: 0 | M73: 0 | N73: 0 | O73: 0 | P73: 0 | Q73: 0 | R73: 0 | S73: 0 | T73: 0
A74: 74 | B74: КЛО_МРЦ82400000 | C74: ФОТ, в т.ч. налоги | D74: HR+ВСЕ | E74: 82400000 | F74: ОтчислНаИндивСтрах | G74: 0 | H74: 0 | I74: 0 | J74: 0 | K74: 0 | L74: 0 | M74: 0 | N74: 0 | O74: 0 | P74: 0 | Q74: 0 | R74: 0 | S74: 0 | T74: 0
A75: 75 | B75: КЛО_МРЦ84220100 | C75: Персонал | D75: HR | E75: 84220100 | F75: ПерсоналПоиск | G75: 0 | H75: 0 | I75: 0 | J75: 0 | K75: 0 | L75: 0 | M75: 0 | N75: 0 | O75: 0 | P75: 0 | Q75: 0 | R75: 0 | S75: 0 | T75: 0
A76: 76 | B76: КЛО_МРЦ84220200 | C76: Персонал | D76: HR | E76: 84220200 | F76: ПерсоналОбучВнутр | G76: 0 | H76: 0 | I76: 0 | J76: 0 | K76: 0 | L76: 0 | M76: 0 | N76: 0 | O76: 0 | P76: 0 | Q76: 0 | R76: 0 | S76: 0 | T76: 0
A77: 77 | B77: КЛО_МРЦ84220300 | C77: Персонал | D77: HR | E77: 84220300 | F77: ПерсоналОбучВнешн | G77: -13965 | H77: 0 | I77: 0 | J77: 0 | K77: 0 | L77: -11885 | M77: 0 | N77: 0 | O77: 0 | P77: 0 | Q77: -2080 | R77: 0 | S77: 0 | T77: 0
A78: 78 | B78: КЛО_МРЦ84220400 | C78: Персонал | D78: HR | E78: 84220400 | F78: Персонал медосмотры | G78: -40740 | H78: 0 | I78: -520 | J78: -3680 | K78: -5230 | L78: -4760 | M78: -13250 | N78: -580 | O78: 0 | P78: -520 | Q78: -12200 | R78: 0 | S78: 0 | T78: 0
A79: 79 | B79: КЛО_МРЦ84220500 | C79: Персонал | D79: HR | E79: 84220500 | F79: ПерсоналСтажеры | G79: 0 | H79: 0 | I79: 0 | J79: 0 | K79: 0 | L79: 0 | M79: 0 | N79: 0 | O79: 0 | P79: 0 | Q79: 0 | R79: 0 | S79: 0 | T79: 0
A80: 80 | B80: КЛО_МРЦ84220700 | C80: Персонал | D80: HR | E80: 84220700 | F80: Персонал прочее | G80: -330168.9 | H80: 0 | I80: -35026.97 | J80: -43128.71 | K80: -43391.67 | L80: -44080.32 | M80: -44569.83 | N80: -33256.31 | O80: -29861.49 | P80: -28223.91 | Q80: -28629.69 | R80: 0 | S80: 0 | T80: 0
... A82: 82 | B82: КЛО_МРЦ84220900 | C82: Персонал | D82: HR | E82: 84220900 | F82: ПЕРСОН | G82: 0 | H82: 0 | I82: 0 | J82: 0 | K82: 0 | L82: 0 | M82: 0 | N82: 0 | O82: 0 | P82: 0 | Q82: 0 | R82: 0 | S82: 0 | T82: 0
A83: 83 | E83: 1
A84: 84 | E84: 1 | F84: 10. Аренда помещений | G84: -7378141.9 | H84: 0 | I84: -802733.33 | J84: -802733.33 | K84: -802733.33 | L84: -802733.33 | M84: -823566.66 | N84: -823566.66 | O84: -828136.56 | P84: -840213.7 | Q84: -851724.99 | R84: 0 | S84: 0 | T84: 0
A85: 85 | B85: КЛО_МРЦ84160200 | C85: Аренда помещений | D85: АДМИН | E85: 84160200 | F85: Аренда помещений | G85: -7378141.9 | H85: 0 | I85: -802733.33 | J85: -802733.33 | K85: -802733.33 | L85: -802733.33 | M85: -823566.66 | N85: -823566.66 | O85: -828136.56 | P85: -840213.7 | Q85: -851724.99 | R85: 0 | S85: 0 | T85: 0
A86: 86 | E86: 1
A87: 87 | E87: 1 | F87: 11. Коммунальные услуги | G87: -5256146.2 | H87: -6.373593e-05 | I87: -757382.46 | J87: -746300.23 | K87: -720077.57 | L87: -564883.64 | M87: -490833.02 | N87: -453994.9 | O87: -574933.27 | P87: -515593.13 | Q87: -432147.94 | R87: 0 | S87: 0 | T87: 0
A88: 88 | B88: КЛО_МРЦ84030100 | C88: Коммунальные услуги | D88: АДМИН+Опер | E88: 84030100 | F88: КомУслВода | G88: 0 | H88: 0 | I88: 0 | J88: 0 | K88: 0 | L88: 0 | M88: 0 | N88: 0 | O88: 0 | P88: 0 | Q88: 0 | R88: 0 | S88: 0 | T88: 0
A89: 89 | B89: КЛО_МРЦ84030200 | C89: Коммунальные услуги | D89: АДМИН+Опер | E89: 84030200 | F89: КомУслВывОтходМус | G89: -152352.75 | H89: -1.4462436e-06 | I89: -18009.75 | J89: -15576 | K89: -16874 | L89: -16874 | M89: -17523 | N89: -16225 | O89: -17523 | P89: -16874 | Q89: -16874 | R89: 0 | S89: 0 | T89: 0
A90: 90 | B90: КЛО_МРЦ84030300 | C90: Коммунальные услуги | D90: АДМИН+Опер | E90: 84030300 | F90: КомУслГаз | G90: 0 | H90: 0 | I90: 0 | J90: 0 | K90: 0 | L90: 0 | M90: 0 | N90: 0 | O90: 0 | P90: 0 | Q90: 0 | R90: 0 | S90: 0 | T90: 0
A91: 91 | B91: КЛО_МРЦ84030400 | C91: Коммунальные услуги | D91: АДМИН+Опер | E91: 84030400 | F91: КомУслОтопление | G91: 0 | H91: -4.3387308e-06 | I91: 0 | J91: 0 | K91: 0 | L91: 0 | M91: 0 | N91: 0 | O91: 0 | P91: 0 | Q91: 0 | R91: 0 | S91: 0 | T91: 0
A92: 92 | B92: КЛО_МРЦ84030500 | C92: Коммунальные услуги | D92: АДМИН+Опер | E92: 84030500 | F92: КомУслЭлектроэн | G92: -5086597.2 | H92: -5.7849745e-06 | I92: -737462.02 | J92: -728813.54 | K92: -701292.88 | L92: -546098.95 | M92: -471399.33 | N92: -435859.21 | O92: -555499.58 | P92: -496808.44 | Q92: -413363.25 | R92: 0 | S92: 0 | T92: 0
A93: 93 | B93: КЛО_МРЦ84030600 | C93: Коммунальные услуги | D93: АДМИН+Опер | E93: 84030600 | F93: ЭксплуатПрочиеКомун | G93: -17196.21 | H93: -7.2312181e-06 | I93: -1910.69 | J93: -1910.69 | K93: -1910.69 | L93: -1910.69 | M93: -1910.69 | N93: -1910.69 | O93: -1910.69 | P93: -1910.69 | Q93: -1910.69 | R93: 0 | S93: 0 | T93: 0
A94: 94 | B94: КЛО_МРЦ84030800 | C94: Коммунальные услуги | D94: АДМИН+Опер | E94: 84030800 | F94: КомУслЭлВозмещГенер. | G94: 0 | H94: -8.6774617e-06 | I94: 0 | J94: 0 | K94: 0 | L94: 0 | M94: 0 | N94: 0 | O94: 0 | P94: 0 | Q94: 0 | R94: 0 | S94: 0 | T94: 0
A95: 95 | B95: КЛО_МРЦ80300100 | C95: Коммунальные услуги | D95: АДМИН+Опер | E95: 80300100 | F95: РасхГСМ Тех.ИПр.нужд | G95: 0 | H95: -1.0123705e-05 | I95: 0 | J95: 0 | K95: 0 | L95: 0 | M95: 0 | N95: 0 | O95: 0 | P95: 0 | Q95: 0 | R95: 0 | S95: 0 | T95: 0
A96: 96 | E96: 1
A97: 97 | E97: 1 | F97: 12. Логистика | G97: -565751.95 | H97: -4.8480906e-06 | I97: -56200.06 | J97: -52453.51 | K97: -60497.35 | L97: -65502.92 | M97: -60441.65 | N97: -62239.23 | O97: -71346.18 | P97: -67379.58 | Q97: -69691.47 | R97: 0 | S97: 0 | T97: 0
A98: 98 | B98: КЛО_МРЦ84020100 | C98: Логистика | D98: КЛО | E98: 84020100 | F98: Транспортные услуги | G98: -492407.86 | H98: -4.3075533e-06 | I98: -50892.66 | J98: -45886.14 | K98: -53512.66 | L98: -54455.31 | M98: -53296.58 | N98: -55851.67 | O98: -64135.98 | P98: -58327.86 | Q98: -56049 | R98: 0 | S98: 0 | T98: 0
A99: 99 | B99: КЛО_МРЦ84020200 | C99: Логистика | D99: КЛО | E99: 84020200 | F99: Логистика | G99: 0 | H99: 0 | I99: 0 | J99: 0 | K99: 0 | L99: 0 | M99: 0 | N99: 0 | O99: 0 | P99: 0 | Q99: 0 | R99: 0 | S99: 0 | T99: 0
A100: 100 | B100: КЛО_МРЦ84020300 | C100: Логистика | D100: КЛО | E100: 84020300 | F100: ПрочУслСкладХоз | G100: -73344.09 | H100: -5.4053723e-07 | I100: -5307.4 | J100: -6567.37 | K100: -6984.69 | L100: -11047.61 | M100: -7145.07 | N100: -6387.56 | O100: -7210.2 | P100: -9051.72 | Q100: -13642.47 | R100: 0 | S100: 0 | T100: 0
A101: 101 | E101: 1
...

Sheet жовтень
I1: 45658 | J1: 45689 | K1: 45717 | L1: 45748 | M1: 45778 | N1: 45809 | O1: 45839 | P1: 45870 | Q1: 45901 | R1: 45931 | S1: 45962 | T1: 45992
A2: 2 | E2: КЛО_МРЦ | F2: Киев,Фора МРЦ Оросительная,5 | G2: ИТОГО 2024 | H2: % К ОБОРОТУ | I2: 45658 | J2: 45689 | K2: 45717 | L2: 45383 | M2: 45778 | N2: 45809 | O2: 45839 | P2: 45870 | Q2: 45901 | R2: 45931 | S2: 45962 | T2: 45992
A3: 3 | B3: КЛО_МРЦДоходы | E3: Доходы
A4: 4 | C4: mapping Бюджет | D4: Разбивка по Офисам | E4: Код | F4: 1. Выручка | G4: 663725.38 | H4: 4.1113201e-06 | I4: 56312.5 | J4: 43272.3 | K4: 43860.04 | L4: 42136.95 | M4: 133672.61 | N4: 28768.98 | O4: 62942.62 | P4: 105747.07 | Q4: 66810.13 | R4: 80202.18 | S4: 0 | T4: 0
A5: 5 | B5: КЛО_МРЦ70200000 | C5: Валовая прибыль (без бонусов) | D5: ВСЕ | E5: 70200000 | F5: ДоходРеалТовара | G5: 663725.38 | H5: 4.1113201e-06 | I5: 56312.5 | J5: 43272.3 | K5: 43860.04 | L5: 42136.95 | M5: 133672.61 | N5: 28768.98 | O5: 62942.62 | P5: 105747.07 | Q5: 66810.13 | R5: 80202.18 | S5: 0 | T5: 0
A6: 6 | B6: КЛО_МРЦ70200001 | C6: Валовая прибыль (без бонусов) | D6: МАРКЕТИНГ | E6: 70200001 | F6: ДоходРеалПрогрЛояльн | G6: 0 | H6: 0 | I6: 0 | J6: 0 | K6: 0 | L6: 0 | M6: 0 | N6: 0 | O6: 0 | P6: 0 | Q6: 0 | R6: 0 | S6: 0 | T6: 0
A7: 7 | B7: КЛО_МРЦ70200002 | C7: Валовая прибыль (без бонусов) | D7: МАРКЕТИНГ | E7: 70200002 | F7: ДоходРеалТВаучера | G7: 0 | H7: 0 | I7: 0 | J7: 0 | K7: 0 | L7: 0 | M7: 0 | N7: 0 | O7: 0 | P7: 0 | Q7: 0 | R7: 0 | S7: 0 | T7: 0
A8: 8 | B8: КЛО_МРЦ70200003 | C8: Валовая прибыль (без бонусов) | E8: 70200003 | F8: ДоходРеалТовКомиссия | G8: 0 | H8: 0 | I8: 0 | J8: 0 | K8: 0 | L8: 0 | M8: 0 | N8: 0 | O8: 0 | P8: 0 | Q8: 0 | R8: 0 | S8: 0 | T8: 0
A9: 9 | B9: КЛО_МРЦ70200004 | C9: Валовая прибыль (без бонусов) | D9: Дирекция | E9: 70200004 | F9: ДоходРеалАгентсДог | G9: 0 | H9: 0 | I9: 0 | J9: 0 | K9: 0 | L9: 0 | M9: 0 | N9: 0 | O9: 0 | P9: 0 | Q9: 0 | R9: 0 | S9: 0 | T9: 0
A10: 10 | B10: КЛО_МРЦ70200009 | C10: Валовая прибыль (без бонусов) | D10: Дирекция | E10: 70200009 | F10: Недополучен.выручка | G10: 0 | H10: 0 | I10: 0 | J10: 0 | K10: 0 | L10: 0 | M10: 0 | N10: 0 | O10: 0 | P10: 0 | Q10: 0 | R10: 0 | S10: 0 | T10: 0
A11: 11 | B11: КЛО_МРЦ70200200 | C11: Валовая прибыль (без бонусов) | D11: Дирекция | E11: 70200200 | F11: ДоходРеалТовЭкспорт | G11: 0 | H11: 0 | I11: 0 | J11: 0 | K11: 0 | L11: 0 | M11: 0 | N11: 0 | O11: 0 | P11: 0 | Q11: 0 | R11: 0 | S11: 0 | T11: 0
A12: 12 | B12: КЛО_МРЦ70400000 | C12: Валовая прибыль (без бонусов) | D12: Дирекция | E12: 70400000 | F12: ВычетыДоходТовар | G12: 0 | H12: 0 | I12: 0 | J12: 0 | K12: 0 | L12: 0 | M12: 0 | N12: 0 | O12: 0 | P12: 0 | Q12: 0 | R12: 0 | S12: 0 | T12: 0
A13: 13 | B13: КЛО_МРЦ70430000 | C13: Валовая прибыль (без бонусов) | D13: Дирекция | E13: 70430000 | F13: ВычетыДоходАгентсДог | G13: 0 | H13: 0 | I13: 0 | J13: 0 | K13: 0 | L13: 0 | M13: 0 | N13: 0 | O13: 0 | P13: 0 | Q13: 0 | R13: 0 | S13: 0 | T13: 0
A14: 14 | E14: 1
A15: 15 | E15: 1 | F15: 2. Себестоимость | G15: -973664.21 | H15: -4.0635167e-06 | I15: -63168.81 | J15: -27005.75 | K15: -51602.41 | L15: -62649.3 | M15: -108767.59 | N15: -41921.78 | O15: -88417.27 | P15: -332714.32 | Q15: -93934.26 | R15: -103482.72 | S15: 0 | T15: 0
A16: 16 | B16: КЛО_МРЦ90200000 | C16: Валовая прибыль (без бонусов) | D16: КЛО | E16: 90200000 | F16: СебестРеализТоваров | G16: -314377.51 | H16: -7.8532048e-10 | I16: 0 | J16: -27.4 | K16: 0 | L16: 0 | M16: -19296.99 | N16: 0 | O16: 0 | P16: -274298.58 | Q16: 0 | R16: -20754.54 | S16: 0 | T16: 0
A17: 17 | B17: КЛО_МРЦ90200001 | C17: Валовая прибыль (без бонусов) | D17: КЛО | E17: 90200001 | F17: СебестРеалТоваровПро | G17: -659286.7 | H17: -4.0627314e-06 | I17: -63168.81 | J17: -26978.35 | K17: -51602.41 | L17: -62649.3 | M17: -89470.6 | N17: -41921.78 | O17: -88417.27 | P17: -58415.74 | Q17: -93934.26 | R17: -82728.18 | S17: 0 | T17: 0
A18: 18 | E18: 1
A19: 19 | E19: 1 | F19: 3. Валовая маржа | G19: -309938.83 | H19: 4.7803375e-08 | I19: -6856.31 | J19: 16266.55 | K19: -7742.37 | L19: -20512.35 | M19: 24905.02 | N19: -13152.8 | O19: -25474.65 | P19: -226967.25 | Q19: -27124.13 | R19: -23280.54 | S19: 0 | T19: 0
A20: 20 | E20: 1
A21: 21 | E21: 1 | F21: 4. Бонусы | G21: 0 | H21: 0 | I21: 0 | J21: 0 | K21: 0 | L21: 0 | M21: 0 | N21: 0 | O21: 0 | P21: 0 | Q21: 0 | R21: 0 | S21: 0 | T21: 0
A22: 22 | B22: КЛО_МРЦ71900700 | C22: Бонусы | D22: КЛО | E22: 71900700 | F22: ДоходОтБонусов | G22: 0 | H22: 0 | I22: 0 | J22: 0 | K22: 0 | L22: 0 | M22: 0 | N22: 0 | O22: 0 | P22: 0 | Q22: 0 | R22: 0 | S22: 0 | T22: 0
A23: 23 | E23: 1
A24: 24 | E24: 1 | F24: 5. Прочее - Доходы | G24: 23673814 | H24: 0 | I24: 3105094.5 | J24: 1605268.9 | K24: 1724627.5 | L24: 1546722.8 | M24: 2920354.5 | N24: 2142183.6 | O24: 1894218 | P24: 2368853 | Q24: 2673577.7 | R24: 3692914 | S24: 0 | T24: 0
A25: 25 | B25: КЛО_МРЦ70300000 | C25: Прочие доходы | D25: МАРКЕТИНГ | E25: 70300000 | F25: ДоходРеалРабУсл | G25: 0 | H25: 0 | I25: 0 | J25: 0 | K25: 0 | L25: 0 | M25: 0 | N25: 0 | O25: 0 | P25: 0 | Q25: 0 | R25: 0 | S25: 0 | T25: 0
A26: 26 | B26: КЛО_МРЦ70300200 | C26: Прочие доходы | D26: МАРКЕТИНГ | E26: 70300200 | F26: ДохРазмРеклСобствНН | G26: 0 | H26: 0 | I26: 0 | J26: 0 | K26: 0 | L26: 0 | M26: 0 | N26: 0 | O26: 0 | P26: 0 | Q26: 0 | R26: 0 | S26: 0 | T26: 0
A27: 27 | B27: КЛО_МРЦ70300700 | C27: Прочие доходы | D27: КЛО | E27: 70300700 | F27: ДохРеалУслЛогист | G27: 0 | H27: 0 | I27: 0 | J27: 0 | K27: 0 | L27: 0 | M27: 0 | N27: 0 | O27: 0 | P27: 0 | Q27: 0 | R27: 0 | S27: 0 | T27: 0
A28: 28 | B28: КЛО_МРЦ70300800 | C28: Прочие доходы | D28: ОПЕРАЦИОННЫЙ | E28: 70300800 | F28: ДоходДогКомиссии | G28: 0 | H28: 0 | I28: 0 | J28: 0 | K28: 0 | L28: 0 | M28: 0 | N28: 0 | O28: 0 | P28: 0 | Q28: 0 | R28: 0 | S28: 0 | T28: 0
A29: 29 | B29: КЛО_МРЦ70300900 | C29: Прочие доходы | D29: ОПЕРАЦИОННЫЙ | E29: 70300900 | F29: ДоходУслугКонечнПотр | G29: 0 | H29: 0 | I29: 0 | J29: 0 | K29: 0 | L29: 0 | M29: 0 | N29: 0 | O29: 0 | P29: 0 | Q29: 0 | R29: 0 | S29: 0 | T29: 0
A30: 30 | B30: КЛО_МРЦ71200000 | C30: Прочие доходы | D30: Дирекция | E30: 71200000 | F30: ДохРеалПрочОбАкт | G30: 0 | H30: 0 | I30: 0 | J30: 0 | K30: 0 | L30: 0 | M30: 0 | N30: 0 | O30: 0 | P30: 0 | Q30: 0 | R30: 0 | S30: 0 | T30: 0
A31: 31 | B31: КЛО_МРЦ71200100 | C31: Прочие доходы | D31: ОПЕРАЦИОННЫЙ+СБ | E31: 71200100 | F31: ДохРеалМакулатуры | G31: 93144.8 | H31: 2.8409112e-07 | I31: 0 | J31: 0 | K31: 9912 | L31: 13862.8 | M31: 12950 | N31: 0 | O31: 8442 | P31: 17626 | Q31: 17094 | R31: 13258 | S31: 0 | T31: 0
A32: 32 | B32: КЛО_МРЦ71300000 | C32: Прочие доходы | E32: 71300000 | F32: ДохАренОборудован | G32: 0 | H32: 0 | I32: 0 | J32: 0 | K32: 0 | L32: 0 | M32: 0 | N32: 0 | O32: 0 | P32: 0 | Q32: 0 | R32: 0 | S32: 0 | T32: 0
A33: 33 | B33: КЛО_МРЦ71300200 | C33: Прочие доходы | E33: 71300200 | F33: ДохАренТранспорта | G33: 0 | H33: 0 | I33: 0 | J33: 0 | K33: 0 | L33: 0 | M33: 0 | N33: 0 | O33: 0 | P33: 0 | Q33: 0 | R33: 0 | S33: 0 | T33: 0
A34: 34 | B34: КЛО_МРЦ71500000 | C34: Прочие доходы | D34: КЛО | E34: 71500000 | F34: ПолучШтрафПени | G34: 0 | H34: 0 | I34: 0 | J34: 0 | K34: 0 | L34: 0 | M34: 0 | N34: 0 | O34: 0 | P34: 0 | Q34: 0 | R34: 0 | S34: 0 | T34: 0
A35: 35 | B35: КЛО_МРЦ71500100 | C35: Прочие доходы | E35: 71500100 | F35: ОтримШтрафиПеніКомер | H35: 0
A36: 36 | B36: КЛО_МРЦ71700000 | C36: Прочие доходы | E36: 71700000 | F36: ДохСписКредЗадолж | G36: 0 | H36: 0 | I36: 0 | J36: 0 | K36: 0 | L36: 0 | M36: 0 | N36: 0 | O36: 0 | P36: 0 | Q36: 0 | R36: 0 | S36: 0 | T36: 0
A37: 37 | B37: КЛО_МРЦ71800000 | C37: Прочие доходы | D37: 0 | E37: 71800000 | F37: ДохБесплПолОборАкт | G37: 0 | H37: 0 | I37: 0 | J37: 0 | K37: 0 | L37: 0 | M37: 0 | N37: 0 | O37: 0 | P37: 0 | Q37: 0 | R37: 0 | S37: 0 | T37: 0
A38: 38 | B38: КЛО_МРЦ71800400 | C38: Прочие доходы | E38: 71800400 | F38: ДохБесплПолАктив.РЦ | G38: 0 | H38: 0 | I38: 0 | J38: 0 | K38: 0 | L38: 0 | M38: 0 | N38: 0 | O38: 0 | P38: 0 | Q38: 0 | R38: 0 | S38: 0 | T38: 0
A39: 39 | B39: КЛО_МРЦ71900000 | C39: Прочие доходы | D39: ВСЕ | E39: 71900000 | F39: ПрочДоходОперДеят | G39: 23580670 | H39: 0 | I39: 3105094.5 | J39: 1605268.9 | K39: 1714715.5 | L39: 1532860 | M39: 2907404.5 | N39: 2142183.6 | O39: 1885776 | P39: 2351227 | Q39: 2656483.7 | R39: 3679656 | S39: 0 | T39: 0
A40: 40 | B40: КЛО_МРЦ71900100 | C40: Прочие доходы | D40: ФИНАНСОВЫЙ | E40: 71900100 | F40: ПрочДоход% банка | G40: 0 | H40: 0 | I40: 0 | J40: 0 | K40: 0 | L40: 0 | M40: 0 | N40: 0 | O40: 0 | P40: 0 | Q40: 0 | R40: 0 | S40: 0 | T40: 0
A41: 41 | B41: КЛО_МРЦ71900500 | C41: Прочие доходы | D41: ОПЕРАЦИОННЫЙ+СБ | E41: 71900500 | F41: ПрДоходИзлишки кассы | G41: 0 | H41: 0 | I41: 0 | J41: 0 | K41: 0 | L41: 0 | M41: 0 | N41: 0 | O41: 0 | P41: 0 | Q41: 0 | R41: 0 | S41: 0 | T41: 0
A42: 42 | B42: КЛО_МРЦ71900600 | C42: Прочие доходы | D42: АДМИН | E42: 71900600 | F42: Доход гостинич услуг | G42: 0 | H42: 0 | I42: 0 | J42: 0 | K42: 0 | L42: 0 | M42: 0 | N42: 0 | O42: 0 | P42: 0 | Q42: 0 | R42: 0 | S42: 0 | T42: 0
A43: 43 | B43: КЛО_МРЦ71900900 | C43: Прочие доходы | E43: 71900900 | F43: ДохідСтраховВідшк | H43: 0
A44: 44 | B44: КЛО_МРЦ71901000 | C44: Прочие доходы | D44: АДМИН | E44: 71901000 | F44: ІнДоход%депозит | G44: 0 | H44: 0 | I44: 0 | J44: 0 | K44: 0 | L44: 0 | M44: 0 | N44: 0 | O44: 0 | P44: 0 | Q44: 0 | R44: 0 | S44: 0 | T44: 0
A45: 45 | C45: Прочие доходы | E45: 1
A46: 46 | E46: 1 | F46: 6. Прочие доходы аренда | G46: 50000 | H46: 4.2991997e-07 | I46: 5000 | J46: 5000 | K46: 5000 | L46: 5000 | M46: 5000 | N46: 5000 | O46: 5000 | P46: 5000 | Q46: 5000 | R46: 5000 | S46: 0 | T46: 0
A47: 47 | B47: КЛО_МРЦ71300100 | C47: Прочие доходы аренда | D47: АДМИН | E47: 71300100 | F47: ДохАренПомещений | G47: 50000 | H47: 4.2991997e-07 | I47: 5000 | J47: 5000 | K47: 5000 | L47: 5000 | M47: 5000 | N47: 5000 | O47: 5000 | P47: 5000 | Q47: 5000 | R47: 5000 | S47: 0 | T47: 0
A48: 48 | B48: КЛО_МРЦ71900400 | C48: Прочие доходы аренда | D48: АДМИН | E48: 71900400 | F48: ВозмещКомЭксплЗатрат | G48: 0 | H48: 0 | I48: 0 | J48: 0 | K48: 0 | L48: 0 | M48: 0 | N48: 0 | O48: 0 | P48: 0 | Q48: 0 | R48: 0 | S48: 0 | T48: 0
A49: 49 | E49: 1
A50: 50 | E50: 1 | F50: Валовая прибыль | G50: 23413876 | H50: 0.00018491313 | I50: 3103238.2 | J50: 1626535.4 | K50: 1721885.1 | L50: 1531210.4 | M50: 2950259.5 | N50: 2134030.8 | O50: 1873743.4 | P50: 2146885.8 | Q50: 2651453.6 | R50: 3674633.5 | S50: 0 | T50: 0
A51: 51 | E51: Затраты
A52: 52 | E52: 1 | F52: 7. Списания и переучеты | G52: -34032566 | H52: -3.8829612e-06 | I52: -1544187 | J52: -3615388.6 | K52: -2556959.6 | L52: -3083264.3 | M52: -2599827.5 | N52: -2665431.5 | O52: -3924202.8 | P52: -5065904 | Q52: -3629045.4 | R52: -5348355.8 | S52: 0 | T52: 0
A53: 53 | B53: КЛО_МРЦ80810000 | C53: Списания и переучеты | D53: КЛО+Опер+СБ | E53: 80810000 | F53: РасхТоварПереуч | G53: 518003.33 | H53: 0 | I53: 2987.1 | J53: 32732.23 | K53: 3779.06 | L53: 2632.71 | M53: 129902.97 | N53: 732.7 | O53: 78751.92 | P53: 263206.78 | Q53: 2618.24 | R53: 659.62 | S53: 0 | T53: 0
A54: 54 | B54: КЛО_МРЦ80810001 | C54: Списания и переучеты | D54: КЛО+Опер+СБ | E54: 80810001 | F54: РасхМатПереучетПроиз | G54: -7489279.2 | H54: 0 | I54: 1930883.7 | J54: -1270673.2 | K54: -351132.89 | L54: -1069338.6 | M54: -234045.08 | N54: -237518.97 | O54: -525119.56 | P54: -3023846.6 | Q54: -1128033.8 | R54: -1580454.1 | S54: 0 | T54: 0
A55: 55 | B55: КЛО_МРЦ80820000 | C55: Списания и переучеты | D55: КЛО+Опер+СБ | E55: 80820000 | F55: РасхТоварПотериСпис | G55: -255161.69 | H55: 0 | I55: 0 | J55: 0 | K55: 0 | L55: 0 | M55: -1677.76 | N55: -151.05 | O55: -302.11 | P55: -253030.77 | Q55: 0 | R55: 0 | S55: 0 | T55: 0
A56: 56 | B56: КЛО_МРЦ80820001 | C56: Списания и переучеты | D56: КЛО+Опер+СБ | E56: 80820001 | F56: РасхМатПотПоСписПр | G56: -26806129 | H56: 0 | I56: -3478057.7 | J56: -2377447.6 | K56: -2209605.7 | L56: -2016558.4 | M56: -2494007.6 | N56: -2428494.2 | O56: -3477533 | P56: -2052233.4 | Q56: -2503629.8 | R56: -3768561.2 | S56: 0 | T56: 0
A57: 57 | E57: 1
A58: 58 | E58: 1 | F58: 8. ФОТ, в т.ч. налоги | G58: -85217714 | H58: -3.8829612e-06 | I58: -8062860.9 | J58: -7376629.3 | K58: -7593884.1 | L58: -8085705.2 | M58: -8853555 | N58: -8697168.5 | O58: -9503743.3 | P58: -8321180.7 | Q58: -8717748.5 | R58: -10005239 | S58: 0 | T58: 0
A59: 59 | B59: КЛО_МРЦ81100000 | C59: ФОТ, в т.ч. налоги | D59: HR+ВСЕ | E59: 81100000 | F59: РасхОплТрОклады | G59: -73374773 | H59: 0 | I59: -6933558.5 | J59: -6161991.5 | K59: -6469881 | L59: -6848666.5 | M59: -7608611.2 | N59: -7453257.3 | O59: -8286876 | P59: -7265122.4 | Q59: -7580948.2 | R59: -8765860 | S59: 0 | T59: 0
A60: 60 | B60: КЛО_МРЦ81100100 | C60: ФОТ, в т.ч. налоги | D60: HR+ВСЕ | E60: 81100100 | F60: Оплата Моб,ТРО | G60: -690360 | H60: 0 | I60: -67990 | J60: -67990 | K60: -67990 | L60: -67990 | M60: -73220 | N60: -73220 | O60: -73220 | P60: -67990 | Q60: -67990 | R60: -62760 | S60: 0 | T60: 0
A61: 61 | B61: КЛО_МРЦ81200000 | C61: ФОТ, в т.ч. налоги | D61: HR+ВСЕ | E61: 81200000 | F61: ПремииПоощрения | G61: 0 | H61: 0 | I61: 0 | J61: 0 | K61: 0 | L61: 0 | M61: 0 | N61: 0 | O61: 0 | P61: 0 | Q61: 0 | R61: 0 | S61: 0 | T61: 0
A62: 62 | B62: КЛО_МРЦ81400000 | C62: ФОТ, в т.ч. налоги | D62: HR+ВСЕ | E62: 81400000 | F62: Оплата отпусков | G62: -2354133.6 | H62: 0 | I62: -217999.17 | J62: -261604.75 | K62: -210532.73 | L62: -275502.66 | M62: -197810.03 | N62: -280264.76 | O62: -267386.09 | P62: -172470.97 | Q62: -249770.64 | R62: -220791.81 | S62: 0 | T62: 0
A63: 63 | B63: КЛО_МРЦ81500000 | C63: ФОТ, в т.ч. налоги | D63: HR+ВСЕ | E63: 81500000 | F63: ПрочРасхНаОплТр | G63: 0 | H63: 0 | I63: 0 | J63: 0 | K63: 0 | L63: 0 | M63: 0 | N63: 0 | O63: 0 | P63: 0 | Q63: 0 | R63: 0 | S63: 0 | T63: 0
A64: 64 | B64: КЛО_МРЦ81500100 | C64: ФОТ, в т.ч. налоги | D64: ФИНАНСОВЫЙ | E64: 81500100 | F64: СПД и директорство | G64: 0 | H64: 0 | I64: 0 | J64: 0 | K64: 0 | L64: 0 | M64: 0 | N64: 0 | O64: 0 | P64: 0 | Q64: 0 | R64: 0 | S64: 0 | T64: 0
A65: 65 | B65: КЛО_МРЦ82100000 | C65: ФОТ, в т.ч. налоги | D65: HR+ВСЕ | E65: 82100000 | F65: Налоги на ФОТ | G65: -8798448.1 | H65: 0 | I65: -843313.31 | J65: -885042.98 | K65: -845480.46 | L65: -893545.99 | M65: -973913.79 | N65: -890426.44 | O65: -876261.22 | P65: -815597.36 | Q65: -819039.64 | R65: -955826.91 | S65: 0 | T65: 0
A66: 66 | B66: КЛО_МРЦ84210100 | C66: ФОТ, в т.ч. налоги | D66: HR+ВСЕ | E66: 84210100 | F66: УслЦенБумагИС | G66: 0 | H66: 0 | I66: 0 | J66: 0 | K66: 0 | L66: 0 | M66: 0 | N66: 0 | O66: 0 | P66: 0 | Q66: 0 | R66: 0 | S66: 0 | T66: 0
A67: 67 | E67: 1
A68: 68 | E68: 1 | F68: 9. Персонал | G68: -423998.48 | H68: 0 | I68: -35546.97 | J68: -46808.71 | K68: -53121.67 | L68: -65225.32 | M68: -68319.83 | N68: -33836.31 | O68: -31505.49 | P68: -28743.91 | Q68: -42909.69 | R68: -17980.58 | S68: 0 | T68: 0
A69: 69 | B69: КЛО_МРЦ81300000 | C69: ФОТ, в т.ч. налоги | D69: HR+ВСЕ | E69: 81300000 | F69: КомпенсацВыплаты | G69: 0 | H69: 0 | I69: 0 | J69: 0 | K69: 0 | L69: 0 | M69: 0 | N69: 0 | O69: 0 | P69: 0 | Q69: 0 | R69: 0 | S69: 0 | T69: 0
A70: 70 | B70: КЛО_МРЦ81300100 | C70: ФОТ, в т.ч. налоги | D70: HR+ВСЕ | E70: 81300100 | F70: КомпЗаИспЛичнТр | G70: -15144 | H70: 0 | I70: 0 | J70: 0 | K70: -4500 | L70: -4500 | M70: -4500 | N70: 0 | O70: -1644 | P70: 0 | Q70: 0 | R70: 0 | S70: 0 | T70: 0
A71: 71 | B71: КЛО_МРЦ81300200 | C71: ФОТ, в т.ч. налоги | D71: HR+ВСЕ | E71: 81300200 | F71: КомпКвартир | G71: 0 | H71: 0 | I71: 0 | J71: 0 | K71: 0 | L71: 0 | M71: 0 | N71: 0 | O71: 0 | P71: 0 | Q71: 0 | R71: 0 | S71: 0 | T71: 0
A72: 72 | B72: КЛО_МРЦ81300300 | C72: ФОТ, в т.ч. налоги | D72: HR+ВСЕ | E72: 81300300 | F72: МатПомощьСотр | G72: -6000 | H72: 0 | I72: 0 | J72: 0 | K72: 0 | L72: 0 | M72: -6000 | N72: 0 | O72: 0 | P72: 0 | Q72: 0 | R72: 0 | S72: 0 | T72: 0
A73: 73 | B73: КЛО_МРЦ81300400 | C73: ФОТ, в т.ч. налоги | D73: HR+ВСЕ | E73: 81300400 | F73: МатПомНаПогребен | G73: 0 | H73: 0 | I73: 0 | J73: 0 | K73: 0 | L73: 0 | M73: 0 | N73: 0 | O73: 0 | P73: 0 | Q73: 0 | R73: 0 | S73: 0 | T73: 0
A74: 74 | B74: КЛО_МРЦ82400000 | C74: ФОТ, в т.ч. налоги | D74: HR+ВСЕ | E74: 82400000 | F74: ОтчислНаИндивСтрах | G74: 0 | H74: 0 | I74: 0 | J74: 0 | K74: 0 | L74: 0 | M74: 0 | N74: 0 | O74: 0 | P74: 0 | Q74: 0 | R74: 0 | S74: 0 | T74: 0
A75: 75 | B75: КЛО_МРЦ84220100 | C75: Персонал | D75: HR | E75: 84220100 | F75: ПерсоналПоиск | G75: 0 | H75: 0 | I75: 0 | J75: 0 | K75: 0 | L75: 0 | M75: 0 | N75: 0 | O75: 0 | P75: 0 | Q75: 0 | R75: 0 | S75: 0 | T75: 0
A76: 76 | B76: КЛО_МРЦ84220200 | C76: Персонал | D76: HR | E76: 84220200 | F76: ПерсоналОбучВнутр | G76: 0 | H76: 0 | I76: 0 | J76: 0 | K76: 0 | L76: 0 | M76: 0 | N76: 0 | O76: 0 | P76: 0 | Q76: 0 | R76: 0 | S76: 0 | T76: 0
A77: 77 | B77: КЛО_МРЦ84220300 | C77: Персонал | D77: HR | E77: 84220300 | F77: ПерсоналОбучВнешн | G77: -13965 | H77: 0 | I77: 0 | J77: 0 | K77: 0 | L77: -11885 | M77: 0 | N77: 0 | O77: 0 | P77: 0 | Q77: -2080 | R77: 0 | S77: 0 | T77: 0
A78: 78 | B78: КЛО_МРЦ84220400 | C78: Персонал | D78: HR | E78: 84220400 | F78: Персонал медосмотры | G78: -40740 | H78: 0 | I78: -520 | J78: -3680 | K78: -5230 | L78: -4760 | M78: -13250 | N78: -580 | O78: 0 | P78: -520 | Q78: -12200 | R78: 0 | S78: 0 | T78: 0
A79: 79 | B79: КЛО_МРЦ84220500 | C79: Персонал | D79: HR | E79: 84220500 | F79: ПерсоналСтажеры | G79: 0 | H79: 0 | I79: 0 | J79: 0 | K79: 0 | L79: 0 | M79: 0 | N79: 0 | O79: 0 | P79: 0 | Q79: 0 | R79: 0 | S79: 0 | T79: 0
A80: 80 | B80: КЛО_МРЦ84220700 | C80: Персонал | D80: HR | E80: 84220700 | F80: Персонал прочее | G80: -348149.48 | H80: 0 | I80: -35026.97 | J80: -43128.71 | K80: -43391.67 | L80: -44080.32 | M80: -44569.83 | N80: -33256.31 | O80: -29861.49 | P80: -28223.91 | Q80: -28629.69 | R80: -17980.58 | S80: 0 | T80: 0
... A82: 82 | B82: КЛО_МРЦ84220900 | C82: Персонал | D82: HR | E82: 84220900 | F82: ПЕРСОН | G82: 0 | H82: 0 | I82: 0 | J82: 0 | K82: 0 | L82: 0 | M82: 0 | N82: 0 | O82: 0 | P82: 0 | Q82: 0 | R82: 0 | S82: 0 | T82: 0
A83: 83 | E83: 1
A84: 84 | E84: 1 | F84: 10. Аренда помещений | G84: -8250866.9 | H84: 0 | I84: -802733.33 | J84: -802733.33 | K84: -802733.33 | L84: -802733.33 | M84: -823566.66 | N84: -823566.66 | O84: -828136.56 | P84: -840213.7 | Q84: -851724.99 | R84: -872724.99 | S84: 0 | T84: 0
A85: 85 | B85: КЛО_МРЦ84160200 | C85: Аренда помещений | D85: АДМИН | E85: 84160200 | F85: Аренда помещений | G85: -8250866.9 | H85: 0 | I85: -802733.33 | J85: -802733.33 | K85: -802733.33 | L85: -802733.33 | M85: -823566.66 | N85: -823566.66 | O85: -828136.56 | P85: -840213.7 | Q85: -851724.99 | R85: -872724.99 | S85: 0 | T85: 0
A86: 86 | E86: 1
A87: 87 | E87: 1 | F87: 11. Коммунальные услуги | G87: -5977730.2 | H87: -6.373593e-05 | I87: -757382.46 | J87: -746300.23 | K87: -720077.57 | L87: -564883.64 | M87: -490833.02 | N87: -453994.9 | O87: -574933.27 | P87: -515593.13 | Q87: -432147.94 | R87: -721584 | S87: 0 | T87: 0
A88: 88 | B88: КЛО_МРЦ84030100 | C88: Коммунальные услуги | D88: АДМИН+Опер | E88: 84030100 | F88: КомУслВода | G88: 0 | H88: 0 | I88: 0 | J88: 0 | K88: 0 | L88: 0 | M88: 0 | N88: 0 | O88: 0 | P88: 0 | Q88: 0 | R88: 0 | S88: 0 | T88: 0
A89: 89 | B89: КЛО_МРЦ84030200 | C89: Коммунальные услуги | D89: АДМИН+Опер | E89: 84030200 | F89: КомУслВывОтходМус | G89: -169875.75 | H89: -1.4462436e-06 | I89: -18009.75 | J89: -15576 | K89: -16874 | L89: -16874 | M89: -17523 | N89: -16225 | O89: -17523 | P89: -16874 | Q89: -16874 | R89: -17523 | S89: 0 | T89: 0
A90: 90 | B90: КЛО_МРЦ84030300 | C90: Коммунальные услуги | D90: АДМИН+Опер | E90: 84030300 | F90: КомУслГаз | G90: 0 | H90: 0 | I90: 0 | J90: 0 | K90: 0 | L90: 0 | M90: 0 | N90: 0 | O90: 0 | P90: 0 | Q90: 0 | R90: 0 | S90: 0 | T90: 0
A91: 91 | B91: КЛО_МРЦ84030400 | C91: Коммунальные услуги | D91: АДМИН+Опер | E91: 84030400 | F91: КомУслОтопление | G91: 0 | H91: -4.3387308e-06 | I91: 0 | J91: 0 | K91: 0 | L91: 0 | M91: 0 | N91: 0 | O91: 0 | P91: 0 | Q91: 0 | R91: 0 | S91: 0 | T91: 0
A92: 92 | B92: КЛО_МРЦ84030500 | C92: Коммунальные услуги | D92: АДМИН+Опер | E92: 84030500 | F92: КомУслЭлектроэн | G92: -5702185.2 | H92: -5.7849745e-06 | I92: -737462.02 | J92: -728813.54 | K92: -701292.88 | L92: -546098.95 | M92: -471399.33 | N92: -435859.21 | O92: -555499.58 | P92: -496808.44 | Q92: -413363.25 | R92: -615588 | S92: 0 | T92: 0
A93: 93 | B93: КЛО_МРЦ84030600 | C93: Коммунальные услуги | D93: АДМИН+Опер | E93: 84030600 | F93: ЭксплуатПрочиеКомун | G93: -19106.9 | H93: -7.2312181e-06 | I93: -1910.69 | J93: -1910.69 | K93: -1910.69 | L93: -1910.69 | M93: -1910.69 | N93: -1910.69 | O93: -1910.69 | P93: -1910.69 | Q93: -1910.69 | R93: -1910.69 | S93: 0 | T93: 0
A94: 94 | B94: КЛО_МРЦ84030800 | C94: Коммунальные услуги | D94: АДМИН+Опер | E94: 84030800 | F94: КомУслЭлВозмещГенер. | G94: 0 | H94: -8.6774617e-06 | I94: 0 | J94: 0 | K94: 0 | L94: 0 | M94: 0 | N94: 0 | O94: 0 | P94: 0 | Q94: 0 | R94: 0 | S94: 0 | T94: 0
A95: 95 | B95: КЛО_МРЦ80300100 | C95: Коммунальные услуги | D95: АДМИН+Опер | E95: 80300100 | F95: РасхГСМ Тех.ИПр.нужд | G95: -86562.31 | H95: -1.0123705e-05 | I95: 0 | J95: 0 | K95: 0 | L95: 0 | M95: 0 | N95: 0 | O95: 0 | P95: 0 | Q95: 0 | R95: -86562.31 | S95: 0 | T95: 0
A96: 96 | E96: 1
A97: 97 | E97: 1 | F97: 12. Логистика | G97: -634923.21 | H97: -4.8480906e-06 | I97: -56200.06 | J97: -52453.51 | K97: -60497.35 | L97: -65502.92 | M97: -60441.65 | N97: -62239.23 | O97: -71346.18 | P97: -67379.58 | Q97: -69691.47 | R97: -69171.26 | S97: 0 | T97: 0
A98: 98 | B98: КЛО_МРЦ84020100 | C98: Логистика | D98: КЛО | E98: 84020100 | F98: Транспортные услуги | G98: -551730.58 | H98: -4.3075533e-06 | I98: -50892.66 | J98: -45886.14 | K98: -53512.66 | L98: -54455.31 | M98: -53296.58 | N98: -55851.67 | O98: -64135.98 | P98: -58327.86 | Q98: -56049 | R98: -59322.72 | S98: 0 | T98: 0
A99: 99 | B99: КЛО_МРЦ84020200 | C99: Логистика | D99: КЛО | E99: 84020200 | F99: Логистика | G99: 0 | H99: 0 | I99: 0 | J99: 0 | K99: 0 | L99: 0 | M99: 0 | N99: 0 | O99: 0 | P99: 0 | Q99: 0 | R99: 0 | S99: 0 | T99: 0
A100: 100 | B100: КЛО_МРЦ84020300 | C100: Логистика | D100: КЛО | E100: 84020300 | F100: ПрочУслСкладХоз | G100: -83192.63 | H100: -5.4053723e-07 | I100: -5307.4 | J100: -6567.37 | K100: -6984.69 | L100: -11047.61 | M100: -7145.07 | N100: -6387.56 | O100: -7210.2 | P100: -9051.72 | Q100: -13642.47 | R100: -9848.54 | S100: 0 | T100: 0
A101: 101 | E101: 1
...

Sheet листопад
I1: 45658 | J1: 45689 | K1: 45717 | L1: 45748 | M1: 45778 | N1: 45809 | O1: 45839 | P1: 45870 | Q1: 45901 | R1: 45931 | S1: 45962 | T1: 45992
A2: 2 | E2: КЛО_МРЦ | F2: Киев,Фора МРЦ Оросительная,5 | G2: ИТОГО 2024 | H2: % К ОБОРОТУ | I2: 45658 | J2: 45689 | K2: 45717 | L2: 45383 | M2: 45778 | N2: 45809 | O2: 45839 | P2: 45870 | Q2: 45901 | R2: 45931 | S2: 45962 | T2: 45992
A3: 3 | B3: КЛО_МРЦДоходы | E3: Доходы
A4: 4 | C4: mapping Бюджет | D4: Разбивка по Офисам | E4: Код | F4: 1. Выручка | G4: 737234.25 | H4: 4.1113201e-06 | I4: 56312.5 | J4: 43272.3 | K4: 43860.04 | L4: 42136.95 | M4: 133672.61 | N4: 28768.98 | O4: 62942.62 | P4: 105747.07 | Q4: 66810.13 | R4: 80202.18 | S4: 73508.87 | T4: 0
A5: 5 | B5: КЛО_МРЦ70200000 | C5: Валовая прибыль (без бонусов) | D5: ВСЕ | E5: 70200000 | F5: ДоходРеалТовара | G5: 737234.25 | H5: 4.1113201e-06 | I5: 56312.5 | J5: 43272.3 | K5: 43860.04 | L5: 42136.95 | M5: 133672.61 | N5: 28768.98 | O5: 62942.62 | P5: 105747.07 | Q5: 66810.13 | R5: 80202.18 | S5: 73508.87 | T5: 0
A6: 6 | B6: КЛО_МРЦ70200001 | C6: Валовая прибыль (без бонусов) | D6: МАРКЕТИНГ | E6: 70200001 | F6: ДоходРеалПрогрЛояльн | G6: 0 | H6: 0 | I6: 0 | J6: 0 | K6: 0 | L6: 0 | M6: 0 | N6: 0 | O6: 0 | P6: 0 | Q6: 0 | R6: 0 | S6: 0 | T6: 0
A7: 7 | B7: КЛО_МРЦ70200002 | C7: Валовая прибыль (без бонусов) | D7: МАРКЕТИНГ | E7: 70200002 | F7: ДоходРеалТВаучера | G7: 0 | H7: 0 | I7: 0 | J7: 0 | K7: 0 | L7: 0 | M7: 0 | N7: 0 | O7: 0 | P7: 0 | Q7: 0 | R7: 0 | S7: 0 | T7: 0
A8: 8 | B8: КЛО_МРЦ70200003 | C8: Валовая прибыль (без бонусов) | E8: 70200003 | F8: ДоходРеалТовКомиссия | G8: 0 | H8: 0 | I8: 0 | J8: 0 | K8: 0 | L8: 0 | M8: 0 | N8: 0 | O8: 0 | P8: 0 | Q8: 0 | R8: 0 | S8: 0 | T8: 0
A9: 9 | B9: КЛО_МРЦ70200004 | C9: Валовая прибыль (без бонусов) | D9: Дирекция | E9: 70200004 | F9: ДоходРеалАгентсДог | G9: 0 | H9: 0 | I9: 0 | J9: 0 | K9: 0 | L9: 0 | M9: 0 | N9: 0 | O9: 0 | P9: 0 | Q9: 0 | R9: 0 | S9: 0 | T9: 0
A10: 10 | B10: КЛО_МРЦ70200009 | C10: Валовая прибыль (без бонусов) | D10: Дирекция | E10: 70200009 | F10: Недополучен.выручка | G10: 0 | H10: 0 | I10: 0 | J10: 0 | K10: 0 | L10: 0 | M10: 0 | N10: 0 | O10: 0 | P10: 0 | Q10: 0 | R10: 0 | S10: 0 | T10: 0
A11: 11 | B11: КЛО_МРЦ70200200 | C11: Валовая прибыль (без бонусов) | D11: Дирекция | E11: 70200200 | F11: ДоходРеалТовЭкспорт | G11: 0 | H11: 0 | I11: 0 | J11: 0 | K11: 0 | L11: 0 | M11: 0 | N11: 0 | O11: 0 | P11: 0 | Q11: 0 | R11: 0 | S11: 0 | T11: 0
A12: 12 | B12: КЛО_МРЦ70400000 | C12: Валовая прибыль (без бонусов) | D12: Дирекция | E12: 70400000 | F12: ВычетыДоходТовар | G12: 0 | H12: 0 | I12: 0 | J12: 0 | K12: 0 | L12: 0 | M12: 0 | N12: 0 | O12: 0 | P12: 0 | Q12: 0 | R12: 0 | S12: 0 | T12: 0
A13: 13 | B13: КЛО_МРЦ70430000 | C13: Валовая прибыль (без бонусов) | D13: Дирекция | E13: 70430000 | F13: ВычетыДоходАгентсДог | G13: 0 | H13: 0 | I13: 0 | J13: 0 | K13: 0 | L13: 0 | M13: 0 | N13: 0 | O13: 0 | P13: 0 | Q13: 0 | R13: 0 | S13: 0 | T13: 0
A14: 14 | E14: 1
A15: 15 | E15: 1 | F15: 2. Себестоимость | G15: 1471181.6 | H15: -4.0635167e-06 | I15: -63168.81 | J15: -27005.75 | K15: -51602.41 | L15: -62649.3 | M15: -108767.59 | N15: -41921.78 | O15: -88417.27 | P15: -332714.32 | Q15: -93934.26 | R15: -103482.72 | S15: 2444845.8 | T15: 0
A16: 16 | B16: КЛО_МРЦ90200000 | C16: Валовая прибыль (без бонусов) | D16: КЛО | E16: 90200000 | F16: СебестРеализТоваров | G16: -319354.18 | H16: -7.8532048e-10 | I16: 0 | J16: -27.4 | K16: 0 | L16: 0 | M16: -19296.99 | N16: 0 | O16: 0 | P16: -274298.58 | Q16: 0 | R16: -20754.54 | S16: -4976.67 | T16: 0
A17: 17 | B17: КЛО_МРЦ90200001 | C17: Валовая прибыль (без бонусов) | D17: КЛО | E17: 90200001 | F17: СебестРеалТоваровПро | G17: 1790535.7 | H17: -4.0627314e-06 | I17: -63168.81 | J17: -26978.35 | K17: -51602.41 | L17: -62649.3 | M17: -89470.6 | N17: -41921.78 | O17: -88417.27 | P17: -58415.74 | Q17: -93934.26 | R17: -82728.18 | S17: 2449822.4 | T17: 0
A18: 18 | E18: 1
A19: 19 | E19: 1 | F19: 3. Валовая маржа | G19: 2208415.8 | H19: 4.7803375e-08 | I19: -6856.31 | J19: 16266.55 | K19: -7742.37 | L19: -20512.35 | M19: 24905.02 | N19: -13152.8 | O19: -25474.65 | P19: -226967.25 | Q19: -27124.13 | R19: -23280.54 | S19: 2518354.6 | T19: 0
A20: 20 | E20: 1
A21: 21 | E21: 1 | F21: 4. Бонусы | G21: 0 | H21: 0 | I21: 0 | J21: 0 | K21: 0 | L21: 0 | M21: 0 | N21: 0 | O21: 0 | P21: 0 | Q21: 0 | R21: 0 | S21: 0 | T21: 0
A22: 22 | B22: КЛО_МРЦ71900700 | C22: Бонусы | D22: КЛО | E22: 71900700 | F22: ДоходОтБонусов | G22: 0 | H22: 0 | I22: 0 | J22: 0 | K22: 0 | L22: 0 | M22: 0 | N22: 0 | O22: 0 | P22: 0 | Q22: 0 | R22: 0 | S22: 0 | T22: 0
A23: 23 | E23: 1
A24: 24 | E24: 1 | F24: 5. Прочее - Доходы | G24: 26639344 | H24: 0 | I24: 3105094.5 | J24: 1605268.9 | K24: 1724627.5 | L24: 1546722.8 | M24: 2920354.5 | N24: 2142183.6 | O24: 1894218 | P24: 2368853 | Q24: 2673577.7 | R24: 3692914 | S24: 2965529.5 | T24: 0
A25: 25 | B25: КЛО_МРЦ70300000 | C25: Прочие доходы | D25: МАРКЕТИНГ | E25: 70300000 | F25: ДоходРеалРабУсл | G25: 0 | H25: 0 | I25: 0 | J25: 0 | K25: 0 | L25: 0 | M25: 0 | N25: 0 | O25: 0 | P25: 0 | Q25: 0 | R25: 0 | S25: 0 | T25: 0
A26: 26 | B26: КЛО_МРЦ70300200 | C26: Прочие доходы | D26: МАРКЕТИНГ | E26: 70300200 | F26: ДохРазмРеклСобствНН | G26: 0 | H26: 0 | I26: 0 | J26: 0 | K26: 0 | L26: 0 | M26: 0 | N26: 0 | O26: 0 | P26: 0 | Q26: 0 | R26: 0 | S26: 0 | T26: 0
A27: 27 | B27: КЛО_МРЦ70300700 | C27: Прочие доходы | D27: КЛО | E27: 70300700 | F27: ДохРеалУслЛогист | G27: 0 | H27: 0 | I27: 0 | J27: 0 | K27: 0 | L27: 0 | M27: 0 | N27: 0 | O27: 0 | P27: 0 | Q27: 0 | R27: 0 | S27: 0 | T27: 0
A28: 28 | B28: КЛО_МРЦ70300800 | C28: Прочие доходы | D28: ОПЕРАЦИОННЫЙ | E28: 70300800 | F28: ДоходДогКомиссии | G28: 0 | H28: 0 | I28: 0 | J28: 0 | K28: 0 | L28: 0 | M28: 0 | N28: 0 | O28: 0 | P28: 0 | Q28: 0 | R28: 0 | S28: 0 | T28: 0
A29: 29 | B29: КЛО_МРЦ70300900 | C29: Прочие доходы | D29: ОПЕРАЦИОННЫЙ | E29: 70300900 | F29: ДоходУслугКонечнПотр | G29: 0 | H29: 0 | I29: 0 | J29: 0 | K29: 0 | L29: 0 | M29: 0 | N29: 0 | O29: 0 | P29: 0 | Q29: 0 | R29: 0 | S29: 0 | T29: 0
A30: 30 | B30: КЛО_МРЦ71200000 | C30: Прочие доходы | D30: Дирекция | E30: 71200000 | F30: ДохРеалПрочОбАкт | G30: 0 | H30: 0 | I30: 0 | J30: 0 | K30: 0 | L30: 0 | M30: 0 | N30: 0 | O30: 0 | P30: 0 | Q30: 0 | R30: 0 | S30: 0 | T30: 0
A31: 31 | B31: КЛО_МРЦ71200100 | C31: Прочие доходы | D31: ОПЕРАЦИОННЫЙ+СБ | E31: 71200100 | F31: ДохРеалМакулатуры | G31: 93144.8 | H31: 2.8409112e-07 | I31: 0 | J31: 0 | K31: 9912 | L31: 13862.8 | M31: 12950 | N31: 0 | O31: 8442 | P31: 17626 | Q31: 17094 | R31: 13258 | S31: 0 | T31: 0
A32: 32 | B32: КЛО_МРЦ71300000 | C32: Прочие доходы | E32: 71300000 | F32: ДохАренОборудован | G32: 0 | H32: 0 | I32: 0 | J32: 0 | K32: 0 | L32: 0 | M32: 0 | N32: 0 | O32: 0 | P32: 0 | Q32: 0 | R32: 0 | S32: 0 | T32: 0
A33: 33 | B33: КЛО_МРЦ71300200 | C33: Прочие доходы | E33: 71300200 | F33: ДохАренТранспорта | G33: 0 | H33: 0 | I33: 0 | J33: 0 | K33: 0 | L33: 0 | M33: 0 | N33: 0 | O33: 0 | P33: 0 | Q33: 0 | R33: 0 | S33: 0 | T33: 0
A34: 34 | B34: КЛО_МРЦ71500000 | C34: Прочие доходы | D34: КЛО | E34: 71500000 | F34: ПолучШтрафПени | G34: 0 | H34: 0 | I34: 0 | J34: 0 | K34: 0 | L34: 0 | M34: 0 | N34: 0 | O34: 0 | P34: 0 | Q34: 0 | R34: 0 | S34: 0 | T34: 0
A35: 35 | B35: КЛО_МРЦ71500100 | C35: Прочие доходы | E35: 71500100 | F35: ОтримШтрафиПеніКомер | H35: 0
A36: 36 | B36: КЛО_МРЦ71700000 | C36: Прочие доходы | E36: 71700000 | F36: ДохСписКредЗадолж | G36: 0 | H36: 0 | I36: 0 | J36: 0 | K36: 0 | L36: 0 | M36: 0 | N36: 0 | O36: 0 | P36: 0 | Q36: 0 | R36: 0 | S36: 0 | T36: 0
A37: 37 | B37: КЛО_МРЦ71800000 | C37: Прочие доходы | D37: 0 | E37: 71800000 | F37: ДохБесплПолОборАкт | G37: 0 | H37: 0 | I37: 0 | J37: 0 | K37: 0 | L37: 0 | M37: 0 | N37: 0 | O37: 0 | P37: 0 | Q37: 0 | R37: 0 | S37: 0 | T37: 0
A38: 38 | B38: КЛО_МРЦ71800400 | C38: Прочие доходы | E38: 71800400 | F38: ДохБесплПолАктив.РЦ | G38: 0 | H38: 0 | I38: 0 | J38: 0 | K38: 0 | L38: 0 | M38: 0 | N38: 0 | O38: 0 | P38: 0 | Q38: 0 | R38: 0 | S38: 0 | T38: 0
A39: 39 | B39: КЛО_МРЦ71900000 | C39: Прочие доходы | D39: ВСЕ | E39: 71900000 | F39: ПрочДоходОперДеят | G39: 26544699 | H39: 0 | I39: 3105094.5 | J39: 1605268.9 | K39: 1714715.5 | L39: 1532860 | M39: 2907404.5 | N39: 2142183.6 | O39: 1885776 | P39: 2351227 | Q39: 2656483.7 | R39: 3679656 | S39: 2964029.5 | T39: 0
A40: 40 | B40: КЛО_МРЦ71900100 | C40: Прочие доходы | D40: ФИНАНСОВЫЙ | E40: 71900100 | F40: ПрочДоход% банка | G40: 0 | H40: 0 | I40: 0 | J40: 0 | K40: 0 | L40: 0 | M40: 0 | N40: 0 | O40: 0 | P40: 0 | Q40: 0 | R40: 0 | S40: 0 | T40: 0
A41: 41 | B41: КЛО_МРЦ71900500 | C41: Прочие доходы | D41: ОПЕРАЦИОННЫЙ+СБ | E41: 71900500 | F41: ПрДоходИзлишки кассы | G41: 1500 | H41: 0 | I41: 0 | J41: 0 | K41: 0 | L41: 0 | M41: 0 | N41: 0 | O41: 0 | P41: 0 | Q41: 0 | R41: 0 | S41: 1500 | T41: 0
A42: 42 | B42: КЛО_МРЦ71900600 | C42: Прочие доходы | D42: АДМИН | E42: 71900600 | F42: Доход гостинич услуг | G42: 0 | H42: 0 | I42: 0 | J42: 0 | K42: 0 | L42: 0 | M42: 0 | N42: 0 | O42: 0 | P42: 0 | Q42: 0 | R42: 0 | S42: 0 | T42: 0
A43: 43 | B43: КЛО_МРЦ71900900 | C43: Прочие доходы | E43: 71900900 | F43: ДохідСтраховВідшк | H43: 0
A44: 44 | B44: КЛО_МРЦ71901000 | C44: Прочие доходы | D44: АДМИН | E44: 71901000 | F44: ІнДоход%депозит | G44: 0 | H44: 0 | I44: 0 | J44: 0 | K44: 0 | L44: 0 | M44: 0 | N44: 0 | O44: 0 | P44: 0 | Q44: 0 | R44: 0 | S44: 0 | T44: 0
A45: 45 | C45: Прочие доходы | E45: 1
A46: 46 | E46: 1 | F46: 6. Прочие доходы аренда | G46: 55000 | H46: 4.2991997e-07 | I46: 5000 | J46: 5000 | K46: 5000 | L46: 5000 | M46: 5000 | N46: 5000 | O46: 5000 | P46: 5000 | Q46: 5000 | R46: 5000 | S46: 5000 | T46: 0
A47: 47 | B47: КЛО_МРЦ71300100 | C47: Прочие доходы аренда | D47: АДМИН | E47: 71300100 | F47: ДохАренПомещений | G47: 55000 | H47: 4.2991997e-07 | I47: 5000 | J47: 5000 | K47: 5000 | L47: 5000 | M47: 5000 | N47: 5000 | O47: 5000 | P47: 5000 | Q47: 5000 | R47: 5000 | S47: 5000 | T47: 0
A48: 48 | B48: КЛО_МРЦ71900400 | C48: Прочие доходы аренда | D48: АДМИН | E48: 71900400 | F48: ВозмещКомЭксплЗатрат | G48: 0 | H48: 0 | I48: 0 | J48: 0 | K48: 0 | L48: 0 | M48: 0 | N48: 0 | O48: 0 | P48: 0 | Q48: 0 | R48: 0 | S48: 0 | T48: 0
A49: 49 | E49: 1
A50: 50 | E50: 1 | F50: Валовая прибыль | G50: 28902760 | H50: 0.00018491313 | I50: 3103238.2 | J50: 1626535.4 | K50: 1721885.1 | L50: 1531210.4 | M50: 2950259.5 | N50: 2134030.8 | O50: 1873743.4 | P50: 2146885.8 | Q50: 2651453.6 | R50: 3674633.5 | S50: 5488884.1 | T50: 0
A51: 51 | E51: Затраты
A52: 52 | E52: 1 | F52: 7. Списания и переучеты | G52: -37630444 | H52: -3.8829612e-06 | I52: -1544187 | J52: -3615388.6 | K52: -2556959.6 | L52: -3083264.3 | M52: -2599827.5 | N52: -2665431.5 | O52: -3924202.8 | P52: -5065904 | Q52: -3629045.4 | R52: -5348355.8 | S52: -3597877.8 | T52: 0
A53: 53 | B53: КЛО_МРЦ80810000 | C53: Списания и переучеты | D53: КЛО+Опер+СБ | E53: 80810000 | F53: РасхТоварПереуч | G53: 531194.48 | H53: 0 | I53: 2987.1 | J53: 32732.23 | K53: 3779.06 | L53: 2632.71 | M53: 129902.97 | N53: 732.7 | O53: 78751.92 | P53: 263206.78 | Q53: 2618.24 | R53: 659.62 | S53: 13191.15 | T53: 0
A54: 54 | B54: КЛО_МРЦ80810001 | C54: Списания и переучеты | D54: КЛО+Опер+СБ | E54: 80810001 | F54: РасхМатПереучетПроиз | G54: -8759081.9 | H54: 0 | I54: 1930883.7 | J54: -1270673.2 | K54: -351132.89 | L54: -1069338.6 | M54: -234045.08 | N54: -237518.97 | O54: -525119.56 | P54: -3023846.6 | Q54: -1128033.8 | R54: -1580454.1 | S54: -1269802.7 | T54: 0
A55: 55 | B55: КЛО_МРЦ80820000 | C55: Списания и переучеты | D55: КЛО+Опер+СБ | E55: 80820000 | F55: РасхТоварПотериСпис | G55: -255161.69 | H55: 0 | I55: 0 | J55: 0 | K55: 0 | L55: 0 | M55: -1677.76 | N55: -151.05 | O55: -302.11 | P55: -253030.77 | Q55: 0 | R55: 0 | S55: 0 | T55: 0
A56: 56 | B56: КЛО_МРЦ80820001 | C56: Списания и переучеты | D56: КЛО+Опер+СБ | E56: 80820001 | F56: РасхМатПотПоСписПр | G56: -29147395 | H56: 0 | I56: -3478057.7 | J56: -2377447.6 | K56: -2209605.7 | L56: -2016558.4 | M56: -2494007.6 | N56: -2428494.2 | O56: -3477533 | P56: -2052233.4 | Q56: -2503629.8 | R56: -3768561.2 | S56: -2341266.2 | T56: 0
A57: 57 | E57: 1
A58: 58 | E58: 1 | F58: 8. ФОТ, в т.ч. налоги | G58: -94189814 | H58: -3.8829612e-06 | I58: -8062860.9 | J58: -7376629.3 | K58: -7593884.1 | L58: -8085705.2 | M58: -8853555 | N58: -8697168.5 | O58: -9503743.3 | P58: -8321180.7 | Q58: -8717748.5 | R58: -10005239 | S58: -8972100.2 | T58: 0
A59: 59 | B59: КЛО_МРЦ81100000 | C59: ФОТ, в т.ч. налоги | D59: HR+ВСЕ | E59: 81100000 | F59: РасхОплТрОклады | G59: -81105845 | H59: 0 | I59: -6933558.5 | J59: -6161991.5 | K59: -6469881 | L59: -6848666.5 | M59: -7608611.2 | N59: -7453257.3 | O59: -8286876 | P59: -7265122.4 | Q59: -7580948.2 | R59: -8765860 | S59: -7731072.2 | T59: 0
A60: 60 | B60: КЛО_МРЦ81100100 | C60: ФОТ, в т.ч. налоги | D60: HR+ВСЕ | E60: 81100100 | F60: Оплата Моб,ТРО | G60: -753120 | H60: 0 | I60: -67990 | J60: -67990 | K60: -67990 | L60: -67990 | M60: -73220 | N60: -73220 | O60: -73220 | P60: -67990 | Q60: -67990 | R60: -62760 | S60: -62760 | T60: 0
A61: 61 | B61: КЛО_МРЦ81200000 | C61: ФОТ, в т.ч. налоги | D61: HR+ВСЕ | E61: 81200000 | F61: ПремииПоощрения | G61: 0 | H61: 0 | I61: 0 | J61: 0 | K61: 0 | L61: 0 | M61: 0 | N61: 0 | O61: 0 | P61: 0 | Q61: 0 | R61: 0 | S61: 0 | T61: 0
A62: 62 | B62: КЛО_МРЦ81400000 | C62: ФОТ, в т.ч. налоги | D62: HR+ВСЕ | E62: 81400000 | F62: Оплата отпусков | G62: -2609506.7 | H62: 0 | I62: -217999.17 | J62: -261604.75 | K62: -210532.73 | L62: -275502.66 | M62: -197810.03 | N62: -280264.76 | O62: -267386.09 | P62: -172470.97 | Q62: -249770.64 | R62: -220791.81 | S62: -255373.04 | T62: 0
A63: 63 | B63: КЛО_МРЦ81500000 | C63: ФОТ, в т.ч. налоги | D63: HR+ВСЕ | E63: 81500000 | F63: ПрочРасхНаОплТр | G63: 0 | H63: 0 | I63: 0 | J63: 0 | K63: 0 | L63: 0 | M63: 0 | N63: 0 | O63: 0 | P63: 0 | Q63: 0 | R63: 0 | S63: 0 | T63: 0
A64: 64 | B64: КЛО_МРЦ81500100 | C64: ФОТ, в т.ч. налоги | D64: ФИНАНСОВЫЙ | E64: 81500100 | F64: СПД и директорство | G64: 0 | H64: 0 | I64: 0 | J64: 0 | K64: 0 | L64: 0 | M64: 0 | N64: 0 | O64: 0 | P64: 0 | Q64: 0 | R64: 0 | S64: 0 | T64: 0
A65: 65 | B65: КЛО_МРЦ82100000 | C65: ФОТ, в т.ч. налоги | D65: HR+ВСЕ | E65: 82100000 | F65: Налоги на ФОТ | G65: -9721343 | H65: 0 | I65: -843313.31 | J65: -885042.98 | K65: -845480.46 | L65: -893545.99 | M65: -973913.79 | N65: -890426.44 | O65: -876261.22 | P65: -815597.36 | Q65: -819039.64 | R65: -955826.91 | S65: -922894.93 | T65: 0
A66: 66 | B66: КЛО_МРЦ84210100 | C66: ФОТ, в т.ч. налоги | D66: HR+ВСЕ | E66: 84210100 | F66: УслЦенБумагИС | G66: 0 | H66: 0 | I66: 0 | J66: 0 | K66: 0 | L66: 0 | M66: 0 | N66: 0 | O66: 0 | P66: 0 | Q66: 0 | R66: 0 | S66: 0 | T66: 0
A67: 67 | E67: 1
A68: 68 | E68: 1 | F68: 9. Персонал | G68: -437195.07 | H68: 0 | I68: -35546.97 | J68: -46808.71 | K68: -53121.67 | L68: -65225.32 | M68: -68319.83 | N68: -33836.31 | O68: -31505.49 | P68: -28743.91 | Q68: -42909.69 | R68: -17980.58 | S68: -13196.59 | T68: 0
A69: 69 | B69: КЛО_МРЦ81300000 | C69: ФОТ, в т.ч. налоги | D69: HR+ВСЕ | E69: 81300000 | F69: КомпенсацВыплаты | G69: 0 | H69: 0 | I69: 0 | J69: 0 | K69: 0 | L69: 0 | M69: 0 | N69: 0 | O69: 0 | P69: 0 | Q69: 0 | R69: 0 | S69: 0 | T69: 0
A70: 70 | B70: КЛО_МРЦ81300100 | C70: ФОТ, в т.ч. налоги | D70: HR+ВСЕ | E70: 81300100 | F70: КомпЗаИспЛичнТр | G70: -15144 | H70: 0 | I70: 0 | J70: 0 | K70: -4500 | L70: -4500 | M70: -4500 | N70: 0 | O70: -1644 | P70: 0 | Q70: 0 | R70: 0 | S70: 0 | T70: 0
A71: 71 | B71: КЛО_МРЦ81300200 | C71: ФОТ, в т.ч. налоги | D71: HR+ВСЕ | E71: 81300200 | F71: КомпКвартир | G71: 0 | H71: 0 | I71: 0 | J71: 0 | K71: 0 | L71: 0 | M71: 0 | N71: 0 | O71: 0 | P71: 0 | Q71: 0 | R71: 0 | S71: 0 | T71: 0
A72: 72 | B72: КЛО_МРЦ81300300 | C72: ФОТ, в т.ч. налоги | D72: HR+ВСЕ | E72: 81300300 | F72: МатПомощьСотр | G72: -6000 | H72: 0 | I72: 0 | J72: 0 | K72: 0 | L72: 0 | M72: -6000 | N72: 0 | O72: 0 | P72: 0 | Q72: 0 | R72: 0 | S72: 0 | T72: 0
A73: 73 | B73: КЛО_МРЦ81300400 | C73: ФОТ, в т.ч. налоги | D73: HR+ВСЕ | E73: 81300400 | F73: МатПомНаПогребен | G73: 0 | H73: 0 | I73: 0 | J73: 0 | K73: 0 | L73: 0 | M73: 0 | N73: 0 | O73: 0 | P73: 0 | Q73: 0 | R73: 0 | S73: 0 | T73: 0
A74: 74 | B74: КЛО_МРЦ82400000 | C74: ФОТ, в т.ч. налоги | D74: HR+ВСЕ | E74: 82400000 | F74: ОтчислНаИндивСтрах | G74: 0 | H74: 0 | I74: 0 | J74: 0 | K74: 0 | L74: 0 | M74: 0 | N74: 0 | O74: 0 | P74: 0 | Q74: 0 | R74: 0 | S74: 0 | T74: 0
A75: 75 | B75: КЛО_МРЦ84220100 | C75: Персонал | D75: HR | E75: 84220100 | F75: ПерсоналПоиск | G75: 0 | H75: 0 | I75: 0 | J75: 0 | K75: 0 | L75: 0 | M75: 0 | N75: 0 | O75: 0 | P75: 0 | Q75: 0 | R75: 0 | S75: 0 | T75: 0
A76: 76 | B76: КЛО_МРЦ84220200 | C76: Персонал | D76: HR | E76: 84220200 | F76: ПерсоналОбучВнутр | G76: 0 | H76: 0 | I76: 0 | J76: 0 | K76: 0 | L76: 0 | M76: 0 | N76: 0 | O76: 0 | P76: 0 | Q76: 0 | R76: 0 | S76: 0 | T76: 0
A77: 77 | B77: КЛО_МРЦ84220300 | C77: Персонал | D77: HR | E77: 84220300 | F77: ПерсоналОбучВнешн | G77: -13965 | H77: 0 | I77: 0 | J77: 0 | K77: 0 | L77: -11885 | M77: 0 | N77: 0 | O77: 0 | P77: 0 | Q77: -2080 | R77: 0 | S77: 0 | T77: 0
A78: 78 | B78: КЛО_МРЦ84220400 | C78: Персонал | D78: HR | E78: 84220400 | F78: Персонал медосмотры | G78: -40740 | H78: 0 | I78: -520 | J78: -3680 | K78: -5230 | L78: -4760 | M78: -13250 | N78: -580 | O78: 0 | P78: -520 | Q78: -12200 | R78: 0 | S78: 0 | T78: 0
A79: 79 | B79: КЛО_МРЦ84220500 | C79: Персонал | D79: HR | E79: 84220500 | F79: ПерсоналСтажеры | G79: 0 | H79: 0 | I79: 0 | J79: 0 | K79: 0 | L79: 0 | M79: 0 | N79: 0 | O79: 0 | P79: 0 | Q79: 0 | R79: 0 | S79: 0 | T79: 0
A80: 80 | B80: КЛО_МРЦ84220700 | C80: Персонал | D80: HR | E80: 84220700 | F80: Персонал прочее | G80: -361346.07 | H80: 0 | I80: -35026.97 | J80: -43128.71 | K80: -43391.67 | L80: -44080.32 | M80: -44569.83 | N80: -33256.31 | O80: -29861.49 | P80: -28223.91 | Q80: -28629.69 | R80: -17980.58 | S80: -13196.59 | T80: 0
... A82: 82 | B82: КЛО_МРЦ84220900 | C82: Персонал | D82: HR | E82: 84220900 | F82: ПЕРСОН | G82: 0 | H82: 0 | I82: 0 | J82: 0 | K82: 0 | L82: 0 | M82: 0 | N82: 0 | O82: 0 | P82: 0 | Q82: 0 | R82: 0 | S82: 0 | T82: 0
A83: 83 | E83: 1
A84: 84 | E84: 1 | F84: 10. Аренда помещений | G84: -9131925.2 | H84: 0 | I84: -802733.33 | J84: -802733.33 | K84: -802733.33 | L84: -802733.33 | M84: -823566.66 | N84: -823566.66 | O84: -828136.56 | P84: -840213.7 | Q84: -851724.99 | R84: -872724.99 | S84: -881058.33 | T84: 0
A85: 85 | B85: КЛО_МРЦ84160200 | C85: Аренда помещений | D85: АДМИН | E85: 84160200 | F85: Аренда помещений | G85: -9131925.2 | H85: 0 | I85: -802733.33 | J85: -802733.33 | K85: -802733.33 | L85: -802733.33 | M85: -823566.66 | N85: -823566.66 | O85: -828136.56 | P85: -840213.7 | Q85: -851724.99 | R85: -872724.99 | S85: -881058.33 | T85: 0
A86: 86 | E86: 1
A87: 87 | E87: 1 | F87: 11. Коммунальные услуги | G87: -6519329.9 | H87: -6.373593e-05 | I87: -757382.46 | J87: -746300.23 | K87: -720077.57 | L87: -564883.64 | M87: -490833.02 | N87: -453994.9 | O87: -574933.27 | P87: -515593.13 | Q87: -432147.94 | R87: -721584 | S87: -541599.71 | T87: 0
A88: 88 | B88: КЛО_МРЦ84030100 | C88: Коммунальные услуги | D88: АДМИН+Опер | E88: 84030100 | F88: КомУслВода | G88: 0 | H88: 0 | I88: 0 | J88: 0 | K88: 0 | L88: 0 | M88: 0 | N88: 0 | O88: 0 | P88: 0 | Q88: 0 | R88: 0 | S88: 0 | T88: 0
A89: 89 | B89: КЛО_МРЦ84030200 | C89: Коммунальные услуги | D89: АДМИН+Опер | E89: 84030200 | F89: КомУслВывОтходМус | G89: -186100.75 | H89: -1.4462436e-06 | I89: -18009.75 | J89: -15576 | K89: -16874 | L89: -16874 | M89: -17523 | N89: -16225 | O89: -17523 | P89: -16874 | Q89: -16874 | R89: -17523 | S89: -16225 | T89: 0
A90: 90 | B90: КЛО_МРЦ84030300 | C90: Коммунальные услуги | D90: АДМИН+Опер | E90: 84030300 | F90: КомУслГаз | G90: 0 | H90: 0 | I90: 0 | J90: 0 | K90: 0 | L90: 0 | M90: 0 | N90: 0 | O90: 0 | P90: 0 | Q90: 0 | R90: 0 | S90: 0 | T90: 0
A91: 91 | B91: КЛО_МРЦ84030400 | C91: Коммунальные услуги | D91: АДМИН+Опер | E91: 84030400 | F91: КомУслОтопление | G91: 0 | H91: -4.3387308e-06 | I91: 0 | J91: 0 | K91: 0 | L91: 0 | M91: 0 | N91: 0 | O91: 0 | P91: 0 | Q91: 0 | R91: 0 | S91: 0 | T91: 0
A92: 92 | B92: КЛО_МРЦ84030500 | C92: Коммунальные услуги | D92: АДМИН+Опер | E92: 84030500 | F92: КомУслЭлектроэн | G92: -6225649.2 | H92: -5.7849745e-06 | I92: -737462.02 | J92: -728813.54 | K92: -701292.88 | L92: -546098.95 | M92: -471399.33 | N92: -435859.21 | O92: -555499.58 | P92: -496808.44 | Q92: -413363.25 | R92: -615588 | S92: -523464.02 | T92: 0
A93: 93 | B93: КЛО_МРЦ84030600 | C93: Коммунальные услуги | D93: АДМИН+Опер | E93: 84030600 | F93: ЭксплуатПрочиеКомун | G93: -21017.59 | H93: -7.2312181e-06 | I93: -1910.69 | J93: -1910.69 | K93: -1910.69 | L93: -1910.69 | M93: -1910.69 | N93: -1910.69 | O93: -1910.69 | P93: -1910.69 | Q93: -1910.69 | R93: -1910.69 | S93: -1910.69 | T93: 0
A94: 94 | B94: КЛО_МРЦ84030800 | C94: Коммунальные услуги | D94: АДМИН+Опер | E94: 84030800 | F94: КомУслЭлВозмещГенер. | G94: 0 | H94: -8.6774617e-06 | I94: 0 | J94: 0 | K94: 0 | L94: 0 | M94: 0 | N94: 0 | O94: 0 | P94: 0 | Q94: 0 | R94: 0 | S94: 0 | T94: 0
A95: 95 | B95: КЛО_МРЦ80300100 | C95: Коммунальные услуги | D95: АДМИН+Опер | E95: 80300100 | F95: РасхГСМ Тех.ИПр.нужд | G95: -86562.31 | H95: -1.0123705e-05 | I95: 0 | J95: 0 | K95: 0 | L95: 0 | M95: 0 | N95: 0 | O95: 0 | P95: 0 | Q95: 0 | R95: -86562.31 | S95: 0 | T95: 0
A96: 96 | E96: 1
A97: 97 | E97: 1 | F97: 12. Логистика | G97: -680627.38 | H97: -4.8480906e-06 | I97: -56200.06 | J97: -52453.51 | K97: -60497.35 | L97: -65502.92 | M97: -60441.65 | N97: -62239.23 | O97: -71346.18 | P97: -67379.58 | Q97: -69691.47 | R97: -69171.26 | S97: -45704.17 | T97: 0
A98: 98 | B98: КЛО_МРЦ84020100 | C98: Логистика | D98: КЛО | E98: 84020100 | F98: Транспортные услуги | G98: -597434.75 | H98: -4.3075533e-06 | I98: -50892.66 | J98: -45886.14 | K98: -53512.66 | L98: -54455.31 | M98: -53296.58 | N98: -55851.67 | O98: -64135.98 | P98: -58327.86 | Q98: -56049 | R98: -59322.72 | S98: -45704.17 | T98: 0
A99: 99 | B99: КЛО_МРЦ84020200 | C99: Логистика | D99: КЛО | E99: 84020200 | F99: Логистика | G99: 0 | H99: 0 | I99: 0 | J99: 0 | K99: 0 | L99: 0 | M99: 0 | N99: 0 | O99: 0 | P99: 0 | Q99: 0 | R99: 0 | S99: 0 | T99: 0
A100: 100 | B100: КЛО_МРЦ84020300 | C100: Логистика | D100: КЛО | E100: 84020300 | F100: ПрочУслСкладХоз | G100: -83192.63 | H100: -5.4053723e-07 | I100: -5307.4 | J100: -6567.37 | K100: -6984.69 | L100: -11047.61 | M100: -7145.07 | N100: -6387.56 | O100: -7210.2 | P100: -9051.72 | Q100: -13642.47 | R100: -9848.54 | S100: 0 | T100: 0
A101: 101 | E101: 1
...

Sheet січень
I1: 46023 | J1: 46054 | K1: 46082 | L1: 46113 | M1: 46143 | N1: 46174 | O1: 46204 | P1: 46235 | Q1: 46266 | R1: 46296 | S1: 46327 | T1: 46357
A2: 2 | E2: КЛО_МРЦ | F2: Киев,Фора МРЦ Оросительная,5 | G2: ИТОГО 2026 | H2: % К ОБОРОТУ | I2: 46023 | J2: 46054 | K2: 45717 | L2: 45383 | M2: 45778 | N2: 45809 | O2: 45839 | P2: 45870 | Q2: 45901 | R2: 45931 | S2: 45962 | T2: 45992
A3: 3 | B3: КЛО_МРЦДоходы | E3: Доходы
A4: 4 | C4: mapping Бюджет | D4: Разбивка по Офисам | E4: Код | F4: 1. Выручка | G4: 210756.16 | H4: 4.1113201e-06 | I4: 210756.16 | J4: 0 | K4: 0 | L4: 0 | M4: 0 | N4: 0 | O4: 0 | P4: 0 | Q4: 0 | R4: 0 | S4: 0 | T4: 0
A5: 5 | B5: КЛО_МРЦ70200000 | C5: Валовая прибыль (без бонусов) | D5: ВСЕ | E5: 70200000 | F5: ДоходРеалТовара | G5: 210756.16 | H5: 4.1113201e-06 | I5: 210756.16 | J5: 0 | K5: 0 | L5: 0 | M5: 0 | N5: 0 | O5: 0 | P5: 0 | Q5: 0 | R5: 0 | S5: 0 | T5: 0
A6: 6 | B6: КЛО_МРЦ70200001 | C6: Валовая прибыль (без бонусов) | D6: МАРКЕТИНГ | E6: 70200001 | F6: ДоходРеалПрогрЛояльн | G6: 0 | H6: 0 | I6: 0 | J6: 0 | K6: 0 | L6: 0 | M6: 0 | N6: 0 | O6: 0 | P6: 0 | Q6: 0 | R6: 0 | S6: 0 | T6: 0
A7: 7 | B7: КЛО_МРЦ70200002 | C7: Валовая прибыль (без бонусов) | D7: МАРКЕТИНГ | E7: 70200002 | F7: ДоходРеалТВаучера | G7: 0 | H7: 0 | I7: 0 | J7: 0 | K7: 0 | L7: 0 | M7: 0 | N7: 0 | O7: 0 | P7: 0 | Q7: 0 | R7: 0 | S7: 0 | T7: 0
A8: 8 | B8: КЛО_МРЦ70200003 | C8: Валовая прибыль (без бонусов) | E8: 70200003 | F8: ДоходРеалТовКомиссия | G8: 0 | H8: 0 | I8: 0 | J8: 0 | K8: 0 | L8: 0 | M8: 0 | N8: 0 | O8: 0 | P8: 0 | Q8: 0 | R8: 0 | S8: 0 | T8: 0
A9: 9 | B9: КЛО_МРЦ70200004 | C9: Валовая прибыль (без бонусов) | D9: Дирекция | E9: 70200004 | F9: ДоходРеалАгентсДог | G9: 0 | H9: 0 | I9: 0 | J9: 0 | K9: 0 | L9: 0 | M9: 0 | N9: 0 | O9: 0 | P9: 0 | Q9: 0 | R9: 0 | S9: 0 | T9: 0
A10: 10 | B10: КЛО_МРЦ70200009 | C10: Валовая прибыль (без бонусов) | D10: Дирекция | E10: 70200009 | F10: Недополучен.выручка | G10: 0 | H10: 0 | I10: 0 | J10: 0 | K10: 0 | L10: 0 | M10: 0 | N10: 0 | O10: 0 | P10: 0 | Q10: 0 | R10: 0 | S10: 0 | T10: 0
B11: КЛО_МРЦ70300500 | E11: 70300500 | F11: ДохРеалПослСклГосп | G11: 0 | H11: 0 | I11: 0 | J11: 0 | K11: 0 | L11: 0 | M11: 0 | N11: 0 | O11: 0 | P11: 0 | Q11: 0 | R11: 0 | S11: 0 | T11: 0
A12: 12 | B12: КЛО_МРЦ70200200 | C12: Валовая прибыль (без бонусов) | D12: Дирекция | E12: 70200200 | F12: ДоходРеалТовЭкспорт | G12: 0 | H12: 0 | I12: 0 | J12: 0 | K12: 0 | L12: 0 | M12: 0 | N12: 0 | O12: 0 | P12: 0 | Q12: 0 | R12: 0 | S12: 0 | T12: 0
A13: 13 | B13: КЛО_МРЦ70400000 | C13: Валовая прибыль (без бонусов) | D13: Дирекция | E13: 70400000 | F13: ВычетыДоходТовар | G13: 0 | H13: 0 | I13: 0 | J13: 0 | K13: 0 | L13: 0 | M13: 0 | N13: 0 | O13: 0 | P13: 0 | Q13: 0 | R13: 0 | S13: 0 | T13: 0
A14: 14 | B14: КЛО_МРЦ70430000 | C14: Валовая прибыль (без бонусов) | D14: Дирекция | E14: 70430000 | F14: ВычетыДоходАгентсДог | G14: 0 | H14: 0 | I14: 0 | J14: 0 | K14: 0 | L14: 0 | M14: 0 | N14: 0 | O14: 0 | P14: 0 | Q14: 0 | R14: 0 | S14: 0 | T14: 0
A15: 15 | E15: 1
A16: 16 | E16: 1 | F16: 2. Себестоимость | G16: -282646.59 | H16: -4.0635167e-06 | I16: -282646.59 | J16: 0 | K16: 0 | L16: 0 | M16: 0 | N16: 0 | O16: 0 | P16: 0 | Q16: 0 | R16: 0 | S16: 0 | T16: 0
A17: 17 | B17: КЛО_МРЦ90200000 | C17: Валовая прибыль (без бонусов) | D17: КЛО | E17: 90200000 | F17: СебестРеализТоваров | G17: -19211.98 | H17: -7.8532048e-10 | I17: -19211.98 | J17: 0 | K17: 0 | L17: 0 | M17: 0 | N17: 0 | O17: 0 | P17: 0 | Q17: 0 | R17: 0 | S17: 0 | T17: 0
A18: 18 | B18: КЛО_МРЦ90200001 | C18: Валовая прибыль (без бонусов) | D18: КЛО | E18: 90200001 | F18: СебестРеалТоваровПро | G18: -263434.61 | H18: -4.0627314e-06 | I18: -263434.61 | J18: 0 | K18: 0 | L18: 0 | M18: 0 | N18: 0 | O18: 0 | P18: 0 | Q18: 0 | R18: 0 | S18: 0 | T18: 0
A19: 19 | E19: 1
A20: 20 | E20: 1 | F20: 3. Валовая маржа | G20: -71890.43 | H20: 4.7803375e-08 | I20: -71890.43 | J20: 0 | K20: 0 | L20: 0 | M20: 0 | N20: 0 | O20: 0 | P20: 0 | Q20: 0 | R20: 0 | S20: 0 | T20: 0
A21: 21 | E21: 1
A22: 22 | E22: 1 | F22: 4. Бонусы | G22: 0 | H22: 0 | I22: 0 | J22: 0 | K22: 0 | L22: 0 | M22: 0 | N22: 0 | O22: 0 | P22: 0 | Q22: 0 | R22: 0 | S22: 0 | T22: 0
A23: 23 | B23: КЛО_МРЦ71900700 | C23: Бонусы | D23: КЛО | E23: 71900700 | F23: ДоходОтБонусов | G23: 0 | H23: 0 | I23: 0 | J23: 0 | K23: 0 | L23: 0 | M23: 0 | N23: 0 | O23: 0 | P23: 0 | Q23: 0 | R23: 0 | S23: 0 | T23: 0
A24: 24 | E24: 1
A25: 25 | E25: 1 | F25: 5. Прочее - Доходы | G25: 2790647 | H25: 0 | I25: 2790647 | J25: 0 | K25: 0 | L25: 0 | M25: 0 | N25: 0 | O25: 0 | P25: 0 | Q25: 0 | R25: 0 | S25: 0 | T25: 0
A26: 26 | B26: КЛО_МРЦ70300000 | C26: Прочие доходы | D26: МАРКЕТИНГ | E26: 70300000 | F26: ДоходРеалРабУсл | G26: 0 | H26: 0 | I26: 0 | J26: 0 | K26: 0 | L26: 0 | M26: 0 | N26: 0 | O26: 0 | P26: 0 | Q26: 0 | R26: 0 | S26: 0 | T26: 0
A27: 27 | B27: КЛО_МРЦ70300200 | C27: Прочие доходы | D27: МАРКЕТИНГ | E27: 70300200 | F27: ДохРазмРеклСобствНН | G27: 0 | H27: 0 | I27: 0 | J27: 0 | K27: 0 | L27: 0 | M27: 0 | N27: 0 | O27: 0 | P27: 0 | Q27: 0 | R27: 0 | S27: 0 | T27: 0
A28: 28 | B28: КЛО_МРЦ70300700 | C28: Прочие доходы | D28: КЛО | E28: 70300700 | F28: ДохРеалУслЛогист | G28: 0 | H28: 0 | I28: 0 | J28: 0 | K28: 0 | L28: 0 | M28: 0 | N28: 0 | O28: 0 | P28: 0 | Q28: 0 | R28: 0 | S28: 0 | T28: 0
A29: 29 | B29: КЛО_МРЦ70300800 | C29: Прочие доходы | D29: ОПЕРАЦИОННЫЙ | E29: 70300800 | F29: ДоходДогКомиссии | G29: 0 | H29: 0 | I29: 0 | J29: 0 | K29: 0 | L29: 0 | M29: 0 | N29: 0 | O29: 0 | P29: 0 | Q29: 0 | R29: 0 | S29: 0 | T29: 0
A30: 30 | B30: КЛО_МРЦ70300900 | C30: Прочие доходы | D30: ОПЕРАЦИОННЫЙ | E30: 70300900 | F30: ДоходУслугКонечнПотр | G30: 0 | H30: 0 | I30: 0 | J30: 0 | K30: 0 | L30: 0 | M30: 0 | N30: 0 | O30: 0 | P30: 0 | Q30: 0 | R30: 0 | S30: 0 | T30: 0
A31: 31 | B31: КЛО_МРЦ71200000 | C31: Прочие доходы | D31: Дирекция | E31: 71200000 | F31: ДохРеалПрочОбАкт | G31: 0 | H31: 0 | I31: 0 | J31: 0 | K31: 0 | L31: 0 | M31: 0 | N31: 0 | O31: 0 | P31: 0 | Q31: 0 | R31: 0 | S31: 0 | T31: 0
A32: 32 | B32: КЛО_МРЦ71200100 | C32: Прочие доходы | D32: ОПЕРАЦИОННЫЙ+СБ | E32: 71200100 | F32: ДохРеалМакулатуры | G32: 0 | H32: 2.8409112e-07 | I32: 0 | J32: 0 | K32: 0 | L32: 0 | M32: 0 | N32: 0 | O32: 0 | P32: 0 | Q32: 0 | R32: 0 | S32: 0 | T32: 0
A33: 33 | B33: КЛО_МРЦ71300000 | C33: Прочие доходы | E33: 71300000 | F33: ДохАренОборудован | G33: 0 | H33: 0 | I33: 0 | J33: 0 | K33: 0 | L33: 0 | M33: 0 | N33: 0 | O33: 0 | P33: 0 | Q33: 0 | R33: 0 | S33: 0 | T33: 0
A34: 34 | B34: КЛО_МРЦ71300200 | C34: Прочие доходы | E34: 71300200 | F34: ДохАренТранспорта | G34: 0 | H34: 0 | I34: 0 | J34: 0 | K34: 0 | L34: 0 | M34: 0 | N34: 0 | O34: 0 | P34: 0 | Q34: 0 | R34: 0 | S34: 0 | T34: 0
A35: 35 | B35: КЛО_МРЦ71500000 | C35: Прочие доходы | D35: КЛО | E35: 71500000 | F35: ПолучШтрафПени | G35: 0 | H35: 0 | I35: 0 | J35: 0 | K35: 0 | L35: 0 | M35: 0 | N35: 0 | O35: 0 | P35: 0 | Q35: 0 | R35: 0 | S35: 0 | T35: 0
A36: 36 | B36: КЛО_МРЦ71500100 | C36: Прочие доходы | E36: 71500100 | F36: ОтримШтрафиПеніКомер | H36: 0
A37: 37 | B37: КЛО_МРЦ71700000 | C37: Прочие доходы | E37: 71700000 | F37: ДохСписКредЗадолж | G37: 0 | H37: 0 | I37: 0 | J37: 0 | K37: 0 | L37: 0 | M37: 0 | N37: 0 | O37: 0 | P37: 0 | Q37: 0 | R37: 0 | S37: 0 | T37: 0
A38: 38 | B38: КЛО_МРЦ71800000 | C38: Прочие доходы | D38: 0 | E38: 71800000 | F38: ДохБесплПолОборАкт | G38: 0 | H38: 0 | I38: 0 | J38: 0 | K38: 0 | L38: 0 | M38: 0 | N38: 0 | O38: 0 | P38: 0 | Q38: 0 | R38: 0 | S38: 0 | T38: 0
A39: 39 | B39: КЛО_МРЦ71800400 | C39: Прочие доходы | E39: 71800400 | F39: ДохБесплПолАктив.РЦ | G39: 0 | H39: 0 | I39: 0 | J39: 0 | K39: 0 | L39: 0 | M39: 0 | N39: 0 | O39: 0 | P39: 0 | Q39: 0 | R39: 0 | S39: 0 | T39: 0
A40: 40 | B40: КЛО_МРЦ71900000 | C40: Прочие доходы | D40: ВСЕ | E40: 71900000 | F40: ПрочДоходОперДеят | G40: 2790647 | H40: 0 | I40: 2790647 | J40: 0 | K40: 0 | L40: 0 | M40: 0 | N40: 0 | O40: 0 | P40: 0 | Q40: 0 | R40: 0 | S40: 0 | T40: 0
A41: 41 | B41: КЛО_МРЦ71900100 | C41: Прочие доходы | D41: ФИНАНСОВЫЙ | E41: 71900100 | F41: ПрочДоход% банка | G41: 0 | H41: 0 | I41: 0 | J41: 0 | K41: 0 | L41: 0 | M41: 0 | N41: 0 | O41: 0 | P41: 0 | Q41: 0 | R41: 0 | S41: 0 | T41: 0
A42: 42 | B42: КЛО_МРЦ71900500 | C42: Прочие доходы | D42: ОПЕРАЦИОННЫЙ+СБ | E42: 71900500 | F42: ПрДоходИзлишки кассы | G42: 0 | H42: 0 | I42: 0 | J42: 0 | K42: 0 | L42: 0 | M42: 0 | N42: 0 | O42: 0 | P42: 0 | Q42: 0 | R42: 0 | S42: 0 | T42: 0
A43: 43 | B43: КЛО_МРЦ71900600 | C43: Прочие доходы | D43: АДМИН | E43: 71900600 | F43: Доход гостинич услуг | G43: 0 | H43: 0 | I43: 0 | J43: 0 | K43: 0 | L43: 0 | M43: 0 | N43: 0 | O43: 0 | P43: 0 | Q43: 0 | R43: 0 | S43: 0 | T43: 0
A44: 44 | B44: КЛО_МРЦ71900900 | C44: Прочие доходы | E44: 71900900 | F44: ДохідСтраховВідшк | H44: 0
A45: 45 | B45: КЛО_МРЦ71901000 | C45: Прочие доходы | D45: АДМИН | E45: 71901000 | F45: ІнДоход%депозит | G45: 0 | H45: 0 | I45: 0 | J45: 0 | K45: 0 | L45: 0 | M45: 0 | N45: 0 | O45: 0 | P45: 0 | Q45: 0 | R45: 0 | S45: 0 | T45: 0
A46: 46 | C46: Прочие доходы | E46: 1
A47: 47 | E47: 1 | F47: 6. Прочие доходы аренда | G47: 5500 | H47: 4.2991997e-07 | I47: 5500 | J47: 0 | K47: 0 | L47: 0 | M47: 0 | N47: 0 | O47: 0 | P47: 0 | Q47: 0 | R47: 0 | S47: 0 | T47: 0
A48: 48 | B48: КЛО_МРЦ71300100 | C48: Прочие доходы аренда | D48: АДМИН | E48: 71300100 | F48: ДохАренПомещений | G48: 5500 | H48: 4.2991997e-07 | I48: 5500 | J48: 0 | K48: 0 | L48: 0 | M48: 0 | N48: 0 | O48: 0 | P48: 0 | Q48: 0 | R48: 0 | S48: 0 | T48: 0
A49: 49 | B49: КЛО_МРЦ71900400 | C49: Прочие доходы аренда | D49: АДМИН | E49: 71900400 | F49: ВозмещКомЭксплЗатрат | G49: 0 | H49: 0 | I49: 0 | J49: 0 | K49: 0 | L49: 0 | M49: 0 | N49: 0 | O49: 0 | P49: 0 | Q49: 0 | R49: 0 | S49: 0 | T49: 0
A50: 50 | E50: 1
A51: 51 | E51: 1 | F51: Валовая прибыль | G51: 2724256.6 | H51: 0.00018491313 | I51: 2724256.6 | J51: 0 | K51: 0 | L51: 0 | M51: 0 | N51: 0 | O51: 0 | P51: 0 | Q51: 0 | R51: 0 | S51: 0 | T51: 0
A52: 52 | E52: Затраты
A53: 53 | E53: 1 | F53: 7. Списания и переучеты | G53: -3524092.7 | H53: -3.8829612e-06 | I53: -3524092.7 | J53: 0 | K53: 0 | L53: 0 | M53: 0 | N53: 0 | O53: 0 | P53: 0 | Q53: 0 | R53: 0 | S53: 0 | T53: 0
A54: 54 | B54: КЛО_МРЦ80810000 | C54: Списания и переучеты | D54: КЛО+Опер+СБ | E54: 80810000 | F54: РасхТоварПереуч | G54: 14441.21 | H54: 0 | I54: 14441.21 | J54: 0 | K54: 0 | L54: 0 | M54: 0 | N54: 0 | O54: 0 | P54: 0 | Q54: 0 | R54: 0 | S54: 0 | T54: 0
A55: 55 | B55: КЛО_МРЦ80810001 | C55: Списания и переучеты | D55: КЛО+Опер+СБ | E55: 80810001 | F55: РасхМатПереучетПроиз | G55: -1785378.6 | H55: 0 | I55: -1785378.6 | J55: 0 | K55: 0 | L55: 0 | M55: 0 | N55: 0 | O55: 0 | P55: 0 | Q55: 0 | R55: 0 | S55: 0 | T55: 0
A56: 56 | B56: КЛО_МРЦ80820000 | C56: Списания и переучеты | D56: КЛО+Опер+СБ | E56: 80820000 | F56: РасхТоварПотериСпис | G56: 8500 | H56: 0 | I56: 8500 | J56: 0 | K56: 0 | L56: 0 | M56: 0 | N56: 0 | O56: 0 | P56: 0 | Q56: 0 | R56: 0 | S56: 0 | T56: 0
A57: 57 | B57: КЛО_МРЦ80820001 | C57: Списания и переучеты | D57: КЛО+Опер+СБ | E57: 80820001 | F57: РасхМатПотПоСписПр | G57: -1761655.3 | H57: 0 | I57: -1761655.3 | J57: 0 | K57: 0 | L57: 0 | M57: 0 | N57: 0 | O57: 0 | P57: 0 | Q57: 0 | R57: 0 | S57: 0 | T57: 0
A58: 58 | E58: 1
A59: 59 | E59: 1 | F59: 8. ФОТ, в т.ч. налоги | G59: -10148934 | H59: -3.8829612e-06 | I59: -10148934 | J59: 0 | K59: 0 | L59: 0 | M59: 0 | N59: 0 | O59: 0 | P59: 0 | Q59: 0 | R59: 0 | S59: 0 | T59: 0
A60: 60 | B60: КЛО_МРЦ81100000 | C60: ФОТ, в т.ч. налоги | D60: HR+ВСЕ | E60: 81100000 | F60: РасхОплТрОклады | G60: -8769446.9 | H60: 0 | I60: -8769446.9 | J60: 0 | K60: 0 | L60: 0 | M60: 0 | N60: 0 | O60: 0 | P60: 0 | Q60: 0 | R60: 0 | S60: 0 | T60: 0
A61: 61 | B61: КЛО_МРЦ81100100 | C61: ФОТ, в т.ч. налоги | D61: HR+ВСЕ | E61: 81100100 | F61: Оплата Моб,ТРО | G61: -62760 | H61: 0 | I61: -62760 | J61: 0 | K61: 0 | L61: 0 | M61: 0 | N61: 0 | O61: 0 | P61: 0 | Q61: 0 | R61: 0 | S61: 0 | T61: 0
A62: 62 | B62: КЛО_МРЦ81200000 | C62: ФОТ, в т.ч. налоги | D62: HR+ВСЕ | E62: 81200000 | F62: ПремииПоощрения | G62: 0 | H62: 0 | I62: 0 | J62: 0 | K62: 0 | L62: 0 | M62: 0 | N62: 0 | O62: 0 | P62: 0 | Q62: 0 | R62: 0 | S62: 0 | T62: 0
A63: 63 | B63: КЛО_МРЦ81400000 | C63: ФОТ, в т.ч. налоги | D63: HR+ВСЕ | E63: 81400000 | F63: Оплата отпусков | G63: -285170.69 | H63: 0 | I63: -285170.69 | J63: 0 | K63: 0 | L63: 0 | M63: 0 | N63: 0 | O63: 0 | P63: 0 | Q63: 0 | R63: 0 | S63: 0 | T63: 0
A64: 64 | B64: КЛО_МРЦ81500000 | C64: ФОТ, в т.ч. налоги | D64: HR+ВСЕ | E64: 81500000 | F64: ПрочРасхНаОплТр | G64: 0 | H64: 0 | I64: 0 | J64: 0 | K64: 0 | L64: 0 | M64: 0 | N64: 0 | O64: 0 | P64: 0 | Q64: 0 | R64: 0 | S64: 0 | T64: 0
A65: 65 | B65: КЛО_МРЦ81500100 | C65: ФОТ, в т.ч. налоги | D65: ФИНАНСОВЫЙ | E65: 81500100 | F65: СПД и директорство | G65: 0 | H65: 0 | I65: 0 | J65: 0 | K65: 0 | L65: 0 | M65: 0 | N65: 0 | O65: 0 | P65: 0 | Q65: 0 | R65: 0 | S65: 0 | T65: 0
A66: 66 | B66: КЛО_МРЦ82100000 | C66: ФОТ, в т.ч. налоги | D66: HR+ВСЕ | E66: 82100000 | F66: Налоги на ФОТ | G66: -1031556.5 | H66: 0 | I66: -1031556.5 | J66: 0 | K66: 0 | L66: 0 | M66: 0 | N66: 0 | O66: 0 | P66: 0 | Q66: 0 | R66: 0 | S66: 0 | T66: 0
A67: 67 | B67: КЛО_МРЦ84210100 | C67: ФОТ, в т.ч. налоги | D67: HR+ВСЕ | E67: 84210100 | F67: УслЦенБумагИС | G67: 0 | H67: 0 | I67: 0 | J67: 0 | K67: 0 | L67: 0 | M67: 0 | N67: 0 | O67: 0 | P67: 0 | Q67: 0 | R67: 0 | S67: 0 | T67: 0
A68: 68 | E68: 1
A69: 69 | E69: 1 | F69: 9. Персонал | G69: -34869.52 | H69: 0 | I69: -34869.52 | J69: 0 | K69: 0 | L69: 0 | M69: 0 | N69: 0 | O69: 0 | P69: 0 | Q69: 0 | R69: 0 | S69: 0 | T69: 0
A70: 70 | B70: КЛО_МРЦ81300000 | C70: ФОТ, в т.ч. налоги | D70: HR+ВСЕ | E70: 81300000 | F70: КомпенсацВыплаты | G70: 0 | H70: 0 | I70: 0 | J70: 0 | K70: 0 | L70: 0 | M70: 0 | N70: 0 | O70: 0 | P70: 0 | Q70: 0 | R70: 0 | S70: 0 | T70: 0
A71: 71 | B71: КЛО_МРЦ81300100 | C71: ФОТ, в т.ч. налоги | D71: HR+ВСЕ | E71: 81300100 | F71: КомпЗаИспЛичнТр | G71: 0 | H71: 0 | I71: 0 | J71: 0 | K71: 0 | L71: 0 | M71: 0 | N71: 0 | O71: 0 | P71: 0 | Q71: 0 | R71: 0 | S71: 0 | T71: 0
A72: 72 | B72: КЛО_МРЦ81300200 | C72: ФОТ, в т.ч. налоги | D72: HR+ВСЕ | E72: 81300200 | F72: КомпКвартир | G72: 0 | H72: 0 | I72: 0 | J72: 0 | K72: 0 | L72: 0 | M72: 0 | N72: 0 | O72: 0 | P72: 0 | Q72: 0 | R72: 0 | S72: 0 | T72: 0
A73: 73 | B73: КЛО_МРЦ81300300 | C73: ФОТ, в т.ч. налоги | D73: HR+ВСЕ | E73: 81300300 | F73: МатПомощьСотр | G73: 0 | H73: 0 | I73: 0 | J73: 0 | K73: 0 | L73: 0 | M73: 0 | N73: 0 | O73: 0 | P73: 0 | Q73: 0 | R73: 0 | S73: 0 | T73: 0
A74: 74 | B74: КЛО_МРЦ81300400 | C74: ФОТ, в т.ч. налоги | D74: HR+ВСЕ | E74: 81300400 | F74: МатПомНаПогребен | G74: 0 | H74: 0 | I74: 0 | J74: 0 | K74: 0 | L74: 0 | M74: 0 | N74: 0 | O74: 0 | P74: 0 | Q74: 0 | R74: 0 | S74: 0 | T74: 0
A75: 75 | B75: КЛО_МРЦ82400000 | C75: ФОТ, в т.ч. налоги | D75: HR+ВСЕ | E75: 82400000 | F75: ОтчислНаИндивСтрах | G75: 0 | H75: 0 | I75: 0 | J75: 0 | K75: 0 | L75: 0 | M75: 0 | N75: 0 | O75: 0 | P75: 0 | Q75: 0 | R75: 0 | S75: 0 | T75: 0
A76: 76 | B76: КЛО_МРЦ84220100 | C76: Персонал | D76: HR | E76: 84220100 | F76: ПерсоналПоиск | G76: 0 | H76: 0 | I76: 0 | J76: 0 | K76: 0 | L76: 0 | M76: 0 | N76: 0 | O76: 0 | P76: 0 | Q76: 0 | R76: 0 | S76: 0 | T76: 0
A77: 77 | B77: КЛО_МРЦ84220200 | C77: Персонал | D77: HR | E77: 84220200 | F77: ПерсоналОбучВнутр | G77: 0 | H77: 0 | I77: 0 | J77: 0 | K77: 0 | L77: 0 | M77: 0 | N77: 0 | O77: 0 | P77: 0 | Q77: 0 | R77: 0 | S77: 0 | T77: 0
A78: 78 | B78: КЛО_МРЦ84220300 | C78: Персонал | D78: HR | E78: 84220300 | F78: ПерсоналОбучВнешн | G78: 0 | H78: 0 | I78: 0 | J78: 0 | K78: 0 | L78: 0 | M78: 0 | N78: 0 | O78: 0 | P78: 0 | Q78: 0 | R78: 0 | S78: 0 | T78: 0
A79: 79 | B79: КЛО_МРЦ84220400 | C79: Персонал | D79: HR | E79: 84220400 | F79: Персонал медосмотры | G79: -1210 | H79: 0 | I79: -1210 | J79: 0 | K79: 0 | L79: 0 | M79: 0 | N79: 0 | O79: 0 | P79: 0 | Q79: 0 | R79: 0 | S79: 0 | T79: 0
A80: 80 | B80: КЛО_МРЦ84220500 | C80: Персонал | D80: HR | E80: 84220500 | F80: ПерсоналСтажеры | G80: 0 | H80: 0 | I80: 0 | J80: 0 | K80: 0 | L80: 0 | M80: 0 | N80: 0 | O80: 0 | P80: 0 | Q80: 0 | R80: 0 | S80: 0 | T80: 0
A81: 81 | B81: КЛО_МРЦ84220700 | C81: Персонал | D81: HR | E81: 84220700 | F81: Персонал прочее | G81: -33659.52 | H81: 0 | I81: -33659.52 | J81: 0 | K81: 0 | L81: 0 | M81: 0 | N81: 0 | O81: 0 | P81: 0 | Q81: 0 | R81: 0 | S81: 0 | T81: 0
... A83: 83 | B83: КЛО_МРЦ84220900 | C83: Персонал | D83: HR | E83: 84220900 | F83: ПЕРСОН | G83: 0 | H83: 0 | I83: 0 | J83: 0 | K83: 0 | L83: 0 | M83: 0 | N83: 0 | O83: 0 | P83: 0 | Q83: 0 | R83: 0 | S83: 0 | T83: 0
A84: 84 | E84: 1
A85: 85 | E85: 1 | F85: 10. Аренда помещений | G85: -876724.99 | H85: 0 | I85: -876724.99 | J85: 0 | K85: 0 | L85: 0 | M85: 0 | N85: 0 | O85: 0 | P85: 0 | Q85: 0 | R85: 0 | S85: 0 | T85: 0
A86: 86 | B86: КЛО_МРЦ84160200 | C86: Аренда помещений | D86: АДМИН | E86: 84160200 | F86: Аренда помещений | G86: -876724.99 | H86: 0 | I86: -876724.99 | J86: 0 | K86: 0 | L86: 0 | M86: 0 | N86: 0 | O86: 0 | P86: 0 | Q86: 0 | R86: 0 | S86: 0 | T86: 0
A87: 87 | E87: 1
A88: 88 | E88: 1 | F88: 11. Коммунальные услуги | G88: -1041059.7 | H88: -6.373593e-05 | I88: -1041059.7 | J88: 0 | K88: 0 | L88: 0 | M88: 0 | N88: 0 | O88: 0 | P88: 0 | Q88: 0 | R88: 0 | S88: 0 | T88: 0
A89: 89 | B89: КЛО_МРЦ84030100 | C89: Коммунальные услуги | D89: АДМИН+Опер | E89: 84030100 | F89: КомУслВода | G89: 0 | H89: 0 | I89: 0 | J89: 0 | K89: 0 | L89: 0 | M89: 0 | N89: 0 | O89: 0 | P89: 0 | Q89: 0 | R89: 0 | S89: 0 | T89: 0
A90: 90 | B90: КЛО_МРЦ84030200 | C90: Коммунальные услуги | D90: АДМИН+Опер | E90: 84030200 | F90: КомУслВывОтходМус | G90: -17523 | H90: -1.4462436e-06 | I90: -17523 | J90: 0 | K90: 0 | L90: 0 | M90: 0 | N90: 0 | O90: 0 | P90: 0 | Q90: 0 | R90: 0 | S90: 0 | T90: 0
A91: 91 | B91: КЛО_МРЦ84030300 | C91: Коммунальные услуги | D91: АДМИН+Опер | E91: 84030300 | F91: КомУслГаз | G91: 0 | H91: 0 | I91: 0 | J91: 0 | K91: 0 | L91: 0 | M91: 0 | N91: 0 | O91: 0 | P91: 0 | Q91: 0 | R91: 0 | S91: 0 | T91: 0
A92: 92 | B92: КЛО_МРЦ84030400 | C92: Коммунальные услуги | D92: АДМИН+Опер | E92: 84030400 | F92: КомУслОтопление | G92: 0 | H92: -4.3387308e-06 | I92: 0 | J92: 0 | K92: 0 | L92: 0 | M92: 0 | N92: 0 | O92: 0 | P92: 0 | Q92: 0 | R92: 0 | S92: 0 | T92: 0
A93: 93 | B93: КЛО_МРЦ84030500 | C93: Коммунальные услуги | D93: АДМИН+Опер | E93: 84030500 | F93: КомУслЭлектроэн | G93: -558576.45 | H93: -5.7849745e-06 | I93: -558576.45 | J93: 0 | K93: 0 | L93: 0 | M93: 0 | N93: 0 | O93: 0 | P93: 0 | Q93: 0 | R93: 0 | S93: 0 | T93: 0
A94: 94 | B94: КЛО_МРЦ84030600 | C94: Коммунальные услуги | D94: АДМИН+Опер | E94: 84030600 | F94: ЭксплуатПрочиеКомун | G94: -17910.69 | H94: -7.2312181e-06 | I94: -17910.69 | J94: 0 | K94: 0 | L94: 0 | M94: 0 | N94: 0 | O94: 0 | P94: 0 | Q94: 0 | R94: 0 | S94: 0 | T94: 0
A95: 95 | B95: КЛО_МРЦ84030800 | C95: Коммунальные услуги | D95: АДМИН+Опер | E95: 84030800 | F95: КомУслЭлВозмещГенер. | G95: 0 | H95: -8.6774617e-06 | I95: 0 | J95: 0 | K95: 0 | L95: 0 | M95: 0 | N95: 0 | O95: 0 | P95: 0 | Q95: 0 | R95: 0 | S95: 0 | T95: 0
A96: 96 | B96: КЛО_МРЦ80300100 | C96: Коммунальные услуги | D96: АДМИН+Опер | E96: 80300100 | F96: РасхГСМ Тех.ИПр.нужд | G96: -447049.53 | H96: -1.0123705e-05 | I96: -447049.53 | J96: 0 | K96: 0 | L96: 0 | M96: 0 | N96: 0 | O96: 0 | P96: 0 | Q96: 0 | R96: 0 | S96: 0 | T96: 0
A97: 97 | E97: 1
A98: 98 | E98: 1 | F98: 12. Логистика | G98: -74000 | H98: -4.8480906e-06 | I98: -74000 | J98: 0 | K98: 0 | L98: 0 | M98: 0 | N98: 0 | O98: 0 | P98: 0 | Q98: 0 | R98: 0 | S98: 0 | T98: 0
A99: 99 | B99: КЛО_МРЦ84020100 | C99: Логистика | D99: КЛО | E99: 84020100 | F99: Транспортные услуги | G99: -74000 | H99: -4.3075533e-06 | I99: -74000 | J99: 0 | K99: 0 | L99: 0 | M99: 0 | N99: 0 | O99: 0 | P99: 0 | Q99: 0 | R99: 0 | S99: 0 | T99: 0
A100: 100 | B100: КЛО_МРЦ84020200 | C100: Логистика | D100: КЛО | E100: 84020200 | F100: Логистика | G100: 0 | H100: 0 | I100: 0 | J100: 0 | K100: 0 | L100: 0 | M100: 0 | N100: 0 | O100: 0 | P100: 0 | Q100: 0 | R100: 0 | S100: 0 | T100: 0
A101: 101 | B101: КЛО_МРЦ84020300 | C101: Логистика | D101: КЛО | E101: 84020300 | F101: ПрочУслСкладХоз | G101: 0 | H101: -5.4053723e-07 | I101: 0 | J101: 0 | K101: 0 | L101: 0 | M101: 0 | N101: 0 | O101: 0 | P101: 0 | Q101: 0 | R101: 0 | S101: 0 | T101: 0
...

Sheet лютий
I1: 46023 | J1: 46054 | K1: 46082 | L1: 46113 | M1: 46143 | N1: 46174 | O1: 46204 | P1: 46235 | Q1: 46266 | R1: 46296 | S1: 46327 | T1: 46357
A2: 2 | E2: КЛО_МРЦ | F2: Киев,Фора МРЦ Оросительная,5 | G2: ИТОГО 2026 | H2: % К ОБОРОТУ | I2: 46023 | J2: 46054 | K2: 45717 | L2: 45383 | M2: 45778 | N2: 45809 | O2: 45839 | P2: 45870 | Q2: 45901 | R2: 45931 | S2: 45962 | T2: 45992
A3: 3 | B3: КЛО_МРЦДоходы | E3: Доходы
A4: 4 | C4: mapping Бюджет | D4: Разбивка по Офисам | E4: Код | F4: 1. Выручка | G4: 744503.87 | H4: 4.1113201e-06 | I4: 421512.32 | J4: 169293.48 | K4: 153698.07 | L4: 0 | M4: 0 | N4: 0 | O4: 0 | P4: 0 | Q4: 0 | R4: 0 | S4: 0 | T4: 0
A5: 5 | B5: КЛО_МРЦ70200000 | C5: Валовая прибыль (без бонусов) | D5: ВСЕ | E5: 70200000 | F5: ДоходРеалТовара | G5: 744503.87 | H5: 4.1113201e-06 | I5: 421512.32 | J5: 169293.48 | K5: 153698.07 | L5: 0 | M5: 0 | N5: 0 | O5: 0 | P5: 0 | Q5: 0 | R5: 0 | S5: 0 | T5: 0
A6: 6 | B6: КЛО_МРЦ70200001 | C6: Валовая прибыль (без бонусов) | D6: МАРКЕТИНГ | E6: 70200001 | F6: ДоходРеалПрогрЛояльн | G6: 0 | H6: 0 | I6: 0 | J6: 0 | K6: 0 | L6: 0 | M6: 0 | N6: 0 | O6: 0 | P6: 0 | Q6: 0 | R6: 0 | S6: 0 | T6: 0
A7: 7 | B7: КЛО_МРЦ70200002 | C7: Валовая прибыль (без бонусов) | D7: МАРКЕТИНГ | E7: 70200002 | F7: ДоходРеалТВаучера | G7: 0 | H7: 0 | I7: 0 | J7: 0 | K7: 0 | L7: 0 | M7: 0 | N7: 0 | O7: 0 | P7: 0 | Q7: 0 | R7: 0 | S7: 0 | T7: 0
A8: 8 | B8: КЛО_МРЦ70200003 | C8: Валовая прибыль (без бонусов) | E8: 70200003 | F8: ДоходРеалТовКомиссия | G8: 0 | H8: 0 | I8: 0 | J8: 0 | K8: 0 | L8: 0 | M8: 0 | N8: 0 | O8: 0 | P8: 0 | Q8: 0 | R8: 0 | S8: 0 | T8: 0
A9: 9 | B9: КЛО_МРЦ70200004 | C9: Валовая прибыль (без бонусов) | D9: Дирекция | E9: 70200004 | F9: ДоходРеалАгентсДог | G9: 0 | H9: 0 | I9: 0 | J9: 0 | K9: 0 | L9: 0 | M9: 0 | N9: 0 | O9: 0 | P9: 0 | Q9: 0 | R9: 0 | S9: 0 | T9: 0
A10: 10 | B10: КЛО_МРЦ70200009 | C10: Валовая прибыль (без бонусов) | D10: Дирекция | E10: 70200009 | F10: Недополучен.выручка | G10: 0 | H10: 0 | I10: 0 | J10: 0 | K10: 0 | L10: 0 | M10: 0 | N10: 0 | O10: 0 | P10: 0 | Q10: 0 | R10: 0 | S10: 0 | T10: 0
B11: КЛО_МРЦ70300500 | E11: 70300500 | F11: ДохРеалПослСклГосп | G11: 0 | H11: 0 | I11: 0 | J11: 0 | K11: 0 | L11: 0 | M11: 0 | N11: 0 | O11: 0 | P11: 0 | Q11: 0 | R11: 0 | S11: 0 | T11: 0
A12: 12 | B12: КЛО_МРЦ70200200 | C12: Валовая прибыль (без бонусов) | D12: Дирекция | E12: 70200200 | F12: ДоходРеалТовЭкспорт | G12: 0 | H12: 0 | I12: 0 | J12: 0 | K12: 0 | L12: 0 | M12: 0 | N12: 0 | O12: 0 | P12: 0 | Q12: 0 | R12: 0 | S12: 0 | T12: 0
A13: 13 | B13: КЛО_МРЦ70400000 | C13: Валовая прибыль (без бонусов) | D13: Дирекция | E13: 70400000 | F13: ВычетыДоходТовар | G13: 0 | H13: 0 | I13: 0 | J13: 0 | K13: 0 | L13: 0 | M13: 0 | N13: 0 | O13: 0 | P13: 0 | Q13: 0 | R13: 0 | S13: 0 | T13: 0
A14: 14 | B14: КЛО_МРЦ70430000 | C14: Валовая прибыль (без бонусов) | D14: Дирекция | E14: 70430000 | F14: ВычетыДоходАгентсДог | G14: 0 | H14: 0 | I14: 0 | J14: 0 | K14: 0 | L14: 0 | M14: 0 | N14: 0 | O14: 0 | P14: 0 | Q14: 0 | R14: 0 | S14: 0 | T14: 0
A15: 15 | E15: 1
A16: 16 | E16: 1 | F16: 2. Себестоимость | G16: -1051234.1 | H16: -4.0635167e-06 | I16: -565293.18 | J16: -233501.53 | K16: -252439.43 | L16: 0 | M16: 0 | N16: 0 | O16: 0 | P16: 0 | Q16: 0 | R16: 0 | S16: 0 | T16: 0
A17: 17 | B17: КЛО_МРЦ90200000 | C17: Валовая прибыль (без бонусов) | D17: КЛО | E17: 90200000 | F17: СебестРеализТоваров | G17: -52537.57 | H17: -7.8532048e-10 | I17: -38423.96 | J17: 0 | K17: -14113.61 | L17: 0 | M17: 0 | N17: 0 | O17: 0 | P17: 0 | Q17: 0 | R17: 0 | S17: 0 | T17: 0
A18: 18 | B18: КЛО_МРЦ90200001 | C18: Валовая прибыль (без бонусов) | D18: КЛО | E18: 90200001 | F18: СебестРеалТоваровПро | G18: -998696.57 | H18: -4.0627314e-06 | I18: -526869.22 | J18: -233501.53 | K18: -238325.82 | L18: 0 | M18: 0 | N18: 0 | O18: 0 | P18: 0 | Q18: 0 | R18: 0 | S18: 0 | T18: 0
A19: 19 | E19: 1
A20: 20 | E20: 1 | F20: 3. Валовая маржа | G20: -306730.27 | H20: 4.7803375e-08 | I20: -143780.86 | J20: -64208.05 | K20: -98741.36 | L20: 0 | M20: 0 | N20: 0 | O20: 0 | P20: 0 | Q20: 0 | R20: 0 | S20: 0 | T20: 0
A21: 21 | E21: 1
A22: 22 | E22: 1 | F22: 4. Бонусы | G22: 0 | H22: 0 | I22: 0 | J22: 0 | K22: 0 | L22: 0 | M22: 0 | N22: 0 | O22: 0 | P22: 0 | Q22: 0 | R22: 0 | S22: 0 | T22: 0
A23: 23 | B23: КЛО_МРЦ71900700 | C23: Бонусы | D23: КЛО | E23: 71900700 | F23: ДоходОтБонусов | G23: 0 | H23: 0 | I23: 0 | J23: 0 | K23: 0 | L23: 0 | M23: 0 | N23: 0 | O23: 0 | P23: 0 | Q23: 0 | R23: 0 | S23: 0 | T23: 0
A24: 24 | E24: 1
A25: 25 | E25: 1 | F25: 5. Прочее - Доходы | G25: 8655505 | H25: 0 | I25: 5581294 | J25: 3072711 | K25: 1500 | L25: 0 | M25: 0 | N25: 0 | O25: 0 | P25: 0 | Q25: 0 | R25: 0 | S25: 0 | T25: 0
A26: 26 | B26: КЛО_МРЦ70300000 | C26: Прочие доходы | D26: МАРКЕТИНГ | E26: 70300000 | F26: ДоходРеалРабУсл | G26: 0 | H26: 0 | I26: 0 | J26: 0 | K26: 0 | L26: 0 | M26: 0 | N26: 0 | O26: 0 | P26: 0 | Q26: 0 | R26: 0 | S26: 0 | T26: 0
A27: 27 | B27: КЛО_МРЦ70300200 | C27: Прочие доходы | D27: МАРКЕТИНГ | E27: 70300200 | F27: ДохРазмРеклСобствНН | G27: 0 | H27: 0 | I27: 0 | J27: 0 | K27: 0 | L27: 0 | M27: 0 | N27: 0 | O27: 0 | P27: 0 | Q27: 0 | R27: 0 | S27: 0 | T27: 0
A28: 28 | B28: КЛО_МРЦ70300700 | C28: Прочие доходы | D28: КЛО | E28: 70300700 | F28: ДохРеалУслЛогист | G28: 0 | H28: 0 | I28: 0 | J28: 0 | K28: 0 | L28: 0 | M28: 0 | N28: 0 | O28: 0 | P28: 0 | Q28: 0 | R28: 0 | S28: 0 | T28: 0
A29: 29 | B29: КЛО_МРЦ70300800 | C29: Прочие доходы | D29: ОПЕРАЦИОННЫЙ | E29: 70300800 | F29: ДоходДогКомиссии | G29: 0 | H29: 0 | I29: 0 | J29: 0 | K29: 0 | L29: 0 | M29: 0 | N29: 0 | O29: 0 | P29: 0 | Q29: 0 | R29: 0 | S29: 0 | T29: 0
A30: 30 | B30: КЛО_МРЦ70300900 | C30: Прочие доходы | D30: ОПЕРАЦИОННЫЙ | E30: 70300900 | F30: ДоходУслугКонечнПотр | G30: 0 | H30: 0 | I30: 0 | J30: 0 | K30: 0 | L30: 0 | M30: 0 | N30: 0 | O30: 0 | P30: 0 | Q30: 0 | R30: 0 | S30: 0 | T30: 0
A31: 31 | B31: КЛО_МРЦ71200000 | C31: Прочие доходы | D31: Дирекция | E31: 71200000 | F31: ДохРеалПрочОбАкт | G31: 0 | H31: 0 | I31: 0 | J31: 0 | K31: 0 | L31: 0 | M31: 0 | N31: 0 | O31: 0 | P31: 0 | Q31: 0 | R31: 0 | S31: 0 | T31: 0
A32: 32 | B32: КЛО_МРЦ71200100 | C32: Прочие доходы | D32: ОПЕРАЦИОННЫЙ+СБ | E32: 71200100 | F32: ДохРеалМакулатуры | G32: 14518 | H32: 2.8409112e-07 | I32: 0 | J32: 14518 | K32: 0 | L32: 0 | M32: 0 | N32: 0 | O32: 0 | P32: 0 | Q32: 0 | R32: 0 | S32: 0 | T32: 0
A33: 33 | B33: КЛО_МРЦ71300000 | C33: Прочие доходы | E33: 71300000 | F33: ДохАренОборудован | G33: 0 | H33: 0 | I33: 0 | J33: 0 | K33: 0 | L33: 0 | M33: 0 | N33: 0 | O33: 0 | P33: 0 | Q33: 0 | R33: 0 | S33: 0 | T33: 0
A34: 34 | B34: КЛО_МРЦ71300200 | C34: Прочие доходы | E34: 71300200 | F34: ДохАренТранспорта | G34: 0 | H34: 0 | I34: 0 | J34: 0 | K34: 0 | L34: 0 | M34: 0 | N34: 0 | O34: 0 | P34: 0 | Q34: 0 | R34: 0 | S34: 0 | T34: 0
A35: 35 | B35: КЛО_МРЦ71500000 | C35: Прочие доходы | D35: КЛО | E35: 71500000 | F35: ПолучШтрафПени | G35: 0 | H35: 0 | I35: 0 | J35: 0 | K35: 0 | L35: 0 | M35: 0 | N35: 0 | O35: 0 | P35: 0 | Q35: 0 | R35: 0 | S35: 0 | T35: 0
A36: 36 | B36: КЛО_МРЦ71500100 | C36: Прочие доходы | E36: 71500100 | F36: ОтримШтрафиПеніКомер | H36: 0
A37: 37 | B37: КЛО_МРЦ71700000 | C37: Прочие доходы | E37: 71700000 | F37: ДохСписКредЗадолж | G37: 0 | H37: 0 | I37: 0 | J37: 0 | K37: 0 | L37: 0 | M37: 0 | N37: 0 | O37: 0 | P37: 0 | Q37: 0 | R37: 0 | S37: 0 | T37: 0
A38: 38 | B38: КЛО_МРЦ71800000 | C38: Прочие доходы | D38: 0 | E38: 71800000 | F38: ДохБесплПолОборАкт | G38: 0 | H38: 0 | I38: 0 | J38: 0 | K38: 0 | L38: 0 | M38: 0 | N38: 0 | O38: 0 | P38: 0 | Q38: 0 | R38: 0 | S38: 0 | T38: 0
A39: 39 | B39: КЛО_МРЦ71800400 | C39: Прочие доходы | E39: 71800400 | F39: ДохБесплПолАктив.РЦ | G39: 0 | H39: 0 | I39: 0 | J39: 0 | K39: 0 | L39: 0 | M39: 0 | N39: 0 | O39: 0 | P39: 0 | Q39: 0 | R39: 0 | S39: 0 | T39: 0
A40: 40 | B40: КЛО_МРЦ71900000 | C40: Прочие доходы | D40: ВСЕ | E40: 71900000 | F40: ПрочДоходОперДеят | G40: 8639487 | H40: 0 | I40: 5581294 | J40: 3058193 | K40: 0 | L40: 0 | M40: 0 | N40: 0 | O40: 0 | P40: 0 | Q40: 0 | R40: 0 | S40: 0 | T40: 0
A41: 41 | B41: КЛО_МРЦ71900100 | C41: Прочие доходы | D41: ФИНАНСОВЫЙ | E41: 71900100 | F41: ПрочДоход% банка | G41: 0 | H41: 0 | I41: 0 | J41: 0 | K41: 0 | L41: 0 | M41: 0 | N41: 0 | O41: 0 | P41: 0 | Q41: 0 | R41: 0 | S41: 0 | T41: 0
A42: 42 | B42: КЛО_МРЦ71900500 | C42: Прочие доходы | D42: ОПЕРАЦИОННЫЙ+СБ | E42: 71900500 | F42: ПрДоходИзлишки кассы | G42: 1500 | H42: 0 | I42: 0 | J42: 0 | K42: 1500 | L42: 0 | M42: 0 | N42: 0 | O42: 0 | P42: 0 | Q42: 0 | R42: 0 | S42: 0 | T42: 0
A43: 43 | B43: КЛО_МРЦ71900600 | C43: Прочие доходы | D43: АДМИН | E43: 71900600 | F43: Доход гостинич услуг | G43: 0 | H43: 0 | I43: 0 | J43: 0 | K43: 0 | L43: 0 | M43: 0 | N43: 0 | O43: 0 | P43: 0 | Q43: 0 | R43: 0 | S43: 0 | T43: 0
A44: 44 | B44: КЛО_МРЦ71900900 | C44: Прочие доходы | E44: 71900900 | F44: ДохідСтраховВідшк | H44: 0
A45: 45 | B45: КЛО_МРЦ71901000 | C45: Прочие доходы | D45: АДМИН | E45: 71901000 | F45: ІнДоход%депозит | G45: 0 | H45: 0 | I45: 0 | J45: 0 | K45: 0 | L45: 0 | M45: 0 | N45: 0 | O45: 0 | P45: 0 | Q45: 0 | R45: 0 | S45: 0 | T45: 0
A46: 46 | C46: Прочие доходы | E46: 1
A47: 47 | E47: 1 | F47: 6. Прочие доходы аренда | G47: 16500 | H47: 4.2991997e-07 | I47: 11000 | J47: 5500 | K47: 0 | L47: 0 | M47: 0 | N47: 0 | O47: 0 | P47: 0 | Q47: 0 | R47: 0 | S47: 0 | T47: 0
A48: 48 | B48: КЛО_МРЦ71300100 | C48: Прочие доходы аренда | D48: АДМИН | E48: 71300100 | F48: ДохАренПомещений | G48: 16500 | H48: 4.2991997e-07 | I48: 11000 | J48: 5500 | K48: 0 | L48: 0 | M48: 0 | N48: 0 | O48: 0 | P48: 0 | Q48: 0 | R48: 0 | S48: 0 | T48: 0
A49: 49 | B49: КЛО_МРЦ71900400 | C49: Прочие доходы аренда | D49: АДМИН | E49: 71900400 | F49: ВозмещКомЭксплЗатрат | G49: 0 | H49: 0 | I49: 0 | J49: 0 | K49: 0 | L49: 0 | M49: 0 | N49: 0 | O49: 0 | P49: 0 | Q49: 0 | R49: 0 | S49: 0 | T49: 0
A50: 50 | E50: 1
A51: 51 | E51: 1 | F51: Валовая прибыль | G51: 8365274.7 | H51: 0.00018491313 | I51: 5448513.1 | J51: 3014003 | K51: -97241.36 | L51: 0 | M51: 0 | N51: 0 | O51: 0 | P51: 0 | Q51: 0 | R51: 0 | S51: 0 | T51: 0
A52: 52 | E52: Затраты
A53: 53 | E53: 1 | F53: 7. Списания и переучеты | G53: -13838025 | H53: -3.8829612e-06 | I53: -7048185.3 | J53: -2700944.2 | K53: -4088895.9 | L53: 0 | M53: 0 | N53: 0 | O53: 0 | P53: 0 | Q53: 0 | R53: 0 | S53: 0 | T53: 0
A54: 54 | B54: КЛО_МРЦ80810000 | C54: Списания и переучеты | D54: КЛО+Опер+СБ | E54: 80810000 | F54: РасхТоварПереуч | G54: 42960.85 | H54: 0 | I54: 28882.42 | J54: 10457.55 | K54: 3620.88 | L54: 0 | M54: 0 | N54: 0 | O54: 0 | P54: 0 | Q54: 0 | R54: 0 | S54: 0 | T54: 0
A55: 55 | B55: КЛО_МРЦ80810001 | C55: Списания и переучеты | D55: КЛО+Опер+СБ | E55: 80810001 | F55: РасхМатПереучетПроиз | G55: -5885466.2 | H55: 0 | I55: -3570757.2 | J55: -1438766.2 | K55: -875942.82 | L55: 0 | M55: 0 | N55: 0 | O55: 0 | P55: 0 | Q55: 0 | R55: 0 | S55: 0 | T55: 0
A56: 56 | B56: КЛО_МРЦ80820000 | C56: Списания и переучеты | D56: КЛО+Опер+СБ | E56: 80820000 | F56: РасхТоварПотериСпис | G56: 17000 | H56: 0 | I56: 17000 | J56: 0 | K56: 0 | L56: 0 | M56: 0 | N56: 0 | O56: 0 | P56: 0 | Q56: 0 | R56: 0 | S56: 0 | T56: 0
A57: 57 | B57: КЛО_МРЦ80820001 | C57: Списания и переучеты | D57: КЛО+Опер+СБ | E57: 80820001 | F57: РасхМатПотПоСписПр | G57: -8012520.1 | H57: 0 | I57: -3523310.5 | J57: -1272635.6 | K57: -3216574 | L57: 0 | M57: 0 | N57: 0 | O57: 0 | P57: 0 | Q57: 0 | R57: 0 | S57: 0 | T57: 0
A58: 58 | E58: 1
A59: 59 | E59: 1 | F59: 8. ФОТ, в т.ч. налоги | G59: -25112520 | H59: -3.8829612e-06 | I59: -20297868 | J59: -9512052.5 | K59: 4697400.8 | L59: 0 | M59: 0 | N59: 0 | O59: 0 | P59: 0 | Q59: 0 | R59: 0 | S59: 0 | T59: 0
A60: 60 | B60: КЛО_МРЦ81100000 | C60: ФОТ, в т.ч. налоги | D60: HR+ВСЕ | E60: 81100000 | F60: РасхОплТрОклады | G60: -21663021 | H60: 0 | I60: -17538894 | J60: -7980865.9 | K60: 3856739 | L60: 0 | M60: 0 | N60: 0 | O60: 0 | P60: 0 | Q60: 0 | R60: 0 | S60: 0 | T60: 0
A61: 61 | B61: КЛО_МРЦ81100100 | C61: ФОТ, в т.ч. налоги | D61: HR+ВСЕ | E61: 81100100 | F61: Оплата Моб,ТРО | G61: -188280 | H61: 0 | I61: -125520 | J61: -62760 | K61: 0 | L61: 0 | M61: 0 | N61: 0 | O61: 0 | P61: 0 | Q61: 0 | R61: 0 | S61: 0 | T61: 0
A62: 62 | B62: КЛО_МРЦ81200000 | C62: ФОТ, в т.ч. налоги | D62: HR+ВСЕ | E62: 81200000 | F62: ПремииПоощрения | G62: 0 | H62: 0 | I62: 0 | J62: 0 | K62: 0 | L62: 0 | M62: 0 | N62: 0 | O62: 0 | P62: 0 | Q62: 0 | R62: 0 | S62: 0 | T62: 0
A63: 63 | B63: КЛО_МРЦ81400000 | C63: ФОТ, в т.ч. налоги | D63: HR+ВСЕ | E63: 81400000 | F63: Оплата отпусков | G63: -897183.55 | H63: 0 | I63: -570341.38 | J63: -326842.17 | K63: 0 | L63: 0 | M63: 0 | N63: 0 | O63: 0 | P63: 0 | Q63: 0 | R63: 0 | S63: 0 | T63: 0
A64: 64 | B64: КЛО_МРЦ81500000 | C64: ФОТ, в т.ч. налоги | D64: HR+ВСЕ | E64: 81500000 | F64: ПрочРасхНаОплТр | G64: 0 | H64: 0 | I64: 0 | J64: 0 | K64: 0 | L64: 0 | M64: 0 | N64: 0 | O64: 0 | P64: 0 | Q64: 0 | R64: 0 | S64: 0 | T64: 0
A65: 65 | B65: КЛО_МРЦ81500100 | C65: ФОТ, в т.ч. налоги | D65: ФИНАНСОВЫЙ | E65: 81500100 | F65: СПД и директорство | G65: 0 | H65: 0 | I65: 0 | J65: 0 | K65: 0 | L65: 0 | M65: 0 | N65: 0 | O65: 0 | P65: 0 | Q65: 0 | R65: 0 | S65: 0 | T65: 0
A66: 66 | B66: КЛО_МРЦ82100000 | C66: ФОТ, в т.ч. налоги | D66: HR+ВСЕ | E66: 82100000 | F66: Налоги на ФОТ | G66: -2364035.7 | H66: 0 | I66: -2063113 | J66: -1141584.5 | K66: 840661.75 | L66: 0 | M66: 0 | N66: 0 | O66: 0 | P66: 0 | Q66: 0 | R66: 0 | S66: 0 | T66: 0
A67: 67 | B67: КЛО_МРЦ84210100 | C67: ФОТ, в т.ч. налоги | D67: HR+ВСЕ | E67: 84210100 | F67: УслЦенБумагИС | G67: 0 | H67: 0 | I67: 0 | J67: 0 | K67: 0 | L67: 0 | M67: 0 | N67: 0 | O67: 0 | P67: 0 | Q67: 0 | R67: 0 | S67: 0 | T67: 0
A68: 68 | E68: 1
A69: 69 | E69: 1 | F69: 9. Персонал | G69: -267157.84 | H69: 0 | I69: -143739.04 | J69: -123418.8 | K69: 0 | L69: 0 | M69: 0 | N69: 0 | O69: 0 | P69: 0 | Q69: 0 | R69: 0 | S69: 0 | T69: 0
A70: 70 | B70: КЛО_МРЦ81300000 | C70: ФОТ, в т.ч. налоги | D70: HR+ВСЕ | E70: 81300000 | F70: КомпенсацВыплаты | G70: 0 | H70: 0 | I70: 0 | J70: 0 | K70: 0 | L70: 0 | M70: 0 | N70: 0 | O70: 0 | P70: 0 | Q70: 0 | R70: 0 | S70: 0 | T70: 0
A71: 71 | B71: КЛО_МРЦ81300100 | C71: ФОТ, в т.ч. налоги | D71: HR+ВСЕ | E71: 81300100 | F71: КомпЗаИспЛичнТр | G71: 0 | H71: 0 | I71: 0 | J71: 0 | K71: 0 | L71: 0 | M71: 0 | N71: 0 | O71: 0 | P71: 0 | Q71: 0 | R71: 0 | S71: 0 | T71: 0
A72: 72 | B72: КЛО_МРЦ81300200 | C72: ФОТ, в т.ч. налоги | D72: HR+ВСЕ | E72: 81300200 | F72: КомпКвартир | G72: 0 | H72: 0 | I72: 0 | J72: 0 | K72: 0 | L72: 0 | M72: 0 | N72: 0 | O72: 0 | P72: 0 | Q72: 0 | R72: 0 | S72: 0 | T72: 0
A73: 73 | B73: КЛО_МРЦ81300300 | C73: ФОТ, в т.ч. налоги | D73: HR+ВСЕ | E73: 81300300 | F73: МатПомощьСотр | G73: 0 | H73: 0 | I73: 0 | J73: 0 | K73: 0 | L73: 0 | M73: 0 | N73: 0 | O73: 0 | P73: 0 | Q73: 0 | R73: 0 | S73: 0 | T73: 0
A74: 74 | B74: КЛО_МРЦ81300400 | C74: ФОТ, в т.ч. налоги | D74: HR+ВСЕ | E74: 81300400 | F74: МатПомНаПогребен | G74: 0 | H74: 0 | I74: 0 | J74: 0 | K74: 0 | L74: 0 | M74: 0 | N74: 0 | O74: 0 | P74: 0 | Q74: 0 | R74: 0 | S74: 0 | T74: 0
A75: 75 | B75: КЛО_МРЦ82400000 | C75: ФОТ, в т.ч. налоги | D75: HR+ВСЕ | E75: 82400000 | F75: ОтчислНаИндивСтрах | G75: 0 | H75: 0 | I75: 0 | J75: 0 | K75: 0 | L75: 0 | M75: 0 | N75: 0 | O75: 0 | P75: 0 | Q75: 0 | R75: 0 | S75: 0 | T75: 0
A76: 76 | B76: КЛО_МРЦ84220100 | C76: Персонал | D76: HR | E76: 84220100 | F76: ПерсоналПоиск | G76: 0 | H76: 0 | I76: 0 | J76: 0 | K76: 0 | L76: 0 | M76: 0 | N76: 0 | O76: 0 | P76: 0 | Q76: 0 | R76: 0 | S76: 0 | T76: 0
A77: 77 | B77: КЛО_МРЦ84220200 | C77: Персонал | D77: HR | E77: 84220200 | F77: ПерсоналОбучВнутр | G77: 0 | H77: 0 | I77: 0 | J77: 0 | K77: 0 | L77: 0 | M77: 0 | N77: 0 | O77: 0 | P77: 0 | Q77: 0 | R77: 0 | S77: 0 | T77: 0
A78: 78 | B78: КЛО_МРЦ84220300 | C78: Персонал | D78: HR | E78: 84220300 | F78: ПерсоналОбучВнешн | G78: 0 | H78: 0 | I78: 0 | J78: 0 | K78: 0 | L78: 0 | M78: 0 | N78: 0 | O78: 0 | P78: 0 | Q78: 0 | R78: 0 | S78: 0 | T78: 0
A79: 79 | B79: КЛО_МРЦ84220400 | C79: Персонал | D79: HR | E79: 84220400 | F79: Персонал медосмотры | G79: -3520 | H79: 0 | I79: -2420 | J79: -1100 | K79: 0 | L79: 0 | M79: 0 | N79: 0 | O79: 0 | P79: 0 | Q79: 0 | R79: 0 | S79: 0 | T79: 0
A80: 80 | B80: КЛО_МРЦ84220500 | C80: Персонал | D80: HR | E80: 84220500 | F80: ПерсоналСтажеры | G80: 0 | H80: 0 | I80: 0 | J80: 0 | K80: 0 | L80: 0 | M80: 0 | N80: 0 | O80: 0 | P80: 0 | Q80: 0 | R80: 0 | S80: 0 | T80: 0
A81: 81 | B81: КЛО_МРЦ84220700 | C81: Персонал | D81: HR | E81: 84220700 | F81: Персонал прочее | G81: -263637.84 | H81: 0 | I81: -141319.04 | J81: -122318.8 | K81: 0 | L81: 0 | M81: 0 | N81: 0 | O81: 0 | P81: 0 | Q81: 0 | R81: 0 | S81: 0 | T81: 0
... A83: 83 | B83: КЛО_МРЦ84220900 | C83: Персонал | D83: HR | E83: 84220900 | F83: ПЕРСОН | G83: 0 | H83: 0 | I83: 0 | J83: 0 | K83: 0 | L83: 0 | M83: 0 | N83: 0 | O83: 0 | P83: 0 | Q83: 0 | R83: 0 | S83: 0 | T83: 0
A84: 84 | E84: 1
A85: 85 | E85: 1 | F85: 10. Аренда помещений | G85: -2630175 | H85: 0 | I85: -1753450 | J85: -876724.99 | K85: 0 | L85: 0 | M85: 0 | N85: 0 | O85: 0 | P85: 0 | Q85: 0 | R85: 0 | S85: 0 | T85: 0
A86: 86 | B86: КЛО_МРЦ84160200 | C86: Аренда помещений | D86: АДМИН | E86: 84160200 | F86: Аренда помещений | G86: -2630175 | H86: 0 | I86: -1753450 | J86: -876724.99 | K86: 0 | L86: 0 | M86: 0 | N86: 0 | O86: 0 | P86: 0 | Q86: 0 | R86: 0 | S86: 0 | T86: 0
A87: 87 | E87: 1
A88: 88 | E88: 1 | F88: 11. Коммунальные услуги | G88: -3905159 | H88: -6.373593e-05 | I88: -2082119.3 | J88: -1823039.7 | K88: 0 | L88: 0 | M88: 0 | N88: 0 | O88: 0 | P88: 0 | Q88: 0 | R88: 0 | S88: 0 | T88: 0
A89: 89 | B89: КЛО_МРЦ84030100 | C89: Коммунальные услуги | D89: АДМИН+Опер | E89: 84030100 | F89: КомУслВода | G89: 0 | H89: 0 | I89: 0 | J89: 0 | K89: 0 | L89: 0 | M89: 0 | N89: 0 | O89: 0 | P89: 0 | Q89: 0 | R89: 0 | S89: 0 | T89: 0
A90: 90 | B90: КЛО_МРЦ84030200 | C90: Коммунальные услуги | D90: АДМИН+Опер | E90: 84030200 | F90: КомУслВывОтходМус | G90: -50622 | H90: -1.4462436e-06 | I90: -35046 | J90: -15576 | K90: 0 | L90: 0 | M90: 0 | N90: 0 | O90: 0 | P90: 0 | Q90: 0 | R90: 0 | S90: 0 | T90: 0
A91: 91 | B91: КЛО_МРЦ84030300 | C91: Коммунальные услуги | D91: АДМИН+Опер | E91: 84030300 | F91: КомУслГаз | G91: 0 | H91: 0 | I91: 0 | J91: 0 | K91: 0 | L91: 0 | M91: 0 | N91: 0 | O91: 0 | P91: 0 | Q91: 0 | R91: 0 | S91: 0 | T91: 0
A92: 92 | B92: КЛО_МРЦ84030400 | C92: Коммунальные услуги | D92: АДМИН+Опер | E92: 84030400 | F92: КомУслОтопление | G92: 0 | H92: -4.3387308e-06 | I92: 0 | J92: 0 | K92: 0 | L92: 0 | M92: 0 | N92: 0 | O92: 0 | P92: 0 | Q92: 0 | R92: 0 | S92: 0 | T92: 0
A93: 93 | B93: КЛО_МРЦ84030500 | C93: Коммунальные услуги | D93: АДМИН+Опер | E93: 84030500 | F93: КомУслЭлектроэн | G93: -2142446.9 | H93: -5.7849745e-06 | I93: -1117152.9 | J93: -1025294 | K93: 0 | L93: 0 | M93: 0 | N93: 0 | O93: 0 | P93: 0 | Q93: 0 | R93: 0 | S93: 0 | T93: 0
A94: 94 | B94: КЛО_МРЦ84030600 | C94: Коммунальные услуги | D94: АДМИН+Опер | E94: 84030600 | F94: ЭксплуатПрочиеКомун | G94: -69732.07 | H94: -7.2312181e-06 | I94: -35821.38 | J94: -33910.69 | K94: 0 | L94: 0 | M94: 0 | N94: 0 | O94: 0 | P94: 0 | Q94: 0 | R94: 0 | S94: 0 | T94: 0
A95: 95 | B95: КЛО_МРЦ84030800 | C95: Коммунальные услуги | D95: АДМИН+Опер | E95: 84030800 | F95: КомУслЭлВозмещГенер. | G95: 0 | H95: -8.6774617e-06 | I95: 0 | J95: 0 | K95: 0 | L95: 0 | M95: 0 | N95: 0 | O95: 0 | P95: 0 | Q95: 0 | R95: 0 | S95: 0 | T95: 0
A96: 96 | B96: КЛО_МРЦ80300100 | C96: Коммунальные услуги | D96: АДМИН+Опер | E96: 80300100 | F96: РасхГСМ Тех.ИПр.нужд | G96: -1642358.1 | H96: -1.0123705e-05 | I96: -894099.06 | J96: -748258.99 | K96: 0 | L96: 0 | M96: 0 | N96: 0 | O96: 0 | P96: 0 | Q96: 0 | R96: 0 | S96: 0 | T96: 0
A97: 97 | E97: 1
A98: 98 | E98: 1 | F98: 12. Логистика | G98: -2094127.2 | H98: -4.8480906e-06 | I98: -107159.53 | J98: -13356.05 | K98: -1973611.7 | L98: 0 | M98: 0 | N98: 0 | O98: 0 | P98: 0 | Q98: 0 | R98: 0 | S98: 0 | T98: 0
A99: 99 | B99: КЛО_МРЦ84020100 | C99: Логистика | D99: КЛО | E99: 84020100 | F99: Транспортные услуги | G99: -2068560.1 | H99: -4.3075533e-06 | I99: -90321.65 | J99: -4626.84 | K99: -1973611.7 | L99: 0 | M99: 0 | N99: 0 | O99: 0 | P99: 0 | Q99: 0 | R99: 0 | S99: 0 | T99: 0
A100: 100 | B100: КЛО_МРЦ84020200 | C100: Логистика | D100: КЛО | E100: 84020200 | F100: Логистика | G100: 0 | H100: 0 | I100: 0 | J100: 0 | K100: 0 | L100: 0 | M100: 0 | N100: 0 | O100: 0 | P100: 0 | Q100: 0 | R100: 0 | S100: 0 | T100: 0
A101: 101 | B101: КЛО_МРЦ84020300 | C101: Логистика | D101: КЛО | E101: 84020300 | F101: ПрочУслСкладХоз | G101: -25567.09 | H101: -5.4053723e-07 | I101: -16837.88 | J101: -8729.21 | K101: 0 | L101: 0 | M101: 0 | N101: 0 | O101: 0 | P101: 0 | Q101: 0 | R101: 0 | S101: 0 | T101: 0
...

Sheet березень
